Workbook

Sheet INSTRUCCIONES
A1: Plantilla simple de importación — Vacaciones Carrier
A3: Regla | B3: Descripción | D3: Color | E3: Uso
A4: No captures NSS | B4: La app hará match por nombre completo normalizado contra Headcount. | D4: Amarillo | E4: Obligatorio/recomendado.
A5: Días utilizados total | B5: Total usado: días disfrutados + vacaciones laboradas. | D5: Azul | E5: Opcional/histórico.
A6: Vacaciones laboradas incluidas | B6: Subconjunto de días utilizados. NO se suma otra vez. | D6: Verde | E6: Prima o dato recomendado.
A7: Días pagados/laboradas | B7: Días de vacaciones laboradas pagadas/tomadas. | D7: Gris | E7: Automático o para uso de la app.
A8: Saldo negativo | B8: Válido: vacaciones tomadas/pagadas de más. | D8: Naranja | E8: Revisión o advertencia.
A9: Prima pagada | B9: Histórico actual: sueldo diario × 3. Sirve para evitar pagos dobles.
A10: Fecha de ingreso | B10: Captura la del Excel si existe; la app priorizará Headcount.
A11: Sueldo diario histórico | B11: Respaldo histórico; la app priorizará Parámetros de Nómina > Headcount > Excel.
A12: Periodos | B12: Usa 2_MOVIMIENTOS para conservar semanas/periodos cuando aplique.
A13: Comentarios | B13: No borres reingresos, ajustes, primas dobles ni casos especiales.

Sheet 1_CAPTURA_SALDOS
A1: Nombre completo | B1: Fecha ingreso Excel | C1: Sueldo diario histórico | D1: Planta histórica | E1: Días utilizados total | F1: Vacaciones laboradas incluidas | G1: Días pagados/laboradas | H1: Días restantes histórico | I1: Prima 2025 pagada | J1: Semana/fecha pago prima 2025 | K1: Prima 2026 pagada | L1: Fecha pago prima 2026 | M1: Monto total histórico | N1: Comentarios | O1: APP: suma movimientos | P1: APP: diferencia | Q1: APP: clasificación | R1: APP: revisión manual
A2: Ejemplo: JUAN PEREZ LOPEZ | B2: 2024-01-15 | C2: 350 | D2: APODACA | E2: 12 | F2: 2 | G2: 2 | H2: 0 | I2: SI | J2: SEM 10 2025 | K2: NO | M2: 4200 | N2: Ejemplo. Borrar antes de importar. | O2: =IF($A2="","",IFERROR(SUMIFS('2_MOVIMIENTOS'!$F$2:$F$501,'2_MOVIMIENTOS'!$A$2:$A$501,$A2),0)) -> 3 | P2: =IF($A2="","",IF(OR($E2="", $O2=""),"",ROUND($E2-$O2,2))) -> 9 | Q2: =IF($A2="","",IF($E2="","SIN_DIAS_UTILIZADOS",IF($O2=0,"SIN_DESGLOSE",IF(ROUND($E2-$O2,2)=0,"CONCILIADO",IF(AND($F2<>"",ROUND($E2-$O2-$F2,2)=0),"LABORADAS_POSIBLEMENTE_FUERA_DESGLOSE",IF($O2>$E2,"POSIBLE_EXCESO_EN_MOVIMIENTOS","DIFERENCIA_A_REVISAR")))))) -> DIFERENCIA_A_REVISAR | R2: =IF($A2="","",IF(OR($H2<0,$Q2<>"CONCILIADO",ISNUMBER(SEARCH("reingreso",LOWER($N2))),ISNUMBER(SEARCH("ajuste",LOWER($N2)))),"SI","NO")) -> SI
O3: =IF($A3="","",IFERROR(SUMIFS('2_MOVIMIENTOS'!$F$2:$F$501,'2_MOVIMIENTOS'!$A$2:$A$501,$A3),0)) | P3: =IF($A3="","",IF(OR($E3="", $O3=""),"",ROUND($E3-$O3,2))) | Q3: =IF($A3="","",IF($E3="","SIN_DIAS_UTILIZADOS",IF($O3=0,"SIN_DESGLOSE",IF(ROUND($E3-$O3,2)=0,"CONCILIADO",IF(AND($F3<>"",ROUND($E3-$O3-$F3,2)=0),"LABORADAS_POSIBLEMENTE_FUERA_DESGLOSE",IF($O3>$E3,"POSIBLE_EXCESO_EN_MOVIMIENTOS","DIFERENCIA_A_REVISAR")))))) | R3: =IF($A3="","",IF(OR($H3<0,$Q3<>"CONCILIADO",ISNUMBER(SEARCH("reingreso",LOWER($N3))),ISNUMBER(SEARCH("ajuste",LOWER($N3)))),"SI","NO"))
O4: =IF($A4="","",IFERROR(SUMIFS('2_MOVIMIENTOS'!$F$2:$F$501,'2_MOVIMIENTOS'!$A$2:$A$501,$A4),0)) | P4: =IF($A4="","",IF(OR($E4="", $O4=""),"",ROUND($E4-$O4,2))) | Q4: =IF($A4="","",IF($E4="","SIN_DIAS_UTILIZADOS",IF($O4=0,"SIN_DESGLOSE",IF(ROUND($E4-$O4,2)=0,"CONCILIADO",IF(AND($F4<>"",ROUND($E4-$O4-$F4,2)=0),"LABORADAS_POSIBLEMENTE_FUERA_DESGLOSE",IF($O4>$E4,"POSIBLE_EXCESO_EN_MOVIMIENTOS","DIFERENCIA_A_REVISAR")))))) | R4: =IF($A4="","",IF(OR($H4<0,$Q4<>"CONCILIADO",ISNUMBER(SEARCH("reingreso",LOWER($N4))),ISNUMBER(SEARCH("ajuste",LOWER($N4)))),"SI","NO"))
O5: =IF($A5="","",IFERROR(SUMIFS('2_MOVIMIENTOS'!$F$2:$F$501,'2_MOVIMIENTOS'!$A$2:$A$501,$A5),0)) | P5: =IF($A5="","",IF(OR($E5="", $O5=""),"",ROUND($E5-$O5,2))) | Q5: =IF($A5="","",IF($E5="","SIN_DIAS_UTILIZADOS",IF($O5=0,"SIN_DESGLOSE",IF(ROUND($E5-$O5,2)=0,"CONCILIADO",IF(AND($F5<>"",ROUND($E5-$O5-$F5,2)=0),"LABORADAS_POSIBLEMENTE_FUERA_DESGLOSE",IF($O5>$E5,"POSIBLE_EXCESO_EN_MOVIMIENTOS","DIFERENCIA_A_REVISAR")))))) | R5: =IF($A5="","",IF(OR($H5<0,$Q5<>"CONCILIADO",ISNUMBER(SEARCH("reingreso",LOWER($N5))),ISNUMBER(SEARCH("ajuste",LOWER($N5)))),"SI","NO"))
O6: =IF($A6="","",IFERROR(SUMIFS('2_MOVIMIENTOS'!$F$2:$F$501,'2_MOVIMIENTOS'!$A$2:$A$501,$A6),0)) | P6: =IF($A6="","",IF(OR($E6="", $O6=""),"",ROUND($E6-$O6,2))) | Q6: =IF($A6="","",IF($E6="","SIN_DIAS_UTILIZADOS",IF($O6=0,"SIN_DESGLOSE",IF(ROUND($E6-$O6,2)=0,"CONCILIADO",IF(AND($F6<>"",ROUND($E6-$O6-$F6,2)=0),"LABORADAS_POSIBLEMENTE_FUERA_DESGLOSE",IF($O6>$E6,"POSIBLE_EXCESO_EN_MOVIMIENTOS","DIFERENCIA_A_REVISAR")))))) | R6: =IF($A6="","",IF(OR($H6<0,$Q6<>"CONCILIADO",ISNUMBER(SEARCH("reingreso",LOWER($N6))),ISNUMBER(SEARCH("ajuste",LOWER($N6)))),"SI","NO"))
O7: =IF($A7="","",IFERROR(SUMIFS('2_MOVIMIENTOS'!$F$2:$F$501,'2_MOVIMIENTOS'!$A$2:$A$501,$A7),0)) | P7: =IF($A7="","",IF(OR($E7="", $O7=""),"",ROUND($E7-$O7,2))) | Q7: =IF($A7="","",IF($E7="","SIN_DIAS_UTILIZADOS",IF($O7=0,"SIN_DESGLOSE",IF(ROUND($E7-$O7,2)=0,"CONCILIADO",IF(AND($F7<>"",ROUND($E7-$O7-$F7,2)=0),"LABORADAS_POSIBLEMENTE_FUERA_DESGLOSE",IF($O7>$E7,"POSIBLE_EXCESO_EN_MOVIMIENTOS","DIFERENCIA_A_REVISAR")))))) | R7: =IF($A7="","",IF(OR($H7<0,$Q7<>"CONCILIADO",ISNUMBER(SEARCH("reingreso",LOWER($N7))),ISNUMBER(SEARCH("ajuste",LOWER($N7)))),"SI","NO"))
O8: =IF($A8="","",IFERROR(SUMIFS('2_MOVIMIENTOS'!$F$2:$F$501,'2_MOVIMIENTOS'!$A$2:$A$501,$A8),0)) | P8: =IF($A8="","",IF(OR($E8="", $O8=""),"",ROUND($E8-$O8,2))) | Q8: =IF($A8="","",IF($E8="","SIN_DIAS_UTILIZADOS",IF($O8=0,"SIN_DESGLOSE",IF(ROUND($E8-$O8,2)=0,"CONCILIADO",IF(AND($F8<>"",ROUND($E8-$O8-$F8,2)=0),"LABORADAS_POSIBLEMENTE_FUERA_DESGLOSE",IF($O8>$E8,"POSIBLE_EXCESO_EN_MOVIMIENTOS","DIFERENCIA_A_REVISAR")))))) | R8: =IF($A8="","",IF(OR($H8<0,$Q8<>"CONCILIADO",ISNUMBER(SEARCH("reingreso",LOWER($N8))),ISNUMBER(SEARCH("ajuste",LOWER($N8)))),"SI","NO"))
O9: =IF($A9="","",IFERROR(SUMIFS('2_MOVIMIENTOS'!$F$2:$F$501,'2_MOVIMIENTOS'!$A$2:$A$501,$A9),0)) | P9: =IF($A9="","",IF(OR($E9="", $O9=""),"",ROUND($E9-$O9,2))) | Q9: =IF($A9="","",IF($E9="","SIN_DIAS_UTILIZADOS",IF($O9=0,"SIN_DESGLOSE",IF(ROUND($E9-$O9,2)=0,"CONCILIADO",IF(AND($F9<>"",ROUND($E9-$O9-$F9,2)=0),"LABORADAS_POSIBLEMENTE_FUERA_DESGLOSE",IF($O9>$E9,"POSIBLE_EXCESO_EN_MOVIMIENTOS","DIFERENCIA_A_REVISAR")))))) | R9: =IF($A9="","",IF(OR($H9<0,$Q9<>"CONCILIADO",ISNUMBER(SEARCH("reingreso",LOWER($N9))),ISNUMBER(SEARCH("ajuste",LOWER($N9)))),"SI","NO"))
O10: =IF($A10="","",IFERROR(SUMIFS('2_MOVIMIENTOS'!$F$2:$F$501,'2_MOVIMIENTOS'!$A$2:$A$501,$A10),0)) | P10: =IF($A10="","",IF(OR($E10="", $O10=""),"",ROUND($E10-$O10,2))) | Q10: =IF($A10="","",IF($E10="","SIN_DIAS_UTILIZADOS",IF($O10=0,"SIN_DESGLOSE",IF(ROUND($E10-$O10,2)=0,"CONCILIADO",IF(AND($F10<>"",ROUND($E10-$O10-$F10,2)=0),"LABORADAS_POSIBLEMENTE_FUERA_DESGLOSE",IF($O10>$E10,"POSIBLE_EXCESO_EN_MOVIMIENTOS","DIFERENCIA_A_REVISAR")))))) | R10: =IF($A10="","",IF(OR($H10<0,$Q10<>"CONCILIADO",ISNUMBER(SEARCH("reingreso",LOWER($N10))),ISNUMBER(SEARCH("ajuste",LOWER($N10)))),"SI","NO"))
O11: =IF($A11="","",IFERROR(SUMIFS('2_MOVIMIENTOS'!$F$2:$F$501,'2_MOVIMIENTOS'!$A$2:$A$501,$A11),0)) | P11: =IF($A11="","",IF(OR($E11="", $O11=""),"",ROUND($E11-$O11,2))) | Q11: =IF($A11="","",IF($E11="","SIN_DIAS_UTILIZADOS",IF($O11=0,"SIN_DESGLOSE",IF(ROUND($E11-$O11,2)=0,"CONCILIADO",IF(AND($F11<>"",ROUND($E11-$O11-$F11,2)=0),"LABORADAS_POSIBLEMENTE_FUERA_DESGLOSE",IF($O11>$E11,"POSIBLE_EXCESO_EN_MOVIMIENTOS","DIFERENCIA_A_REVISAR")))))) | R11: =IF($A11="","",IF(OR($H11<0,$Q11<>"CONCILIADO",ISNUMBER(SEARCH("reingreso",LOWER($N11))),ISNUMBER(SEARCH("ajuste",LOWER($N11)))),"SI","NO"))
O12: =IF($A12="","",IFERROR(SUMIFS('2_MOVIMIENTOS'!$F$2:$F$501,'2_MOVIMIENTOS'!$A$2:$A$501,$A12),0)) | P12: =IF($A12="","",IF(OR($E12="", $O12=""),"",ROUND($E12-$O12,2))) | Q12: =IF($A12="","",IF($E12="","SIN_DIAS_UTILIZADOS",IF($O12=0,"SIN_DESGLOSE",IF(ROUND($E12-$O12,2)=0,"CONCILIADO",IF(AND($F12<>"",ROUND($E12-$O12-$F12,2)=0),"LABORADAS_POSIBLEMENTE_FUERA_DESGLOSE",IF($O12>$E12,"POSIBLE_EXCESO_EN_MOVIMIENTOS","DIFERENCIA_A_REVISAR")))))) | R12: =IF($A12="","",IF(OR($H12<0,$Q12<>"CONCILIADO",ISNUMBER(SEARCH("reingreso",LOWER($N12))),ISNUMBER(SEARCH("ajuste",LOWER($N12)))),"SI","NO"))
O13: =IF($A13="","",IFERROR(SUMIFS('2_MOVIMIENTOS'!$F$2:$F$501,'2_MOVIMIENTOS'!$A$2:$A$501,$A13),0)) | P13: =IF($A13="","",IF(OR($E13="", $O13=""),"",ROUND($E13-$O13,2))) | Q13: =IF($A13="","",IF($E13="","SIN_DIAS_UTILIZADOS",IF($O13=0,"SIN_DESGLOSE",IF(ROUND($E13-$O13,2)=0,"CONCILIADO",IF(AND($F13<>"",ROUND($E13-$O13-$F13,2)=0),"LABORADAS_POSIBLEMENTE_FUERA_DESGLOSE",IF($O13>$E13,"POSIBLE_EXCESO_EN_MOVIMIENTOS","DIFERENCIA_A_REVISAR")))))) | R13: =IF($A13="","",IF(OR($H13<0,$Q13<>"CONCILIADO",ISNUMBER(SEARCH("reingreso",LOWER($N13))),ISNUMBER(SEARCH("ajuste",LOWER($N13)))),"SI","NO"))
O14: =IF($A14="","",IFERROR(SUMIFS('2_MOVIMIENTOS'!$F$2:$F$501,'2_MOVIMIENTOS'!$A$2:$A$501,$A14),0)) | P14: =IF($A14="","",IF(OR($E14="", $O14=""),"",ROUND($E14-$O14,2))) | Q14: =IF($A14="","",IF($E14="","SIN_DIAS_UTILIZADOS",IF($O14=0,"SIN_DESGLOSE",IF(ROUND($E14-$O14,2)=0,"CONCILIADO",IF(AND($F14<>"",ROUND($E14-$O14-$F14,2)=0),"LABORADAS_POSIBLEMENTE_FUERA_DESGLOSE",IF($O14>$E14,"POSIBLE_EXCESO_EN_MOVIMIENTOS","DIFERENCIA_A_REVISAR")))))) | R14: =IF($A14="","",IF(OR($H14<0,$Q14<>"CONCILIADO",ISNUMBER(SEARCH("reingreso",LOWER($N14))),ISNUMBER(SEARCH("ajuste",LOWER($N14)))),"SI","NO"))
... O251: =IF($A251="","",IFERROR(SUMIFS('2_MOVIMIENTOS'!$F$2:$F$501,'2_MOVIMIENTOS'!$A$2:$A$501,$A251),0)) | P251: =IF($A251="","",IF(OR($E251="", $O251=""),"",ROUND($E251-$O251,2))) | Q251: =IF($A251="","",IF($E251="","SIN_DIAS_UTILIZADOS",IF($O251=0,"SIN_DESGLOSE",IF(ROUND($E251-$O251,2)=0,"CONCILIADO",IF(AND($F251<>"",ROUND($E251-$O251-$F251,2)=0),"LABORADAS_POSIBLEMENTE_FUERA_DESGLOSE",IF($O251>$E251,"POSIBLE_EXCESO_EN_MOVIMIENTOS","DIFERENCIA_A_REVISAR")))))) | R251: =IF($A251="","",IF(OR($H251<0,$Q251<>"CONCILIADO",ISNUMBER(SEARCH("reingreso",LOWER($N251))),ISNUMBER(SEARCH("ajuste",LOWER($N251)))),"SI","NO"))

Sheet 2_MOVIMIENTOS
A1: Nombre completo | B1: Año | C1: Semana/periodo original | D1: Fecha inicio opcional | E1: Fecha fin opcional | F1: Días capturados | G1: Tipo movimiento | H1: ¿Vacación laborada? | I1: Comentarios
A2: Ejemplo: JUAN PEREZ LOPEZ | B2: 2026 | C2: SEM 03 2026 | F2: 3 | G2: VACACIONES_DISFRUTADAS | H2: NO | I2: Ejemplo. Borrar antes de importar.

Sheet 3_PRIMA_VACACIONAL
A1: Nombre completo | B1: Año prima | C1: Prima pagada | D1: Sueldo diario base histórico | E1: Monto histórico sugerido | F1: Monto pagado real | G1: Semana/fecha de pago | H1: Comentarios
A2: Ejemplo: JUAN PEREZ LOPEZ | B2: 2025 | C2: SI | D2: 350 | E2: sueldo diario × 3 | G2: SEM 10 2025 | H2: Ejemplo. Borrar antes de importar.

Sheet EJEMPLOS
A1: Ejemplos de captura correcta
A3: Caso | B3: Cómo capturarlo | C3: Por qué
A4: Vacaciones normales | B4: Días utilizados = 6; movimientos suman 6; laboradas = 0 | C4: Conciliado.
A5: Laboradas ya incluidas | B5: Días utilizados = 12; vacaciones laboradas = 2; movimientos suman 12 | C5: No se suma doble.
A6: Laboradas fuera del desglose | B6: Días utilizados = 12; vacaciones laboradas = 2; movimientos suman 10 | C6: La app lo manda a revisión sin duplicar.
A7: Saldo negativo | B7: Días restantes = -2 | C7: Válido: pagadas/tomadas de más.
A8: Prima pagada | B8: Prima pagada = SI; sueldo diario = 350; sugerido = 1050 | C8: Histórico sueldo diario × 3.
A9: Comentario clave | B9: Registrar reingreso, ajuste o prima doble | C9: Ayuda a auditoría.

Sheet CATALOGOS
A1: Catálogo | B1: Valor | C1: Descripción
A2: SI_NO | B2: SI | C2: Sí / verdadero
A3: SI_NO | B3: NO | C3: No / falso
A4: TIPO_MOVIMIENTO | B4: VACACIONES_DISFRUTADAS | C4: Días descansados de vacaciones
A5: TIPO_MOVIMIENTO | B5: VACACIONES_LABORADAS | C5: Días de vacaciones laboradas/pagadas
A6: TIPO_MOVIMIENTO | B6: AJUSTE_HISTORICO | C6: Ajuste manual o diferencia histórica
A7: TIPO_MOVIMIENTO | B7: SIN_CLASIFICAR | C7: Usar solo si no se puede clasificar
