Workbook
Name meta_coordinador: Asistencia!$G$2
Name meta_nomina: Asistencia!$D$2
Name meta_semana: Asistencia!$B$2

Sheet Instrucciones
B1: PROCLEAN · ASISTENCIA NÓMINA MIÉRCOLES v3 · CAPTURA POR CLIENTE / TURNO
B3: 1. CLAVES DE ASISTENCIA DIARIA
B4: CLAVE | C4: SIGNIFICADO | D4: CUÁNDO USAR | F4: COLOR
B5: A | C5: Asistencia | D5: El empleado trabajó su turno normal | F5: Verde
B6: D | C6: Descanso programado | D6: Día de descanso según horario | F6: Azul
B7: F | C7: Falta | D7: Ausencia injustificada | F7: Rojo
B8: V | C8: Vacaciones | D8: Días de vacaciones disfrutadas | F8: Amarillo
B9: I | C9: Incapacidad IMSS | D9: Baja médica con folio IMSS | F9: Gris
B10: PSS | C10: Permiso sin goce de sueldo | D10: Permiso autorizado sin pago | F10: Rojo
B11: PCS | C11: Permiso con goce de sueldo | D11: Permiso autorizado con pago | F11: Rojo
B12: NI | C12: Nuevo ingreso | D12: Primera semana del empleado nuevo | F12: Gris
B13: B | C13: Baja | D13: El empleado causó baja definitiva | F13: Rojo
B14: R | C14: Retardo | D14: Llegó tarde pero trabajó | F14: Amarillo
B15: S | C15: Suspensión | D15: Suspensión disciplinaria | F15: Rojo
... B19: OT | C19: Otro / Revisar | D19: Caso especial – explicar en Observaciones | F19: Morado
B21: 2. COLUMNAS DE INCIDENCIAS OPERATIVAS
B22: COLUMNA | C22: QUÉ CAPTURA | D22: TIPO DE DATO | E22: EJEMPLO | F22: NOTAS
B23: HE | C23: Horas extra trabajadas | D23: Número ≥ 0 | E23: 3 / 4.5 / 8 | F23: No capturar monto
B24: TURNOS EXTRA NORMALES | C24: Horas trabajadas en turno extra | D24: Número ≥ 0 | E24: 8 / 16 | F24: Si trabajó turno completo = 8hrs
B25: DÍAS CUBIERTOS NORMALES | C25: Días extra cubiertos | D25: Número ≥ 0 | E25: 1 / 2 | F25: Para extras que se miden por día
B26: FESTIVO LABORADO | C26: Días festivos trabajados | D26: Número ≥ 0 | E26: 1 | F26: También marcar FL en el día
B27: DOMINGO LABORADO | C27: Domingos trabajados | D27: Número ≥ 0 | E27: 1 | F27: También marcar DL en el día
B28: VACACIONES LABORADAS | C28: Vacaciones que se piden como laboradas | D28: Número ≥ 0 | E28: 1 / 2 | F28: NO para vacaciones disfrutadas (esas van como V)
B29: PRIMA VACACIONAL | C29: Solicitud de prima vacacional | D29: N/A o SOLICITA | E29: SOLICITA | F29: N/A por default. Nómina verificará en la app.
B30: BONO | C30: Bono o apoyo especial | D30: Número o texto | E30: 300 / 'revisar bono' | F30: Monto preliminar sujeto a revisión de Nómina
B31: DEDUCCIONES | C31: Descuentos o deducciones | D31: Número o texto | E31: 150 / 'préstamo' | F31: No calcular en Excel. Nómina valida en app.
B32: OBSERVACIONES | C32: Notas o aclaraciones libres | D32: Texto | E32: 'Falta sin aviso' | F32: Obligatorio si usa clave OT
B34: 3. INSTRUCCIONES DE LLENADO
B35: REGLA DE ORO: Este archivo solo captura asistencia e incidencias operativas. NUNCA capturar importes de nómina.
B36: Días de la semana | C36: Captura UNA clave por día. Usa solo las claves del catálogo. Si el caso es raro, usa OT y explica en Observaciones.
B37: Incidencias | C37: Las columnas de incidencias registran cantidades o datos adicionales. No capturan sueldo ni cálculo.
B38: No modificar | C38: No cambiar encabezados de columnas. No inventar claves. No agregar hojas.
B39: Flujo del archivo | C39: 1) Descarga desde ProClean-App 2) Llena asistencia e incidencias 3) Sube a ProClean-App 4) Nómina revisa y aprueba en web.
B40: Caso no contemplado | C40: Usa OT en el día y escribe la situación en la columna OBSERVACIONES para que Nómina la revise.
B42: 4. EJEMPLOS PRÁCTICOS DE LLENADO
B43: Ej 1 – Semana normal | C43: Días: A, A, D, A, A, A, A | Incidencias: todas vacías
B44: Ej 2 – Falta | C44: Día correspondiente: F | Observaciones: opcional
B45: Ej 3 – Permiso sin goce | C45: Día: PSS
B46: Ej 4 – Permiso con goce | C46: Día: PCS
B47: Ej 5 – Vacaciones | C47: Días correspondientes: V, V, V…
B48: Ej 6 – Incapacidad | C48: Días correspondientes: I, I, I…
B49: Ej 7 – Domingo laborado | C49: Día domingo: DL | DOMINGO LABORADO: 1
B50: Ej 8 – Festivo laborado | C50: Día festivo: FL | FESTIVO LABORADO: 1
B51: Ej 9 – 3 horas extra | C51: Día: A | HE: 3
B52: Ej 10 – Turno extra 8h | C52: Día: A | TURNOS EXTRA NORMALES: 8
B53: Ej 11 – Cubre 1 día extra | C53: DÍAS CUBIERTOS NORMALES: 1
B54: Ej 12 – Prima vacacional | C54: PRIMA VACACIONAL: SOLICITA
... B56: Ej 14 – Deducción | C56: DEDUCCIONES: 150 o DEDUCCIONES: 'revisar préstamo'
B58: 5. HOJA ASISTENCIA — INSTRUCCIONES
B59: Captura por cliente | C59: Llena la sección del cliente donde laboró el trabajador esa semana. Si trabajó en dos clientes, captúralo en ambas secciones.
B60: Columna TURNO | C60: Indica el turno: DÍA / TARDE / NOCHE / MIXTO / OTRO. Usa la lista desplegable. Si una persona trabaja dos turnos distintos el mismo día en clientes diferentes, captura el turno correspondiente en cada sección.
B61: Mismo día, dos clientes | C61: Captura normalmente en cada sección. El Compilado detectará el evento adicional y lo registrará en OBSERVACIONES.
B62: No capturar en Asistencia | C62: No anotes banco, cuenta, NSS ni importes de nómina. Solo asistencia e incidencias.
B63: 6. HOJA COMPILADO — INSTRUCCIONES
B64: Una fila por trabajador | C64: El Compilado consolida aunque la persona aparezca en varios clientes. Escribe el nombre igual en todas las secciones.
B65: CLIENTES / TURNOS | C65: Se llena automáticamente. Ejemplo: ARMIDA-DÍA / GM-NOCHE. Si no hay turno capturado, muestra solo el cliente.
B66: Columnas amarillas | C66: BANCO, CUENTA, VACACIONES LABORADAS, PRIMA VACACIONAL y DEDUCCIONES son de captura manual (Nómina). El resto es automático.
B67: OBSERVACIONES | C67: Concentra alertas automáticas: más de 6 días, doble evento mismo día, FL/DL múltiple. No hay columna de Estatus separada.

Sheet Asistencia
A1: PROCLEAN
A2: SEMANA: | B2: NOMINA: | C2: MIÉRCOLES | E2: COORDINADOR:
A4: CLIENTE: ARMIDA
A5: NOMBRE DE EMPLEADO | B5: CLIENTE | C5: PLANTA | D5: TURNO | E5: PUESTO | F5: V1 | G5: S2 | H5: D3 | I5: L4 | J5: M5 | K5: M6 | L5: J7 | M5: HORAS EXTRA | N5: HORAS EXTRA NORMALES | O5: DÍAS CUBIERTOS NORMALES | P5: BONO | Q5: OBSERVACIONES
B6: ARMIDA
B7: ARMIDA
B8: ARMIDA
B9: ARMIDA
B10: ARMIDA
B11: ARMIDA
B12: ARMIDA
B13: ARMIDA
B14: ARMIDA
B15: ARMIDA
B16: ARMIDA
B17: ARMIDA
... B45: ARMIDA
A46: CLIENTE: AURIGA
A47: NOMBRE DE EMPLEADO | B47: CLIENTE | C47: PLANTA | D47: TURNO | E47: PUESTO | F47: V1 | G47: S2 | H47: D3 | I47: L4 | J47: M5 | K47: M6 | L47: J7 | M47: HORAS EXTRA | N47: HORAS EXTRA NORMALES | O47: DÍAS CUBIERTOS NORMALES | P47: BONO | Q47: OBSERVACIONES
B48: AURIGA
B49: AURIGA
B50: AURIGA
B51: AURIGA
B52: AURIGA
B53: AURIGA
B54: AURIGA
B55: AURIGA
B56: AURIGA
B57: AURIGA
B58: AURIGA
B59: AURIGA
... B87: AURIGA
A88: CLIENTE: AURORA
A89: NOMBRE DE EMPLEADO | B89: CLIENTE | C89: PLANTA | D89: TURNO | E89: PUESTO | F89: V1 | G89: S2 | H89: D3 | I89: L4 | J89: M5 | K89: M6 | L89: J7 | M89: HORAS EXTRA | N89: HORAS EXTRA NORMALES | O89: DÍAS CUBIERTOS NORMALES | P89: BONO | Q89: OBSERVACIONES
B90: AURORA
B91: AURORA
B92: AURORA
B93: AURORA
B94: AURORA
B95: AURORA
B96: AURORA
B97: AURORA
B98: AURORA
B99: AURORA
B100: AURORA
B101: AURORA
... B129: AURORA
A130: CLIENTE: CITICA
A131: NOMBRE DE EMPLEADO | B131: CLIENTE | C131: PLANTA | D131: TURNO | E131: PUESTO | F131: V1 | G131: S2 | H131: D3 | I131: L4 | J131: M5 | K131: M6 | L131: J7 | M131: HORAS EXTRA | N131: HORAS EXTRA NORMALES | O131: DÍAS CUBIERTOS NORMALES | P131: BONO | Q131: OBSERVACIONES
B132: CITICA
B133: CITICA
B134: CITICA
B135: CITICA
B136: CITICA
B137: CITICA
B138: CITICA
B139: CITICA
B140: CITICA
B141: CITICA
B142: CITICA
B143: CITICA
... B171: CITICA
A172: CLIENTE: GM
A173: NOMBRE DE EMPLEADO | B173: CLIENTE | C173: PLANTA | D173: TURNO | E173: PUESTO | F173: V1 | G173: S2 | H173: D3 | I173: L4 | J173: M5 | K173: M6 | L173: J7 | M173: HORAS EXTRA | N173: HORAS EXTRA NORMALES | O173: DÍAS CUBIERTOS NORMALES | P173: BONO | Q173: OBSERVACIONES
B174: GM
B175: GM
B176: GM
B177: GM
B178: GM
B179: GM
B180: GM
B181: GM
B182: GM
B183: GM
B184: GM
B185: GM
... B213: GM
A214: CLIENTE: TORRE BALZAK
A215: NOMBRE DE EMPLEADO | B215: CLIENTE | C215: PLANTA | D215: TURNO | E215: PUESTO | F215: V1 | G215: S2 | H215: D3 | I215: L4 | J215: M5 | K215: M6 | L215: J7 | M215: HORAS EXTRA | N215: HORAS EXTRA NORMALES | O215: DÍAS CUBIERTOS NORMALES | P215: BONO | Q215: OBSERVACIONES
B216: TORRE BALZAK
B217: TORRE BALZAK
B218: TORRE BALZAK
B219: TORRE BALZAK
B220: TORRE BALZAK
B221: TORRE BALZAK
B222: TORRE BALZAK
B223: TORRE BALZAK
B224: TORRE BALZAK
B225: TORRE BALZAK
B226: TORRE BALZAK
B227: TORRE BALZAK
... B255: TORRE BALZAK
A256: CLIENTE: TORRE OLMA
A257: NOMBRE DE EMPLEADO | B257: CLIENTE | C257: PLANTA | D257: TURNO | E257: PUESTO | F257: V1 | G257: S2 | H257: D3 | I257: L4 | J257: M5 | K257: M6 | L257: J7 | M257: HORAS EXTRA | N257: HORAS EXTRA NORMALES | O257: DÍAS CUBIERTOS NORMALES | P257: BONO | Q257: OBSERVACIONES
B258: TORRE OLMA
B259: TORRE OLMA
B260: TORRE OLMA
B261: TORRE OLMA
B262: TORRE OLMA
B263: TORRE OLMA
...

Sheet Compilado
A1: PROCLEAN · COMPILADO POR TRABAJADOR · NÓMINA MIÉRCOLES
A2: SEMANA: | B2: NOMINA: | E2: COORDINADOR:
A4: NOMBRE COMPLETO | B4: PUESTO | C4: BANCO | D4: CUENTA | E4: CLIENTES / TURNOS DONDE LABORÓ | F4: V1 | G4: S2 | H4: D3 | I4: L4 | J4: M5 | K4: M6 | L4: J7 | M4: DÍAS ÚNICOS LABORADOS | N4: DÍAS ADICIONALES DETECTADOS | O4: EVENTOS ADICIONALES MISMO DÍA | P4: HORAS EXTRA | Q4: HORAS EXTRA NORMALES | R4: DÍAS CUBIERTOS NORMALES | S4: VACACIONES LABORADAS | T4: PRIMA VACACIONAL | U4: BONO | V4: DEDUCCIONES | W4: OBSERVACIONES | Y4: mRow | Z4: wKey | AA4: key | AB4: nombre | AC4: nrmNom | AD4: puesto | AE4: turno | AF4: cliente | AG4: isFirst | AH4: uID | AI4: w1 | AJ4: w2 | AK4: w3 | AL4: w4 | AM4: w5 | AN4: w6 | AO4: w7 | AP4: wSum | AQ4: fl1 | AR4: fl2 | AS4: fl3 | AT4: fl4 | AU4: fl5 | AV4: fl6 | AW4: fl7 | AX4: flSum | AY4: dl1 | AZ4: dl2 | BA4: dl3 | BB4: dl4 | BC4: dl5 | BD4: dl6 | BE4: dl7 | BF4: dlSum | BG4: HE | BH4: HEN | BI4: DCN | BJ4: Bono | BK4: day1 | BL4: day2 | BM4: day3 | BN4: day4 | BO4: day5 | BP4: day6 | BQ4: day7
A5: =IF(Y5="","",INDEX($AB$5:$AB$323,Y5)) | B5: =IF(Y5="","",INDEX($AD$5:$AD$323,Y5)) | E5: =IF($A5="","",_xlfn.TEXTJOIN(" / ",TRUE(),IF(SUMIFS($AP$5:$AP$323,$AA$5:$AA$323,$Z5,$AF$5:$AF$323,"ARMIDA")>0,IFERROR("ARMIDA-"&INDEX($AE$5:$AE$323,MATCH($Z5&"ARMIDA",$AA$5:$AA$323&$AF$5:$AF$323,0)),"ARMIDA"),""),IF(SUMIFS($AP$5:$AP$323,$AA$5:$AA$323,$Z5,$AF$5:$AF$323,"AURIGA")>0,IFERROR("AURIGA-"&INDEX($AE$5:$AE$323,MATCH($Z5&"AURIGA",$AA$5:$AA$323&$AF$5:$AF$323,0)),"AURIGA"),""),IF(SUMIFS($AP$5:$AP$323,$AA$5:$AA$323,$Z5,$AF$5:$AF$323,"AURORA")>0,IFERROR("AURORA-"&INDEX($AE$5:$AE$323,MATCH($Z5&"AURORA",$AA$5:$AA$323&$AF$5:$AF$323,0)),"AURORA"),""),IF(SUMIFS($AP$5:$AP$323,$AA$5:$AA$323,$Z5,$AF$5:$AF$323,"CITICA")>0,IFERROR("CITICA-"&INDEX($AE$5:$AE$323,MATCH($Z5&"CITICA",$AA$5:$AA$323&$AF$5:$AF$323,0)),"CITICA"),""),IF(SUMIFS($AP$5:$AP$323,$AA$5:$AA$323,$Z5,$AF$5:$AF$323,"GM")>0,IFERROR("GM-"&INDEX($AE$5:$AE$323,MATCH($Z5&"GM",$AA$5:$AA$323&$AF$5:$AF$323,0)),"GM"),""),IF(SUMIFS($AP$5:$AP$323,$AA$5:$AA$323,$Z5,$AF$5:$AF$323,"TORRE BALZAK")>0,IFERROR("TORRE BALZAK-"&INDEX($AE$5:$AE$323,MATCH($Z5&"TORRE BALZAK",$AA$5:$AA$323&$AF$5:$AF$323,0)),"TORRE BALZAK"),""),IF(SUMIFS($AP$5:$AP$323,$AA$5:$AA$323,$Z5,$AF$5:$AF$323,"TORRE OLMA")>0,IFERROR("TORRE OLMA-"&INDEX($AE$5:$AE$323,MATCH($Z5&"TORRE OLMA",$AA$5:$AA$323&$AF$5:$AF$323,0)),"TORRE OLMA"),""),IF(SUMIFS($AP$5:$AP$323,$AA$5:$AA$323,$Z5,$AF$5:$AF$323,"OTROS")>0,IFERROR("OTROS-"&INDEX($AE$5:$AE$323,MATCH($Z5&"OTROS",$AA$5:$AA$323&$AF$5:$AF$323,0)),"OTROS"),""))) | F5: =IF($A5="","",IFERROR(INDEX($BK$5:$BK$323,MATCH($Z5,$AA$5:$AA$323,0)),"-")) | G5: =IF($A5="","",IFERROR(INDEX($BL$5:$BL$323,MATCH($Z5,$AA$5:$AA$323,0)),"-")) | H5: =IF($A5="","",IFERROR(INDEX($BM$5:$BM$323,MATCH($Z5,$AA$5:$AA$323,0)),"-")) | I5: =IF($A5="","",IFERROR(INDEX($BN$5:$BN$323,MATCH($Z5,$AA$5:$AA$323,0)),"-")) | J5: =IF($A5="","",IFERROR(INDEX($BO$5:$BO$323,MATCH($Z5,$AA$5:$AA$323,0)),"-")) | K5: =IF($A5="","",IFERROR(INDEX($BP$5:$BP$323,MATCH($Z5,$AA$5:$AA$323,0)),"-")) | L5: =IF($A5="","",IFERROR(INDEX($BQ$5:$BQ$323,MATCH($Z5,$AA$5:$AA$323,0)),"-")) | M5: =IF($A5="","",(--(SUMIF($AA$5:$AA$323,$Z5,$AI$5:$AI$323)>0))+(--(SUMIF($AA$5:$AA$323,$Z5,$AJ$5:$AJ$323)>0))+(--(SUMIF($AA$5:$AA$323,$Z5,$AK$5:$AK$323)>0))+(--(SUMIF($AA$5:$AA$323,$Z5,$AL$5:$AL$323)>0))+(--(SUMIF($AA$5:$AA$323,$Z5,$AM$5:$AM$323)>0))+(--(SUMIF($AA$5:$AA$323,$Z5,$AN$5:$AN$323)>0))+(--(SUMIF($AA$5:$AA$323,$Z5,$AO$5:$AO$323)>0))) | N5: =IF($A5="","",MAX(0,M5-6)) | O5: =IF($A5="","",SUMIF($AA$5:$AA$323,$Z5,$AP$5:$AP$323)-M5) | P5: =IF($A5="","",SUMIF($AA$5:$AA$323,$Z5,$BG$5:$BG$323)) | Q5: =IF($A5="","",SUMIF($AA$5:$AA$323,$Z5,$BH$5:$BH$323)) | R5: =IF($A5="","",SUMIF($AA$5:$AA$323,$Z5,$BI$5:$BI$323)) | U5: =IF($A5="","",SUMIF($AA$5:$AA$323,$Z5,$BJ$5:$BJ$323)) | W5: =IF($A5="","",_xlfn.TEXTJOIN(" | ",TRUE(),IF(N5>0,"+ de 6 días: revisar adicionales",""),IF(O5>0,"Doble evento mismo día: revisar turno/pago",""),IF(SUMIF($AA$5:$AA$323,$Z5,$AX$5:$AX$323)>((--(SUMIF($AA$5:$AA$323,$Z5,$AQ$5:$AQ$323)>0))+(--(SUMIF($AA$5:$AA$323,$Z5,$AR$5:$AR$323)>0))+(--(SUMIF($AA$5:$AA$323,$Z5,$AS$5:$AS$323)>0))+(--(SUMIF($AA$5:$AA$323,$Z5,$AT$5:$AT$323)>0))+(--(SUMIF($AA$5:$AA$323,$Z5,$AU$5:$AU$323)>0))+(--(SUMIF($AA$5:$AA$323,$Z5,$AV$5:$AV$323)>0))+(--(SUMIF($AA$5:$AA$323,$Z5,$AW$5:$AW$323)>0))),"FL múltiple mismo día: revisar pago festivo",""),IF(SUMIF($AA$5:$AA$323,$Z5,$BF$5:$BF$323)>((--(SUMIF($AA$5:$AA$323,$Z5,$AY$5:$AY$323)>0))+(--(SUMIF($AA$5:$AA$323,$Z5,$AZ$5:$AZ$323)>0))+(--(SUMIF($AA$5:$AA$323,$Z5,$BA$5:$BA$323)>0))+(--(SUMIF($AA$5:$AA$323,$Z5,$BB$5:$BB$323)>0))+(--(SUMIF($AA$5:$AA$323,$Z5,$BC$5:$BC$323)>0))+(--(SUMIF($AA$5:$AA$323,$Z5,$BD$5:$BD$323)>0))+(--(SUMIF($AA$5:$AA$323,$Z5,$BE$5:$BE$323)>0))),"DL múltiple mismo día: revisar pago descanso",""))) | Y5: =IFERROR(MATCH(1,$AH$5:$AH$323,0),"") | Z5: =IF(Y5="","",INDEX($AA$5:$AA$323,Y5)) | AA5: =IF(AC5="","","M:"&AC5) | AB5: =IF(Asistencia!A6="","",Asistencia!A6) | AC5: =IF(Asistencia!A6="","",SUBSTITUTE(SUBSTITUTE(SUBSTITUTE(SUBSTITUTE(SUBSTITUTE(SUBSTITUTE(SUBSTITUTE(UPPER(TRIM(Asistencia!A6)),"Á","A"),"É","E"),"Í","I"),"Ó","O"),"Ú","U"),"Ñ","N")," "," ")) | AD5: =IF(Asistencia!E6="","",Asistencia!E6) | AE5: =IF(Asistencia!D6="","",UPPER(TRIM(Asistencia!D6))) | AF5: ARMIDA | AG5: =IF(AND(AA5<>"",COUNTIF($AA$5:AA5,AA5)=1),1,0) -> 0 | AH5: =IF(AG5=1,SUM($AG$5:AG5),"") | AI5: =IF(OR(EXACT(Asistencia!F6,"A"),EXACT(Asistencia!F6,"R"),EXACT(Asistencia!F6,"DL"),EXACT(Asistencia!F6,"FL"),EXACT(Asistencia!F6,"FE"),EXACT(Asistencia!F6,"PCS"),EXACT(Asistencia!F6,"V")),1,0) -> 0 | AJ5: =IF(OR(EXACT(Asistencia!G6,"A"),EXACT(Asistencia!G6,"R"),EXACT(Asistencia!G6,"DL"),EXACT(Asistencia!G6,"FL"),EXACT(Asistencia!G6,"FE"),EXACT(Asistencia!G6,"PCS"),EXACT(Asistencia!G6,"V")),1,0) -> 0 | AK5: =IF(OR(EXACT(Asistencia!H6,"A"),EXACT(Asistencia!H6,"R"),EXACT(Asistencia!H6,"DL"),EXACT(Asistencia!H6,"FL"),EXACT(Asistencia!H6,"FE"),EXACT(Asistencia!H6,"PCS"),EXACT(Asistencia!H6,"V")),1,0) -> 0 | AL5: =IF(OR(EXACT(Asistencia!I6,"A"),EXACT(Asistencia!I6,"R"),EXACT(Asistencia!I6,"DL"),EXACT(Asistencia!I6,"FL"),EXACT(Asistencia!I6,"FE"),EXACT(Asistencia!I6,"PCS"),EXACT(Asistencia!I6,"V")),1,0) -> 0 | AM5: =IF(OR(EXACT(Asistencia!J6,"A"),EXACT(Asistencia!J6,"R"),EXACT(Asistencia!J6,"DL"),EXACT(Asistencia!J6,"FL"),EXACT(Asistencia!J6,"FE"),EXACT(Asistencia!J6,"PCS"),EXACT(Asistencia!J6,"V")),1,0) -> 0 | AN5: =IF(OR(EXACT(Asistencia!K6,"A"),EXACT(Asistencia!K6,"R"),EXACT(Asistencia!K6,"DL"),EXACT(Asistencia!K6,"FL"),EXACT(Asistencia!K6,"FE"),EXACT(Asistencia!K6,"PCS"),EXACT(Asistencia!K6,"V")),1,0) -> 0 | AO5: =IF(OR(EXACT(Asistencia!L6,"A"),EXACT(Asistencia!L6,"R"),EXACT(Asistencia!L6,"DL"),EXACT(Asistencia!L6,"FL"),EXACT(Asistencia!L6,"FE"),EXACT(Asistencia!L6,"PCS"),EXACT(Asistencia!L6,"V")),1,0) -> 0 | AP5: =SUM(AI5:AO5) -> 0 | AQ5: =IF(EXACT(Asistencia!F6,"FL"),1,0) -> 0 | AR5: =IF(EXACT(Asistencia!G6,"FL"),1,0) -> 0 | AS5: =IF(EXACT(Asistencia!H6,"FL"),1,0) -> 0 | AT5: =IF(EXACT(Asistencia!I6,"FL"),1,0) -> 0 | AU5: =IF(EXACT(Asistencia!J6,"FL"),1,0) -> 0 | AV5: =IF(EXACT(Asistencia!K6,"FL"),1,0) -> 0 | AW5: =IF(EXACT(Asistencia!L6,"FL"),1,0) -> 0 | AX5: =SUM(AQ5:AW5) -> 0 | AY5: =IF(EXACT(Asistencia!F6,"DL"),1,0) -> 0 | AZ5: =IF(EXACT(Asistencia!G6,"DL"),1,0) -> 0 | BA5: =IF(EXACT(Asistencia!H6,"DL"),1,0) -> 0 | BB5: =IF(EXACT(Asistencia!I6,"DL"),1,0) -> 0 | BC5: =IF(EXACT(Asistencia!J6,"DL"),1,0) -> 0 | BD5: =IF(EXACT(Asistencia!K6,"DL"),1,0) -> 0 | BE5: =IF(EXACT(Asistencia!L6,"DL"),1,0) -> 0 | BF5: =SUM(AY5:BE5) -> 0 | BG5: =IF(ISNUMBER(Asistencia!M6),Asistencia!M6,0) -> 0 | BH5: =IF(ISNUMBER(Asistencia!N6),Asistencia!N6,0) -> 0 | BI5: =IF(ISNUMBER(Asistencia!O6),Asistencia!O6,0) -> 0 | BJ5: =IF(ISNUMBER(Asistencia!P6),Asistencia!P6,0) -> 0 | BK5: =IF(Asistencia!F6="","",Asistencia!F6) | BL5: =IF(Asistencia!G6="","",Asistencia!G6) | BM5: =IF(Asistencia!H6="","",Asistencia!H6) | BN5: =IF(Asistencia!I6="","",Asistencia!I6) | BO5: =IF(Asistencia!J6="","",Asistencia!J6) | BP5: =IF(Asistencia!K6="","",Asistencia!K6) | BQ5: =IF(Asistencia!L6="","",Asistencia!L6)
A6: =IF(Y6="","",INDEX($AB$5:$AB$323,Y6)) | B6: =IF(Y6="","",INDEX($AD$5:$AD$323,Y6)) | E6: =IF($A6="","",_xlfn.TEXTJOIN(" / ",TRUE(),IF(SUMIFS($AP$5:$AP$323,$AA$5:$AA$323,$Z6,$AF$5:$AF$323,"ARMIDA")>0,IFERROR("ARMIDA-"&INDEX($AE$5:$AE$323,MATCH($Z6&"ARMIDA",$AA$5:$AA$323&$AF$5:$AF$323,0)),"ARMIDA"),""),IF(SUMIFS($AP$5:$AP$323,$AA$5:$AA$323,$Z6,$AF$5:$AF$323,"AURIGA")>0,IFERROR("AURIGA-"&INDEX($AE$5:$AE$323,MATCH($Z6&"AURIGA",$AA$5:$AA$323&$AF$5:$AF$323,0)),"AURIGA"),""),IF(SUMIFS($AP$5:$AP$323,$AA$5:$AA$323,$Z6,$AF$5:$AF$323,"AURORA")>0,IFERROR("AURORA-"&INDEX($AE$5:$AE$323,MATCH($Z6&"AURORA",$AA$5:$AA$323&$AF$5:$AF$323,0)),"AURORA"),""),IF(SUMIFS($AP$5:$AP$323,$AA$5:$AA$323,$Z6,$AF$5:$AF$323,"CITICA")>0,IFERROR("CITICA-"&INDEX($AE$5:$AE$323,MATCH($Z6&"CITICA",$AA$5:$AA$323&$AF$5:$AF$323,0)),"CITICA"),""),IF(SUMIFS($AP$5:$AP$323,$AA$5:$AA$323,$Z6,$AF$5:$AF$323,"GM")>0,IFERROR("GM-"&INDEX($AE$5:$AE$323,MATCH($Z6&"GM",$AA$5:$AA$323&$AF$5:$AF$323,0)),"GM"),""),IF(SUMIFS($AP$5:$AP$323,$AA$5:$AA$323,$Z6,$AF$5:$AF$323,"TORRE BALZAK")>0,IFERROR("TORRE BALZAK-"&INDEX($AE$5:$AE$323,MATCH($Z6&"TORRE BALZAK",$AA$5:$AA$323&$AF$5:$AF$323,0)),"TORRE BALZAK"),""),IF(SUMIFS($AP$5:$AP$323,$AA$5:$AA$323,$Z6,$AF$5:$AF$323,"TORRE OLMA")>0,IFERROR("TORRE OLMA-"&INDEX($AE$5:$AE$323,MATCH($Z6&"TORRE OLMA",$AA$5:$AA$323&$AF$5:$AF$323,0)),"TORRE OLMA"),""),IF(SUMIFS($AP$5:$AP$323,$AA$5:$AA$323,$Z6,$AF$5:$AF$323,"OTROS")>0,IFERROR("OTROS-"&INDEX($AE$5:$AE$323,MATCH($Z6&"OTROS",$AA$5:$AA$323&$AF$5:$AF$323,0)),"OTROS"),""))) | F6: =IF($A6="","",IFERROR(INDEX($BK$5:$BK$323,MATCH($Z6,$AA$5:$AA$323,0)),"-")) | G6: =IF($A6="","",IFERROR(INDEX($BL$5:$BL$323,MATCH($Z6,$AA$5:$AA$323,0)),"-")) | H6: =IF($A6="","",IFERROR(INDEX($BM$5:$BM$323,MATCH($Z6,$AA$5:$AA$323,0)),"-")) | I6: =IF($A6="","",IFERROR(INDEX($BN$5:$BN$323,MATCH($Z6,$AA$5:$AA$323,0)),"-")) | J6: =IF($A6="","",IFERROR(INDEX($BO$5:$BO$323,MATCH($Z6,$AA$5:$AA$323,0)),"-")) | K6: =IF($A6="","",IFERROR(INDEX($BP$5:$BP$323,MATCH($Z6,$AA$5:$AA$323,0)),"-")) | L6: =IF($A6="","",IFERROR(INDEX($BQ$5:$BQ$323,MATCH($Z6,$AA$5:$AA$323,0)),"-")) | M6: =IF($A6="","",(--(SUMIF($AA$5:$AA$323,$Z6,$AI$5:$AI$323)>0))+(--(SUMIF($AA$5:$AA$323,$Z6,$AJ$5:$AJ$323)>0))+(--(SUMIF($AA$5:$AA$323,$Z6,$AK$5:$AK$323)>0))+(--(SUMIF($AA$5:$AA$323,$Z6,$AL$5:$AL$323)>0))+(--(SUMIF($AA$5:$AA$323,$Z6,$AM$5:$AM$323)>0))+(--(SUMIF($AA$5:$AA$323,$Z6,$AN$5:$AN$323)>0))+(--(SUMIF($AA$5:$AA$323,$Z6,$AO$5:$AO$323)>0))) | N6: =IF($A6="","",MAX(0,M6-6)) | O6: =IF($A6="","",SUMIF($AA$5:$AA$323,$Z6,$AP$5:$AP$323)-M6) | P6: =IF($A6="","",SUMIF($AA$5:$AA$323,$Z6,$BG$5:$BG$323)) | Q6: =IF($A6="","",SUMIF($AA$5:$AA$323,$Z6,$BH$5:$BH$323)) | R6: =IF($A6="","",SUMIF($AA$5:$AA$323,$Z6,$BI$5:$BI$323)) | U6: =IF($A6="","",SUMIF($AA$5:$AA$323,$Z6,$BJ$5:$BJ$323)) | W6: =IF($A6="","",_xlfn.TEXTJOIN(" | ",TRUE(),IF(N6>0,"+ de 6 días: revisar adicionales",""),IF(O6>0,"Doble evento mismo día: revisar turno/pago",""),IF(SUMIF($AA$5:$AA$323,$Z6,$AX$5:$AX$323)>((--(SUMIF($AA$5:$AA$323,$Z6,$AQ$5:$AQ$323)>0))+(--(SUMIF($AA$5:$AA$323,$Z6,$AR$5:$AR$323)>0))+(--(SUMIF($AA$5:$AA$323,$Z6,$AS$5:$AS$323)>0))+(--(SUMIF($AA$5:$AA$323,$Z6,$AT$5:$AT$323)>0))+(--(SUMIF($AA$5:$AA$323,$Z6,$AU$5:$AU$323)>0))+(--(SUMIF($AA$5:$AA$323,$Z6,$AV$5:$AV$323)>0))+(--(SUMIF($AA$5:$AA$323,$Z6,$AW$5:$AW$323)>0))),"FL múltiple mismo día: revisar pago festivo",""),IF(SUMIF($AA$5:$AA$323,$Z6,$BF$5:$BF$323)>((--(SUMIF($AA$5:$AA$323,$Z6,$AY$5:$AY$323)>0))+(--(SUMIF($AA$5:$AA$323,$Z6,$AZ$5:$AZ$323)>0))+(--(SUMIF($AA$5:$AA$323,$Z6,$BA$5:$BA$323)>0))+(--(SUMIF($AA$5:$AA$323,$Z6,$BB$5:$BB$323)>0))+(--(SUMIF($AA$5:$AA$323,$Z6,$BC$5:$BC$323)>0))+(--(SUMIF($AA$5:$AA$323,$Z6,$BD$5:$BD$323)>0))+(--(SUMIF($AA$5:$AA$323,$Z6,$BE$5:$BE$323)>0))),"DL múltiple mismo día: revisar pago descanso",""))) | Y6: =IFERROR(MATCH(2,$AH$5:$AH$323,0),"") | Z6: =IF(Y6="","",INDEX($AA$5:$AA$323,Y6)) | AA6: =IF(AC6="","","M:"&AC6) | AB6: =IF(Asistencia!A7="","",Asistencia!A7) | AC6: =IF(Asistencia!A7="","",SUBSTITUTE(SUBSTITUTE(SUBSTITUTE(SUBSTITUTE(SUBSTITUTE(SUBSTITUTE(SUBSTITUTE(UPPER(TRIM(Asistencia!A7)),"Á","A"),"É","E"),"Í","I"),"Ó","O"),"Ú","U"),"Ñ","N")," "," ")) | AD6: =IF(Asistencia!E7="","",Asistencia!E7) | AE6: =IF(Asistencia!D7="","",UPPER(TRIM(Asistencia!D7))) | AF6: ARMIDA | AG6: =IF(AND(AA6<>"",COUNTIF($AA$5:AA6,AA6)=1),1,0) -> 0 | AH6: =IF(AG6=1,SUM($AG$5:AG6),"") | AI6: =IF(OR(EXACT(Asistencia!F7,"A"),EXACT(Asistencia!F7,"R"),EXACT(Asistencia!F7,"DL"),EXACT(Asistencia!F7,"FL"),EXACT(Asistencia!F7,"FE"),EXACT(Asistencia!F7,"PCS"),EXACT(Asistencia!F7,"V")),1,0) -> 0 | AJ6: =IF(OR(EXACT(Asistencia!G7,"A"),EXACT(Asistencia!G7,"R"),EXACT(Asistencia!G7,"DL"),EXACT(Asistencia!G7,"FL"),EXACT(Asistencia!G7,"FE"),EXACT(Asistencia!G7,"PCS"),EXACT(Asistencia!G7,"V")),1,0) -> 0 | AK6: =IF(OR(EXACT(Asistencia!H7,"A"),EXACT(Asistencia!H7,"R"),EXACT(Asistencia!H7,"DL"),EXACT(Asistencia!H7,"FL"),EXACT(Asistencia!H7,"FE"),EXACT(Asistencia!H7,"PCS"),EXACT(Asistencia!H7,"V")),1,0) -> 0 | AL6: =IF(OR(EXACT(Asistencia!I7,"A"),EXACT(Asistencia!I7,"R"),EXACT(Asistencia!I7,"DL"),EXACT(Asistencia!I7,"FL"),EXACT(Asistencia!I7,"FE"),EXACT(Asistencia!I7,"PCS"),EXACT(Asistencia!I7,"V")),1,0) -> 0 | AM6: =IF(OR(EXACT(Asistencia!J7,"A"),EXACT(Asistencia!J7,"R"),EXACT(Asistencia!J7,"DL"),EXACT(Asistencia!J7,"FL"),EXACT(Asistencia!J7,"FE"),EXACT(Asistencia!J7,"PCS"),EXACT(Asistencia!J7,"V")),1,0) -> 0 | AN6: =IF(OR(EXACT(Asistencia!K7,"A"),EXACT(Asistencia!K7,"R"),EXACT(Asistencia!K7,"DL"),EXACT(Asistencia!K7,"FL"),EXACT(Asistencia!K7,"FE"),EXACT(Asistencia!K7,"PCS"),EXACT(Asistencia!K7,"V")),1,0) -> 0 | AO6: =IF(OR(EXACT(Asistencia!L7,"A"),EXACT(Asistencia!L7,"R"),EXACT(Asistencia!L7,"DL"),EXACT(Asistencia!L7,"FL"),EXACT(Asistencia!L7,"FE"),EXACT(Asistencia!L7,"PCS"),EXACT(Asistencia!L7,"V")),1,0) -> 0 | AP6: =SUM(AI6:AO6) -> 0 | AQ6: =IF(EXACT(Asistencia!F7,"FL"),1,0) -> 0 | AR6: =IF(EXACT(Asistencia!G7,"FL"),1,0) -> 0 | AS6: =IF(EXACT(Asistencia!H7,"FL"),1,0) -> 0 | AT6: =IF(EXACT(Asistencia!I7,"FL"),1,0) -> 0 | AU6: =IF(EXACT(Asistencia!J7,"FL"),1,0) -> 0 | AV6: =IF(EXACT(Asistencia!K7,"FL"),1,0) -> 0 | AW6: =IF(EXACT(Asistencia!L7,"FL"),1,0) -> 0 | AX6: =SUM(AQ6:AW6) -> 0 | AY6: =IF(EXACT(Asistencia!F7,"DL"),1,0) -> 0 | AZ6: =IF(EXACT(Asistencia!G7,"DL"),1,0) -> 0 | BA6: =IF(EXACT(Asistencia!H7,"DL"),1,0) -> 0 | BB6: =IF(EXACT(Asistencia!I7,"DL"),1,0) -> 0 | BC6: =IF(EXACT(Asistencia!J7,"DL"),1,0) -> 0 | BD6: =IF(EXACT(Asistencia!K7,"DL"),1,0) -> 0 | BE6: =IF(EXACT(Asistencia!L7,"DL"),1,0) -> 0 | BF6: =SUM(AY6:BE6) -> 0 | BG6: =IF(ISNUMBER(Asistencia!M7),Asistencia!M7,0) -> 0 | BH6: =IF(ISNUMBER(Asistencia!N7),Asistencia!N7,0) -> 0 | BI6: =IF(ISNUMBER(Asistencia!O7),Asistencia!O7,0) -> 0 | BJ6: =IF(ISNUMBER(Asistencia!P7),Asistencia!P7,0) -> 0 | BK6: =IF(Asistencia!F7="","",Asistencia!F7) | BL6: =IF(Asistencia!G7="","",Asistencia!G7) | BM6: =IF(Asistencia!H7="","",Asistencia!H7) | BN6: =IF(Asistencia!I7="","",Asistencia!I7) | BO6: =IF(Asistencia!J7="","",Asistencia!J7) | BP6: =IF(Asistencia!K7="","",Asistencia!K7) | BQ6: =IF(Asistencia!L7="","",Asistencia!L7)
A7: =IF(Y7="","",INDEX($AB$5:$AB$323,Y7)) | B7: =IF(Y7="","",INDEX($AD$5:$AD$323,Y7)) | E7: =IF($A7="","",_xlfn.TEXTJOIN(" / ",TRUE(),IF(SUMIFS($AP$5:$AP$323,$AA$5:$AA$323,$Z7,$AF$5:$AF$323,"ARMIDA")>0,IFERROR("ARMIDA-"&INDEX($AE$5:$AE$323,MATCH($Z7&"ARMIDA",$AA$5:$AA$323&$AF$5:$AF$323,0)),"ARMIDA"),""),IF(SUMIFS($AP$5:$AP$323,$AA$5:$AA$323,$Z7,$AF$5:$AF$323,"AURIGA")>0,IFERROR("AURIGA-"&INDEX($AE$5:$AE$323,MATCH($Z7&"AURIGA",$AA$5:$AA$323&$AF$5:$AF$323,0)),"AURIGA"),""),IF(SUMIFS($AP$5:$AP$323,$AA$5:$AA$323,$Z7,$AF$5:$AF$323,"AURORA")>0,IFERROR("AURORA-"&INDEX($AE$5:$AE$323,MATCH($Z7&"AURORA",$AA$5:$AA$323&$AF$5:$AF$323,0)),"AURORA"),""),IF(SUMIFS($AP$5:$AP$323,$AA$5:$AA$323,$Z7,$AF$5:$AF$323,"CITICA")>0,IFERROR("CITICA-"&INDEX($AE$5:$AE$323,MATCH($Z7&"CITICA",$AA$5:$AA$323&$AF$5:$AF$323,0)),"CITICA"),""),IF(SUMIFS($AP$5:$AP$323,$AA$5:$AA$323,$Z7,$AF$5:$AF$323,"GM")>0,IFERROR("GM-"&INDEX($AE$5:$AE$323,MATCH($Z7&"GM",$AA$5:$AA$323&$AF$5:$AF$323,0)),"GM"),""),IF(SUMIFS($AP$5:$AP$323,$AA$5:$AA$323,$Z7,$AF$5:$AF$323,"TORRE BALZAK")>0,IFERROR("TORRE BALZAK-"&INDEX($AE$5:$AE$323,MATCH($Z7&"TORRE BALZAK",$AA$5:$AA$323&$AF$5:$AF$323,0)),"TORRE BALZAK"),""),IF(SUMIFS($AP$5:$AP$323,$AA$5:$AA$323,$Z7,$AF$5:$AF$323,"TORRE OLMA")>0,IFERROR("TORRE OLMA-"&INDEX($AE$5:$AE$323,MATCH($Z7&"TORRE OLMA",$AA$5:$AA$323&$AF$5:$AF$323,0)),"TORRE OLMA"),""),IF(SUMIFS($AP$5:$AP$323,$AA$5:$AA$323,$Z7,$AF$5:$AF$323,"OTROS")>0,IFERROR("OTROS-"&INDEX($AE$5:$AE$323,MATCH($Z7&"OTROS",$AA$5:$AA$323&$AF$5:$AF$323,0)),"OTROS"),""))) | F7: =IF($A7="","",IFERROR(INDEX($BK$5:$BK$323,MATCH($Z7,$AA$5:$AA$323,0)),"-")) | G7: =IF($A7="","",IFERROR(INDEX($BL$5:$BL$323,MATCH($Z7,$AA$5:$AA$323,0)),"-")) | H7: =IF($A7="","",IFERROR(INDEX($BM$5:$BM$323,MATCH($Z7,$AA$5:$AA$323,0)),"-")) | I7: =IF($A7="","",IFERROR(INDEX($BN$5:$BN$323,MATCH($Z7,$AA$5:$AA$323,0)),"-")) | J7: =IF($A7="","",IFERROR(INDEX($BO$5:$BO$323,MATCH($Z7,$AA$5:$AA$323,0)),"-")) | K7: =IF($A7="","",IFERROR(INDEX($BP$5:$BP$323,MATCH($Z7,$AA$5:$AA$323,0)),"-")) | L7: =IF($A7="","",IFERROR(INDEX($BQ$5:$BQ$323,MATCH($Z7,$AA$5:$AA$323,0)),"-")) | M7: =IF($A7="","",(--(SUMIF($AA$5:$AA$323,$Z7,$AI$5:$AI$323)>0))+(--(SUMIF($AA$5:$AA$323,$Z7,$AJ$5:$AJ$323)>0))+(--(SUMIF($AA$5:$AA$323,$Z7,$AK$5:$AK$323)>0))+(--(SUMIF($AA$5:$AA$323,$Z7,$AL$5:$AL$323)>0))+(--(SUMIF($AA$5:$AA$323,$Z7,$AM$5:$AM$323)>0))+(--(SUMIF($AA$5:$AA$323,$Z7,$AN$5:$AN$323)>0))+(--(SUMIF($AA$5:$AA$323,$Z7,$AO$5:$AO$323)>0))) | N7: =IF($A7="","",MAX(0,M7-6)) | O7: =IF($A7="","",SUMIF($AA$5:$AA$323,$Z7,$AP$5:$AP$323)-M7) | P7: =IF($A7="","",SUMIF($AA$5:$AA$323,$Z7,$BG$5:$BG$323)) | Q7: =IF($A7="","",SUMIF($AA$5:$AA$323,$Z7,$BH$5:$BH$323)) | R7: =IF($A7="","",SUMIF($AA$5:$AA$323,$Z7,$BI$5:$BI$323)) | U7: =IF($A7="","",SUMIF($AA$5:$AA$323,$Z7,$BJ$5:$BJ$323)) | W7: =IF($A7="","",_xlfn.TEXTJOIN(" | ",TRUE(),IF(N7>0,"+ de 6 días: revisar adicionales",""),IF(O7>0,"Doble evento mismo día: revisar turno/pago",""),IF(SUMIF($AA$5:$AA$323,$Z7,$AX$5:$AX$323)>((--(SUMIF($AA$5:$AA$323,$Z7,$AQ$5:$AQ$323)>0))+(--(SUMIF($AA$5:$AA$323,$Z7,$AR$5:$AR$323)>0))+(--(SUMIF($AA$5:$AA$323,$Z7,$AS$5:$AS$323)>0))+(--(SUMIF($AA$5:$AA$323,$Z7,$AT$5:$AT$323)>0))+(--(SUMIF($AA$5:$AA$323,$Z7,$AU$5:$AU$323)>0))+(--(SUMIF($AA$5:$AA$323,$Z7,$AV$5:$AV$323)>0))+(--(SUMIF($AA$5:$AA$323,$Z7,$AW$5:$AW$323)>0))),"FL múltiple mismo día: revisar pago festivo",""),IF(SUMIF($AA$5:$AA$323,$Z7,$BF$5:$BF$323)>((--(SUMIF($AA$5:$AA$323,$Z7,$AY$5:$AY$323)>0))+(--(SUMIF($AA$5:$AA$323,$Z7,$AZ$5:$AZ$323)>0))+(--(SUMIF($AA$5:$AA$323,$Z7,$BA$5:$BA$323)>0))+(--(SUMIF($AA$5:$AA$323,$Z7,$BB$5:$BB$323)>0))+(--(SUMIF($AA$5:$AA$323,$Z7,$BC$5:$BC$323)>0))+(--(SUMIF($AA$5:$AA$323,$Z7,$BD$5:$BD$323)>0))+(--(SUMIF($AA$5:$AA$323,$Z7,$BE$5:$BE$323)>0))),"DL múltiple mismo día: revisar pago descanso",""))) | Y7: =IFERROR(MATCH(3,$AH$5:$AH$323,0),"") | Z7: =IF(Y7="","",INDEX($AA$5:$AA$323,Y7)) | AA7: =IF(AC7="","","M:"&AC7) | AB7: =IF(Asistencia!A8="","",Asistencia!A8) | AC7: =IF(Asistencia!A8="","",SUBSTITUTE(SUBSTITUTE(SUBSTITUTE(SUBSTITUTE(SUBSTITUTE(SUBSTITUTE(SUBSTITUTE(UPPER(TRIM(Asistencia!A8)),"Á","A"),"É","E"),"Í","I"),"Ó","O"),"Ú","U"),"Ñ","N")," "," ")) | AD7: =IF(Asistencia!E8="","",Asistencia!E8) | AE7: =IF(Asistencia!D8="","",UPPER(TRIM(Asistencia!D8))) | AF7: ARMIDA | AG7: =IF(AND(AA7<>"",COUNTIF($AA$5:AA7,AA7)=1),1,0) -> 0 | AH7: =IF(AG7=1,SUM($AG$5:AG7),"") | AI7: =IF(OR(EXACT(Asistencia!F8,"A"),EXACT(Asistencia!F8,"R"),EXACT(Asistencia!F8,"DL"),EXACT(Asistencia!F8,"FL"),EXACT(Asistencia!F8,"FE"),EXACT(Asistencia!F8,"PCS"),EXACT(Asistencia!F8,"V")),1,0) -> 0 | AJ7: =IF(OR(EXACT(Asistencia!G8,"A"),EXACT(Asistencia!G8,"R"),EXACT(Asistencia!G8,"DL"),EXACT(Asistencia!G8,"FL"),EXACT(Asistencia!G8,"FE"),EXACT(Asistencia!G8,"PCS"),EXACT(Asistencia!G8,"V")),1,0) -> 0 | AK7: =IF(OR(EXACT(Asistencia!H8,"A"),EXACT(Asistencia!H8,"R"),EXACT(Asistencia!H8,"DL"),EXACT(Asistencia!H8,"FL"),EXACT(Asistencia!H8,"FE"),EXACT(Asistencia!H8,"PCS"),EXACT(Asistencia!H8,"V")),1,0) -> 0 | AL7: =IF(OR(EXACT(Asistencia!I8,"A"),EXACT(Asistencia!I8,"R"),EXACT(Asistencia!I8,"DL"),EXACT(Asistencia!I8,"FL"),EXACT(Asistencia!I8,"FE"),EXACT(Asistencia!I8,"PCS"),EXACT(Asistencia!I8,"V")),1,0) -> 0 | AM7: =IF(OR(EXACT(Asistencia!J8,"A"),EXACT(Asistencia!J8,"R"),EXACT(Asistencia!J8,"DL"),EXACT(Asistencia!J8,"FL"),EXACT(Asistencia!J8,"FE"),EXACT(Asistencia!J8,"PCS"),EXACT(Asistencia!J8,"V")),1,0) -> 0 | AN7: =IF(OR(EXACT(Asistencia!K8,"A"),EXACT(Asistencia!K8,"R"),EXACT(Asistencia!K8,"DL"),EXACT(Asistencia!K8,"FL"),EXACT(Asistencia!K8,"FE"),EXACT(Asistencia!K8,"PCS"),EXACT(Asistencia!K8,"V")),1,0) -> 0 | AO7: =IF(OR(EXACT(Asistencia!L8,"A"),EXACT(Asistencia!L8,"R"),EXACT(Asistencia!L8,"DL"),EXACT(Asistencia!L8,"FL"),EXACT(Asistencia!L8,"FE"),EXACT(Asistencia!L8,"PCS"),EXACT(Asistencia!L8,"V")),1,0) -> 0 | AP7: =SUM(AI7:AO7) -> 0 | AQ7: =IF(EXACT(Asistencia!F8,"FL"),1,0) -> 0 | AR7: =IF(EXACT(Asistencia!G8,"FL"),1,0) -> 0 | AS7: =IF(EXACT(Asistencia!H8,"FL"),1,0) -> 0 | AT7: =IF(EXACT(Asistencia!I8,"FL"),1,0) -> 0 | AU7: =IF(EXACT(Asistencia!J8,"FL"),1,0) -> 0 | AV7: =IF(EXACT(Asistencia!K8,"FL"),1,0) -> 0 | AW7: =IF(EXACT(Asistencia!L8,"FL"),1,0) -> 0 | AX7: =SUM(AQ7:AW7) -> 0 | AY7: =IF(EXACT(Asistencia!F8,"DL"),1,0) -> 0 | AZ7: =IF(EXACT(Asistencia!G8,"DL"),1,0) -> 0 | BA7: =IF(EXACT(Asistencia!H8,"DL"),1,0) -> 0 | BB7: =IF(EXACT(Asistencia!I8,"DL"),1,0) -> 0 | BC7: =IF(EXACT(Asistencia!J8,"DL"),1,0) -> 0 | BD7: =IF(EXACT(Asistencia!K8,"DL"),1,0) -> 0 | BE7: =IF(EXACT(Asistencia!L8,"DL"),1,0) -> 0 | BF7: =SUM(AY7:BE7) -> 0 | BG7: =IF(ISNUMBER(Asistencia!M8),Asistencia!M8,0) -> 0 | BH7: =IF(ISNUMBER(Asistencia!N8),Asistencia!N8,0) -> 0 | BI7: =IF(ISNUMBER(Asistencia!O8),Asistencia!O8,0) -> 0 | BJ7: =IF(ISNUMBER(Asistencia!P8),Asistencia!P8,0) -> 0 | BK7: =IF(Asistencia!F8="","",Asistencia!F8) | BL7: =IF(Asistencia!G8="","",Asistencia!G8) | BM7: =IF(Asistencia!H8="","",Asistencia!H8) | BN7: =IF(Asistencia!I8="","",Asistencia!I8) | BO7: =IF(Asistencia!J8="","",Asistencia!J8) | BP7: =IF(Asistencia!K8="","",Asistencia!K8) | BQ7: =IF(Asistencia!L8="","",Asistencia!L8)
A8: =IF(Y8="","",INDEX($AB$5:$AB$323,Y8)) | B8: =IF(Y8="","",INDEX($AD$5:$AD$323,Y8)) | E8: =IF($A8="","",_xlfn.TEXTJOIN(" / ",TRUE(),IF(SUMIFS($AP$5:$AP$323,$AA$5:$AA$323,$Z8,$AF$5:$AF$323,"ARMIDA")>0,IFERROR("ARMIDA-"&INDEX($AE$5:$AE$323,MATCH($Z8&"ARMIDA",$AA$5:$AA$323&$AF$5:$AF$323,0)),"ARMIDA"),""),IF(SUMIFS($AP$5:$AP$323,$AA$5:$AA$323,$Z8,$AF$5:$AF$323,"AURIGA")>0,IFERROR("AURIGA-"&INDEX($AE$5:$AE$323,MATCH($Z8&"AURIGA",$AA$5:$AA$323&$AF$5:$AF$323,0)),"AURIGA"),""),IF(SUMIFS($AP$5:$AP$323,$AA$5:$AA$323,$Z8,$AF$5:$AF$323,"AURORA")>0,IFERROR("AURORA-"&INDEX($AE$5:$AE$323,MATCH($Z8&"AURORA",$AA$5:$AA$323&$AF$5:$AF$323,0)),"AURORA"),""),IF(SUMIFS($AP$5:$AP$323,$AA$5:$AA$323,$Z8,$AF$5:$AF$323,"CITICA")>0,IFERROR("CITICA-"&INDEX($AE$5:$AE$323,MATCH($Z8&"CITICA",$AA$5:$AA$323&$AF$5:$AF$323,0)),"CITICA"),""),IF(SUMIFS($AP$5:$AP$323,$AA$5:$AA$323,$Z8,$AF$5:$AF$323,"GM")>0,IFERROR("GM-"&INDEX($AE$5:$AE$323,MATCH($Z8&"GM",$AA$5:$AA$323&$AF$5:$AF$323,0)),"GM"),""),IF(SUMIFS($AP$5:$AP$323,$AA$5:$AA$323,$Z8,$AF$5:$AF$323,"TORRE BALZAK")>0,IFERROR("TORRE BALZAK-"&INDEX($AE$5:$AE$323,MATCH($Z8&"TORRE BALZAK",$AA$5:$AA$323&$AF$5:$AF$323,0)),"TORRE BALZAK"),""),IF(SUMIFS($AP$5:$AP$323,$AA$5:$AA$323,$Z8,$AF$5:$AF$323,"TORRE OLMA")>0,IFERROR("TORRE OLMA-"&INDEX($AE$5:$AE$323,MATCH($Z8&"TORRE OLMA",$AA$5:$AA$323&$AF$5:$AF$323,0)),"TORRE OLMA"),""),IF(SUMIFS($AP$5:$AP$323,$AA$5:$AA$323,$Z8,$AF$5:$AF$323,"OTROS")>0,IFERROR("OTROS-"&INDEX($AE$5:$AE$323,MATCH($Z8&"OTROS",$AA$5:$AA$323&$AF$5:$AF$323,0)),"OTROS"),""))) | F8: =IF($A8="","",IFERROR(INDEX($BK$5:$BK$323,MATCH($Z8,$AA$5:$AA$323,0)),"-")) | G8: =IF($A8="","",IFERROR(INDEX($BL$5:$BL$323,MATCH($Z8,$AA$5:$AA$323,0)),"-")) | H8: =IF($A8="","",IFERROR(INDEX($BM$5:$BM$323,MATCH($Z8,$AA$5:$AA$323,0)),"-")) | I8: =IF($A8="","",IFERROR(INDEX($BN$5:$BN$323,MATCH($Z8,$AA$5:$AA$323,0)),"-")) | J8: =IF($A8="","",IFERROR(INDEX($BO$5:$BO$323,MATCH($Z8,$AA$5:$AA$323,0)),"-")) | K8: =IF($A8="","",IFERROR(INDEX($BP$5:$BP$323,MATCH($Z8,$AA$5:$AA$323,0)),"-")) | L8: =IF($A8="","",IFERROR(INDEX($BQ$5:$BQ$323,MATCH($Z8,$AA$5:$AA$323,0)),"-")) | M8: =IF($A8="","",(--(SUMIF($AA$5:$AA$323,$Z8,$AI$5:$AI$323)>0))+(--(SUMIF($AA$5:$AA$323,$Z8,$AJ$5:$AJ$323)>0))+(--(SUMIF($AA$5:$AA$323,$Z8,$AK$5:$AK$323)>0))+(--(SUMIF($AA$5:$AA$323,$Z8,$AL$5:$AL$323)>0))+(--(SUMIF($AA$5:$AA$323,$Z8,$AM$5:$AM$323)>0))+(--(SUMIF($AA$5:$AA$323,$Z8,$AN$5:$AN$323)>0))+(--(SUMIF($AA$5:$AA$323,$Z8,$AO$5:$AO$323)>0))) | N8: =IF($A8="","",MAX(0,M8-6)) | O8: =IF($A8="","",SUMIF($AA$5:$AA$323,$Z8,$AP$5:$AP$323)-M8) | P8: =IF($A8="","",SUMIF($AA$5:$AA$323,$Z8,$BG$5:$BG$323)) | Q8: =IF($A8="","",SUMIF($AA$5:$AA$323,$Z8,$BH$5:$BH$323)) | R8: =IF($A8="","",SUMIF($AA$5:$AA$323,$Z8,$BI$5:$BI$323)) | U8: =IF($A8="","",SUMIF($AA$5:$AA$323,$Z8,$BJ$5:$BJ$323)) | W8: =IF($A8="","",_xlfn.TEXTJOIN(" | ",TRUE(),IF(N8>0,"+ de 6 días: revisar adicionales",""),IF(O8>0,"Doble evento mismo día: revisar turno/pago",""),IF(SUMIF($AA$5:$AA$323,$Z8,$AX$5:$AX$323)>((--(SUMIF($AA$5:$AA$323,$Z8,$AQ$5:$AQ$323)>0))+(--(SUMIF($AA$5:$AA$323,$Z8,$AR$5:$AR$323)>0))+(--(SUMIF($AA$5:$AA$323,$Z8,$AS$5:$AS$323)>0))+(--(SUMIF($AA$5:$AA$323,$Z8,$AT$5:$AT$323)>0))+(--(SUMIF($AA$5:$AA$323,$Z8,$AU$5:$AU$323)>0))+(--(SUMIF($AA$5:$AA$323,$Z8,$AV$5:$AV$323)>0))+(--(SUMIF($AA$5:$AA$323,$Z8,$AW$5:$AW$323)>0))),"FL múltiple mismo día: revisar pago festivo",""),IF(SUMIF($AA$5:$AA$323,$Z8,$BF$5:$BF$323)>((--(SUMIF($AA$5:$AA$323,$Z8,$AY$5:$AY$323)>0))+(--(SUMIF($AA$5:$AA$323,$Z8,$AZ$5:$AZ$323)>0))+(--(SUMIF($AA$5:$AA$323,$Z8,$BA$5:$BA$323)>0))+(--(SUMIF($AA$5:$AA$323,$Z8,$BB$5:$BB$323)>0))+(--(SUMIF($AA$5:$AA$323,$Z8,$BC$5:$BC$323)>0))+(--(SUMIF($AA$5:$AA$323,$Z8,$BD$5:$BD$323)>0))+(--(SUMIF($AA$5:$AA$323,$Z8,$BE$5:$BE$323)>0))),"DL múltiple mismo día: revisar pago descanso",""))) | Y8: =IFERROR(MATCH(4,$AH$5:$AH$323,0),"") | Z8: =IF(Y8="","",INDEX($AA$5:$AA$323,Y8)) | AA8: =IF(AC8="","","M:"&AC8) | AB8: =IF(Asistencia!A9="","",Asistencia!A9) | AC8: =IF(Asistencia!A9="","",SUBSTITUTE(SUBSTITUTE(SUBSTITUTE(SUBSTITUTE(SUBSTITUTE(SUBSTITUTE(SUBSTITUTE(UPPER(TRIM(Asistencia!A9)),"Á","A"),"É","E"),"Í","I"),"Ó","O"),"Ú","U"),"Ñ","N")," "," ")) | AD8: =IF(Asistencia!E9="","",Asistencia!E9) | AE8: =IF(Asistencia!D9="","",UPPER(TRIM(Asistencia!D9))) | AF8: ARMIDA | AG8: =IF(AND(AA8<>"",COUNTIF($AA$5:AA8,AA8)=1),1,0) -> 0 | AH8: =IF(AG8=1,SUM($AG$5:AG8),"") | AI8: =IF(OR(EXACT(Asistencia!F9,"A"),EXACT(Asistencia!F9,"R"),EXACT(Asistencia!F9,"DL"),EXACT(Asistencia!F9,"FL"),EXACT(Asistencia!F9,"FE"),EXACT(Asistencia!F9,"PCS"),EXACT(Asistencia!F9,"V")),1,0) -> 0 | AJ8: =IF(OR(EXACT(Asistencia!G9,"A"),EXACT(Asistencia!G9,"R"),EXACT(Asistencia!G9,"DL"),EXACT(Asistencia!G9,"FL"),EXACT(Asistencia!G9,"FE"),EXACT(Asistencia!G9,"PCS"),EXACT(Asistencia!G9,"V")),1,0) -> 0 | AK8: =IF(OR(EXACT(Asistencia!H9,"A"),EXACT(Asistencia!H9,"R"),EXACT(Asistencia!H9,"DL"),EXACT(Asistencia!H9,"FL"),EXACT(Asistencia!H9,"FE"),EXACT(Asistencia!H9,"PCS"),EXACT(Asistencia!H9,"V")),1,0) -> 0 | AL8: =IF(OR(EXACT(Asistencia!I9,"A"),EXACT(Asistencia!I9,"R"),EXACT(Asistencia!I9,"DL"),EXACT(Asistencia!I9,"FL"),EXACT(Asistencia!I9,"FE"),EXACT(Asistencia!I9,"PCS"),EXACT(Asistencia!I9,"V")),1,0) -> 0 | AM8: =IF(OR(EXACT(Asistencia!J9,"A"),EXACT(Asistencia!J9,"R"),EXACT(Asistencia!J9,"DL"),EXACT(Asistencia!J9,"FL"),EXACT(Asistencia!J9,"FE"),EXACT(Asistencia!J9,"PCS"),EXACT(Asistencia!J9,"V")),1,0) -> 0 | AN8: =IF(OR(EXACT(Asistencia!K9,"A"),EXACT(Asistencia!K9,"R"),EXACT(Asistencia!K9,"DL"),EXACT(Asistencia!K9,"FL"),EXACT(Asistencia!K9,"FE"),EXACT(Asistencia!K9,"PCS"),EXACT(Asistencia!K9,"V")),1,0) -> 0 | AO8: =IF(OR(EXACT(Asistencia!L9,"A"),EXACT(Asistencia!L9,"R"),EXACT(Asistencia!L9,"DL"),EXACT(Asistencia!L9,"FL"),EXACT(Asistencia!L9,"FE"),EXACT(Asistencia!L9,"PCS"),EXACT(Asistencia!L9,"V")),1,0) -> 0 | AP8: =SUM(AI8:AO8) -> 0 | AQ8: =IF(EXACT(Asistencia!F9,"FL"),1,0) -> 0 | AR8: =IF(EXACT(Asistencia!G9,"FL"),1,0) -> 0 | AS8: =IF(EXACT(Asistencia!H9,"FL"),1,0) -> 0 | AT8: =IF(EXACT(Asistencia!I9,"FL"),1,0) -> 0 | AU8: =IF(EXACT(Asistencia!J9,"FL"),1,0) -> 0 | AV8: =IF(EXACT(Asistencia!K9,"FL"),1,0) -> 0 | AW8: =IF(EXACT(Asistencia!L9,"FL"),1,0) -> 0 | AX8: =SUM(AQ8:AW8) -> 0 | AY8: =IF(EXACT(Asistencia!F9,"DL"),1,0) -> 0 | AZ8: =IF(EXACT(Asistencia!G9,"DL"),1,0) -> 0 | BA8: =IF(EXACT(Asistencia!H9,"DL"),1,0) -> 0 | BB8: =IF(EXACT(Asistencia!I9,"DL"),1,0) -> 0 | BC8: =IF(EXACT(Asistencia!J9,"DL"),1,0) -> 0 | BD8: =IF(EXACT(Asistencia!K9,"DL"),1,0) -> 0 | BE8: =IF(EXACT(Asistencia!L9,"DL"),1,0) -> 0 | BF8: =SUM(AY8:BE8) -> 0 | BG8: =IF(ISNUMBER(Asistencia!M9),Asistencia!M9,0) -> 0 | BH8: =IF(ISNUMBER(Asistencia!N9),Asistencia!N9,0) -> 0 | BI8: =IF(ISNUMBER(Asistencia!O9),Asistencia!O9,0) -> 0 | BJ8: =IF(ISNUMBER(Asistencia!P9),Asistencia!P9,0) -> 0 | BK8: =IF(Asistencia!F9="","",Asistencia!F9) | BL8: =IF(Asistencia!G9="","",Asistencia!G9) | BM8: =IF(Asistencia!H9="","",Asistencia!H9) | BN8: =IF(Asistencia!I9="","",Asistencia!I9) | BO8: =IF(Asistencia!J9="","",Asistencia!J9) | BP8: =IF(Asistencia!K9="","",Asistencia!K9) | BQ8: =IF(Asistencia!L9="","",Asistencia!L9)
A9: =IF(Y9="","",INDEX($AB$5:$AB$323,Y9)) | B9: =IF(Y9="","",INDEX($AD$5:$AD$323,Y9)) | E9: =IF($A9="","",_xlfn.TEXTJOIN(" / ",TRUE(),IF(SUMIFS($AP$5:$AP$323,$AA$5:$AA$323,$Z9,$AF$5:$AF$323,"ARMIDA")>0,IFERROR("ARMIDA-"&INDEX($AE$5:$AE$323,MATCH($Z9&"ARMIDA",$AA$5:$AA$323&$AF$5:$AF$323,0)),"ARMIDA"),""),IF(SUMIFS($AP$5:$AP$323,$AA$5:$AA$323,$Z9,$AF$5:$AF$323,"AURIGA")>0,IFERROR("AURIGA-"&INDEX($AE$5:$AE$323,MATCH($Z9&"AURIGA",$AA$5:$AA$323&$AF$5:$AF$323,0)),"AURIGA"),""),IF(SUMIFS($AP$5:$AP$323,$AA$5:$AA$323,$Z9,$AF$5:$AF$323,"AURORA")>0,IFERROR("AURORA-"&INDEX($AE$5:$AE$323,MATCH($Z9&"AURORA",$AA$5:$AA$323&$AF$5:$AF$323,0)),"AURORA"),""),IF(SUMIFS($AP$5:$AP$323,$AA$5:$AA$323,$Z9,$AF$5:$AF$323,"CITICA")>0,IFERROR("CITICA-"&INDEX($AE$5:$AE$323,MATCH($Z9&"CITICA",$AA$5:$AA$323&$AF$5:$AF$323,0)),"CITICA"),""),IF(SUMIFS($AP$5:$AP$323,$AA$5:$AA$323,$Z9,$AF$5:$AF$323,"GM")>0,IFERROR("GM-"&INDEX($AE$5:$AE$323,MATCH($Z9&"GM",$AA$5:$AA$323&$AF$5:$AF$323,0)),"GM"),""),IF(SUMIFS($AP$5:$AP$323,$AA$5:$AA$323,$Z9,$AF$5:$AF$323,"TORRE BALZAK")>0,IFERROR("TORRE BALZAK-"&INDEX($AE$5:$AE$323,MATCH($Z9&"TORRE BALZAK",$AA$5:$AA$323&$AF$5:$AF$323,0)),"TORRE BALZAK"),""),IF(SUMIFS($AP$5:$AP$323,$AA$5:$AA$323,$Z9,$AF$5:$AF$323,"TORRE OLMA")>0,IFERROR("TORRE OLMA-"&INDEX($AE$5:$AE$323,MATCH($Z9&"TORRE OLMA",$AA$5:$AA$323&$AF$5:$AF$323,0)),"TORRE OLMA"),""),IF(SUMIFS($AP$5:$AP$323,$AA$5:$AA$323,$Z9,$AF$5:$AF$323,"OTROS")>0,IFERROR("OTROS-"&INDEX($AE$5:$AE$323,MATCH($Z9&"OTROS",$AA$5:$AA$323&$AF$5:$AF$323,0)),"OTROS"),""))) | F9: =IF($A9="","",IFERROR(INDEX($BK$5:$BK$323,MATCH($Z9,$AA$5:$AA$323,0)),"-")) | G9: =IF($A9="","",IFERROR(INDEX($BL$5:$BL$323,MATCH($Z9,$AA$5:$AA$323,0)),"-")) | H9: =IF($A9="","",IFERROR(INDEX($BM$5:$BM$323,MATCH($Z9,$AA$5:$AA$323,0)),"-")) | I9: =IF($A9="","",IFERROR(INDEX($BN$5:$BN$323,MATCH($Z9,$AA$5:$AA$323,0)),"-")) | J9: =IF($A9="","",IFERROR(INDEX($BO$5:$BO$323,MATCH($Z9,$AA$5:$AA$323,0)),"-")) | K9: =IF($A9="","",IFERROR(INDEX($BP$5:$BP$323,MATCH($Z9,$AA$5:$AA$323,0)),"-")) | L9: =IF($A9="","",IFERROR(INDEX($BQ$5:$BQ$323,MATCH($Z9,$AA$5:$AA$323,0)),"-")) | M9: =IF($A9="","",(--(SUMIF($AA$5:$AA$323,$Z9,$AI$5:$AI$323)>0))+(--(SUMIF($AA$5:$AA$323,$Z9,$AJ$5:$AJ$323)>0))+(--(SUMIF($AA$5:$AA$323,$Z9,$AK$5:$AK$323)>0))+(--(SUMIF($AA$5:$AA$323,$Z9,$AL$5:$AL$323)>0))+(--(SUMIF($AA$5:$AA$323,$Z9,$AM$5:$AM$323)>0))+(--(SUMIF($AA$5:$AA$323,$Z9,$AN$5:$AN$323)>0))+(--(SUMIF($AA$5:$AA$323,$Z9,$AO$5:$AO$323)>0))) | N9: =IF($A9="","",MAX(0,M9-6)) | O9: =IF($A9="","",SUMIF($AA$5:$AA$323,$Z9,$AP$5:$AP$323)-M9) | P9: =IF($A9="","",SUMIF($AA$5:$AA$323,$Z9,$BG$5:$BG$323)) | Q9: =IF($A9="","",SUMIF($AA$5:$AA$323,$Z9,$BH$5:$BH$323)) | R9: =IF($A9="","",SUMIF($AA$5:$AA$323,$Z9,$BI$5:$BI$323)) | U9: =IF($A9="","",SUMIF($AA$5:$AA$323,$Z9,$BJ$5:$BJ$323)) | W9: =IF($A9="","",_xlfn.TEXTJOIN(" | ",TRUE(),IF(N9>0,"+ de 6 días: revisar adicionales",""),IF(O9>0,"Doble evento mismo día: revisar turno/pago",""),IF(SUMIF($AA$5:$AA$323,$Z9,$AX$5:$AX$323)>((--(SUMIF($AA$5:$AA$323,$Z9,$AQ$5:$AQ$323)>0))+(--(SUMIF($AA$5:$AA$323,$Z9,$AR$5:$AR$323)>0))+(--(SUMIF($AA$5:$AA$323,$Z9,$AS$5:$AS$323)>0))+(--(SUMIF($AA$5:$AA$323,$Z9,$AT$5:$AT$323)>0))+(--(SUMIF($AA$5:$AA$323,$Z9,$AU$5:$AU$323)>0))+(--(SUMIF($AA$5:$AA$323,$Z9,$AV$5:$AV$323)>0))+(--(SUMIF($AA$5:$AA$323,$Z9,$AW$5:$AW$323)>0))),"FL múltiple mismo día: revisar pago festivo",""),IF(SUMIF($AA$5:$AA$323,$Z9,$BF$5:$BF$323)>((--(SUMIF($AA$5:$AA$323,$Z9,$AY$5:$AY$323)>0))+(--(SUMIF($AA$5:$AA$323,$Z9,$AZ$5:$AZ$323)>0))+(--(SUMIF($AA$5:$AA$323,$Z9,$BA$5:$BA$323)>0))+(--(SUMIF($AA$5:$AA$323,$Z9,$BB$5:$BB$323)>0))+(--(SUMIF($AA$5:$AA$323,$Z9,$BC$5:$BC$323)>0))+(--(SUMIF($AA$5:$AA$323,$Z9,$BD$5:$BD$323)>0))+(--(SUMIF($AA$5:$AA$323,$Z9,$BE$5:$BE$323)>0))),"DL múltiple mismo día: revisar pago descanso",""))) | Y9: =IFERROR(MATCH(5,$AH$5:$AH$323,0),"") | Z9: =IF(Y9="","",INDEX($AA$5:$AA$323,Y9)) | AA9: =IF(AC9="","","M:"&AC9) | AB9: =IF(Asistencia!A10="","",Asistencia!A10) | AC9: =IF(Asistencia!A10="","",SUBSTITUTE(SUBSTITUTE(SUBSTITUTE(SUBSTITUTE(SUBSTITUTE(SUBSTITUTE(SUBSTITUTE(UPPER(TRIM(Asistencia!A10)),"Á","A"),"É","E"),"Í","I"),"Ó","O"),"Ú","U"),"Ñ","N")," "," ")) | AD9: =IF(Asistencia!E10="","",Asistencia!E10) | AE9: =IF(Asistencia!D10="","",UPPER(TRIM(Asistencia!D10))) | AF9: ARMIDA | AG9: =IF(AND(AA9<>"",COUNTIF($AA$5:AA9,AA9)=1),1,0) -> 0 | AH9: =IF(AG9=1,SUM($AG$5:AG9),"") | AI9: =IF(OR(EXACT(Asistencia!F10,"A"),EXACT(Asistencia!F10,"R"),EXACT(Asistencia!F10,"DL"),EXACT(Asistencia!F10,"FL"),EXACT(Asistencia!F10,"FE"),EXACT(Asistencia!F10,"PCS"),EXACT(Asistencia!F10,"V")),1,0) -> 0 | AJ9: =IF(OR(EXACT(Asistencia!G10,"A"),EXACT(Asistencia!G10,"R"),EXACT(Asistencia!G10,"DL"),EXACT(Asistencia!G10,"FL"),EXACT(Asistencia!G10,"FE"),EXACT(Asistencia!G10,"PCS"),EXACT(Asistencia!G10,"V")),1,0) -> 0 | AK9: =IF(OR(EXACT(Asistencia!H10,"A"),EXACT(Asistencia!H10,"R"),EXACT(Asistencia!H10,"DL"),EXACT(Asistencia!H10,"FL"),EXACT(Asistencia!H10,"FE"),EXACT(Asistencia!H10,"PCS"),EXACT(Asistencia!H10,"V")),1,0) -> 0 | AL9: =IF(OR(EXACT(Asistencia!I10,"A"),EXACT(Asistencia!I10,"R"),EXACT(Asistencia!I10,"DL"),EXACT(Asistencia!I10,"FL"),EXACT(Asistencia!I10,"FE"),EXACT(Asistencia!I10,"PCS"),EXACT(Asistencia!I10,"V")),1,0) -> 0 | AM9: =IF(OR(EXACT(Asistencia!J10,"A"),EXACT(Asistencia!J10,"R"),EXACT(Asistencia!J10,"DL"),EXACT(Asistencia!J10,"FL"),EXACT(Asistencia!J10,"FE"),EXACT(Asistencia!J10,"PCS"),EXACT(Asistencia!J10,"V")),1,0) -> 0 | AN9: =IF(OR(EXACT(Asistencia!K10,"A"),EXACT(Asistencia!K10,"R"),EXACT(Asistencia!K10,"DL"),EXACT(Asistencia!K10,"FL"),EXACT(Asistencia!K10,"FE"),EXACT(Asistencia!K10,"PCS"),EXACT(Asistencia!K10,"V")),1,0) -> 0 | AO9: =IF(OR(EXACT(Asistencia!L10,"A"),EXACT(Asistencia!L10,"R"),EXACT(Asistencia!L10,"DL"),EXACT(Asistencia!L10,"FL"),EXACT(Asistencia!L10,"FE"),EXACT(Asistencia!L10,"PCS"),EXACT(Asistencia!L10,"V")),1,0) -> 0 | AP9: =SUM(AI9:AO9) -> 0 | AQ9: =IF(EXACT(Asistencia!F10,"FL"),1,0) -> 0 | AR9: =IF(EXACT(Asistencia!G10,"FL"),1,0) -> 0 | AS9: =IF(EXACT(Asistencia!H10,"FL"),1,0) -> 0 | AT9: =IF(EXACT(Asistencia!I10,"FL"),1,0) -> 0 | AU9: =IF(EXACT(Asistencia!J10,"FL"),1,0) -> 0 | AV9: =IF(EXACT(Asistencia!K10,"FL"),1,0) -> 0 | AW9: =IF(EXACT(Asistencia!L10,"FL"),1,0) -> 0 | AX9: =SUM(AQ9:AW9) -> 0 | AY9: =IF(EXACT(Asistencia!F10,"DL"),1,0) -> 0 | AZ9: =IF(EXACT(Asistencia!G10,"DL"),1,0) -> 0 | BA9: =IF(EXACT(Asistencia!H10,"DL"),1,0) -> 0 | BB9: =IF(EXACT(Asistencia!I10,"DL"),1,0) -> 0 | BC9: =IF(EXACT(Asistencia!J10,"DL"),1,0) -> 0 | BD9: =IF(EXACT(Asistencia!K10,"DL"),1,0) -> 0 | BE9: =IF(EXACT(Asistencia!L10,"DL"),1,0) -> 0 | BF9: =SUM(AY9:BE9) -> 0 | BG9: =IF(ISNUMBER(Asistencia!M10),Asistencia!M10,0) -> 0 | BH9: =IF(ISNUMBER(Asistencia!N10),Asistencia!N10,0) -> 0 | BI9: =IF(ISNUMBER(Asistencia!O10),Asistencia!O10,0) -> 0 | BJ9: =IF(ISNUMBER(Asistencia!P10),Asistencia!P10,0) -> 0 | BK9: =IF(Asistencia!F10="","",Asistencia!F10) | BL9: =IF(Asistencia!G10="","",Asistencia!G10) | BM9: =IF(Asistencia!H10="","",Asistencia!H10) | BN9: =IF(Asistencia!I10="","",Asistencia!I10) | BO9: =IF(Asistencia!J10="","",Asistencia!J10) | BP9: =IF(Asistencia!K10="","",Asistencia!K10) | BQ9: =IF(Asistencia!L10="","",Asistencia!L10)
A10: =IF(Y10="","",INDEX($AB$5:$AB$323,Y10)) | B10: =IF(Y10="","",INDEX($AD$5:$AD$323,Y10)) | E10: =IF($A10="","",_xlfn.TEXTJOIN(" / ",TRUE(),IF(SUMIFS($AP$5:$AP$323,$AA$5:$AA$323,$Z10,$AF$5:$AF$323,"ARMIDA")>0,IFERROR("ARMIDA-"&INDEX($AE$5:$AE$323,MATCH($Z10&"ARMIDA",$AA$5:$AA$323&$AF$5:$AF$323,0)),"ARMIDA"),""),IF(SUMIFS($AP$5:$AP$323,$AA$5:$AA$323,$Z10,$AF$5:$AF$323,"AURIGA")>0,IFERROR("AURIGA-"&INDEX($AE$5:$AE$323,MATCH($Z10&"AURIGA",$AA$5:$AA$323&$AF$5:$AF$323,0)),"AURIGA"),""),IF(SUMIFS($AP$5:$AP$323,$AA$5:$AA$323,$Z10,$AF$5:$AF$323,"AURORA")>0,IFERROR("AURORA-"&INDEX($AE$5:$AE$323,MATCH($Z10&"AURORA",$AA$5:$AA$323&$AF$5:$AF$323,0)),"AURORA"),""),IF(SUMIFS($AP$5:$AP$323,$AA$5:$AA$323,$Z10,$AF$5:$AF$323,"CITICA")>0,IFERROR("CITICA-"&INDEX($AE$5:$AE$323,MATCH($Z10&"CITICA",$AA$5:$AA$323&$AF$5:$AF$323,0)),"CITICA"),""),IF(SUMIFS($AP$5:$AP$323,$AA$5:$AA$323,$Z10,$AF$5:$AF$323,"GM")>0,IFERROR("GM-"&INDEX($AE$5:$AE$323,MATCH($Z10&"GM",$AA$5:$AA$323&$AF$5:$AF$323,0)),"GM"),""),IF(SUMIFS($AP$5:$AP$323,$AA$5:$AA$323,$Z10,$AF$5:$AF$323,"TORRE BALZAK")>0,IFERROR("TORRE BALZAK-"&INDEX($AE$5:$AE$323,MATCH($Z10&"TORRE BALZAK",$AA$5:$AA$323&$AF$5:$AF$323,0)),"TORRE BALZAK"),""),IF(SUMIFS($AP$5:$AP$323,$AA$5:$AA$323,$Z10,$AF$5:$AF$323,"TORRE OLMA")>0,IFERROR("TORRE OLMA-"&INDEX($AE$5:$AE$323,MATCH($Z10&"TORRE OLMA",$AA$5:$AA$323&$AF$5:$AF$323,0)),"TORRE OLMA"),""),IF(SUMIFS($AP$5:$AP$323,$AA$5:$AA$323,$Z10,$AF$5:$AF$323,"OTROS")>0,IFERROR("OTROS-"&INDEX($AE$5:$AE$323,MATCH($Z10&"OTROS",$AA$5:$AA$323&$AF$5:$AF$323,0)),"OTROS"),""))) | F10: =IF($A10="","",IFERROR(INDEX($BK$5:$BK$323,MATCH($Z10,$AA$5:$AA$323,0)),"-")) | G10: =IF($A10="","",IFERROR(INDEX($BL$5:$BL$323,MATCH($Z10,$AA$5:$AA$323,0)),"-")) | H10: =IF($A10="","",IFERROR(INDEX($BM$5:$BM$323,MATCH($Z10,$AA$5:$AA$323,0)),"-")) | I10: =IF($A10="","",IFERROR(INDEX($BN$5:$BN$323,MATCH($Z10,$AA$5:$AA$323,0)),"-")) | J10: =IF($A10="","",IFERROR(INDEX($BO$5:$BO$323,MATCH($Z10,$AA$5:$AA$323,0)),"-")) | K10: =IF($A10="","",IFERROR(INDEX($BP$5:$BP$323,MATCH($Z10,$AA$5:$AA$323,0)),"-")) | L10: =IF($A10="","",IFERROR(INDEX($BQ$5:$BQ$323,MATCH($Z10,$AA$5:$AA$323,0)),"-")) | M10: =IF($A10="","",(--(SUMIF($AA$5:$AA$323,$Z10,$AI$5:$AI$323)>0))+(--(SUMIF($AA$5:$AA$323,$Z10,$AJ$5:$AJ$323)>0))+(--(SUMIF($AA$5:$AA$323,$Z10,$AK$5:$AK$323)>0))+(--(SUMIF($AA$5:$AA$323,$Z10,$AL$5:$AL$323)>0))+(--(SUMIF($AA$5:$AA$323,$Z10,$AM$5:$AM$323)>0))+(--(SUMIF($AA$5:$AA$323,$Z10,$AN$5:$AN$323)>0))+(--(SUMIF($AA$5:$AA$323,$Z10,$AO$5:$AO$323)>0))) | N10: =IF($A10="","",MAX(0,M10-6)) | O10: =IF($A10="","",SUMIF($AA$5:$AA$323,$Z10,$AP$5:$AP$323)-M10) | P10: =IF($A10="","",SUMIF($AA$5:$AA$323,$Z10,$BG$5:$BG$323)) | Q10: =IF($A10="","",SUMIF($AA$5:$AA$323,$Z10,$BH$5:$BH$323)) | R10: =IF($A10="","",SUMIF($AA$5:$AA$323,$Z10,$BI$5:$BI$323)) | U10: =IF($A10="","",SUMIF($AA$5:$AA$323,$Z10,$BJ$5:$BJ$323)) | W10: =IF($A10="","",_xlfn.TEXTJOIN(" | ",TRUE(),IF(N10>0,"+ de 6 días: revisar adicionales",""),IF(O10>0,"Doble evento mismo día: revisar turno/pago",""),IF(SUMIF($AA$5:$AA$323,$Z10,$AX$5:$AX$323)>((--(SUMIF($AA$5:$AA$323,$Z10,$AQ$5:$AQ$323)>0))+(--(SUMIF($AA$5:$AA$323,$Z10,$AR$5:$AR$323)>0))+(--(SUMIF($AA$5:$AA$323,$Z10,$AS$5:$AS$323)>0))+(--(SUMIF($AA$5:$AA$323,$Z10,$AT$5:$AT$323)>0))+(--(SUMIF($AA$5:$AA$323,$Z10,$AU$5:$AU$323)>0))+(--(SUMIF($AA$5:$AA$323,$Z10,$AV$5:$AV$323)>0))+(--(SUMIF($AA$5:$AA$323,$Z10,$AW$5:$AW$323)>0))),"FL múltiple mismo día: revisar pago festivo",""),IF(SUMIF($AA$5:$AA$323,$Z10,$BF$5:$BF$323)>((--(SUMIF($AA$5:$AA$323,$Z10,$AY$5:$AY$323)>0))+(--(SUMIF($AA$5:$AA$323,$Z10,$AZ$5:$AZ$323)>0))+(--(SUMIF($AA$5:$AA$323,$Z10,$BA$5:$BA$323)>0))+(--(SUMIF($AA$5:$AA$323,$Z10,$BB$5:$BB$323)>0))+(--(SUMIF($AA$5:$AA$323,$Z10,$BC$5:$BC$323)>0))+(--(SUMIF($AA$5:$AA$323,$Z10,$BD$5:$BD$323)>0))+(--(SUMIF($AA$5:$AA$323,$Z10,$BE$5:$BE$323)>0))),"DL múltiple mismo día: revisar pago descanso",""))) | Y10: =IFERROR(MATCH(6,$AH$5:$AH$323,0),"") | Z10: =IF(Y10="","",INDEX($AA$5:$AA$323,Y10)) | AA10: =IF(AC10="","","M:"&AC10) | AB10: =IF(Asistencia!A11="","",Asistencia!A11) | AC10: =IF(Asistencia!A11="","",SUBSTITUTE(SUBSTITUTE(SUBSTITUTE(SUBSTITUTE(SUBSTITUTE(SUBSTITUTE(SUBSTITUTE(UPPER(TRIM(Asistencia!A11)),"Á","A"),"É","E"),"Í","I"),"Ó","O"),"Ú","U"),"Ñ","N")," "," ")) | AD10: =IF(Asistencia!E11="","",Asistencia!E11) | AE10: =IF(Asistencia!D11="","",UPPER(TRIM(Asistencia!D11))) | AF10: ARMIDA | AG10: =IF(AND(AA10<>"",COUNTIF($AA$5:AA10,AA10)=1),1,0) -> 0 | AH10: =IF(AG10=1,SUM($AG$5:AG10),"") | AI10: =IF(OR(EXACT(Asistencia!F11,"A"),EXACT(Asistencia!F11,"R"),EXACT(Asistencia!F11,"DL"),EXACT(Asistencia!F11,"FL"),EXACT(Asistencia!F11,"FE"),EXACT(Asistencia!F11,"PCS"),EXACT(Asistencia!F11,"V")),1,0) -> 0 | AJ10: =IF(OR(EXACT(Asistencia!G11,"A"),EXACT(Asistencia!G11,"R"),EXACT(Asistencia!G11,"DL"),EXACT(Asistencia!G11,"FL"),EXACT(Asistencia!G11,"FE"),EXACT(Asistencia!G11,"PCS"),EXACT(Asistencia!G11,"V")),1,0) -> 0 | AK10: =IF(OR(EXACT(Asistencia!H11,"A"),EXACT(Asistencia!H11,"R"),EXACT(Asistencia!H11,"DL"),EXACT(Asistencia!H11,"FL"),EXACT(Asistencia!H11,"FE"),EXACT(Asistencia!H11,"PCS"),EXACT(Asistencia!H11,"V")),1,0) -> 0 | AL10: =IF(OR(EXACT(Asistencia!I11,"A"),EXACT(Asistencia!I11,"R"),EXACT(Asistencia!I11,"DL"),EXACT(Asistencia!I11,"FL"),EXACT(Asistencia!I11,"FE"),EXACT(Asistencia!I11,"PCS"),EXACT(Asistencia!I11,"V")),1,0) -> 0 | AM10: =IF(OR(EXACT(Asistencia!J11,"A"),EXACT(Asistencia!J11,"R"),EXACT(Asistencia!J11,"DL"),EXACT(Asistencia!J11,"FL"),EXACT(Asistencia!J11,"FE"),EXACT(Asistencia!J11,"PCS"),EXACT(Asistencia!J11,"V")),1,0) -> 0 | AN10: =IF(OR(EXACT(Asistencia!K11,"A"),EXACT(Asistencia!K11,"R"),EXACT(Asistencia!K11,"DL"),EXACT(Asistencia!K11,"FL"),EXACT(Asistencia!K11,"FE"),EXACT(Asistencia!K11,"PCS"),EXACT(Asistencia!K11,"V")),1,0) -> 0 | AO10: =IF(OR(EXACT(Asistencia!L11,"A"),EXACT(Asistencia!L11,"R"),EXACT(Asistencia!L11,"DL"),EXACT(Asistencia!L11,"FL"),EXACT(Asistencia!L11,"FE"),EXACT(Asistencia!L11,"PCS"),EXACT(Asistencia!L11,"V")),1,0) -> 0 | AP10: =SUM(AI10:AO10) -> 0 | AQ10: =IF(EXACT(Asistencia!F11,"FL"),1,0) -> 0 | AR10: =IF(EXACT(Asistencia!G11,"FL"),1,0) -> 0 | AS10: =IF(EXACT(Asistencia!H11,"FL"),1,0) -> 0 | AT10: =IF(EXACT(Asistencia!I11,"FL"),1,0) -> 0 | AU10: =IF(EXACT(Asistencia!J11,"FL"),1,0) -> 0 | AV10: =IF(EXACT(Asistencia!K11,"FL"),1,0) -> 0 | AW10: =IF(EXACT(Asistencia!L11,"FL"),1,0) -> 0 | AX10: =SUM(AQ10:AW10) -> 0 | AY10: =IF(EXACT(Asistencia!F11,"DL"),1,0) -> 0 | AZ10: =IF(EXACT(Asistencia!G11,"DL"),1,0) -> 0 | BA10: =IF(EXACT(Asistencia!H11,"DL"),1,0) -> 0 | BB10: =IF(EXACT(Asistencia!I11,"DL"),1,0) -> 0 | BC10: =IF(EXACT(Asistencia!J11,"DL"),1,0) -> 0 | BD10: =IF(EXACT(Asistencia!K11,"DL"),1,0) -> 0 | BE10: =IF(EXACT(Asistencia!L11,"DL"),1,0) -> 0 | BF10: =SUM(AY10:BE10) -> 0 | BG10: =IF(ISNUMBER(Asistencia!M11),Asistencia!M11,0) -> 0 | BH10: =IF(ISNUMBER(Asistencia!N11),Asistencia!N11,0) -> 0 | BI10: =IF(ISNUMBER(Asistencia!O11),Asistencia!O11,0) -> 0 | BJ10: =IF(ISNUMBER(Asistencia!P11),Asistencia!P11,0) -> 0 | BK10: =IF(Asistencia!F11="","",Asistencia!F11) | BL10: =IF(Asistencia!G11="","",Asistencia!G11) | BM10: =IF(Asistencia!H11="","",Asistencia!H11) | BN10: =IF(Asistencia!I11="","",Asistencia!I11) | BO10: =IF(Asistencia!J11="","",Asistencia!J11) | BP10: =IF(Asistencia!K11="","",Asistencia!K11) | BQ10: =IF(Asistencia!L11="","",Asistencia!L11)
A11: =IF(Y11="","",INDEX($AB$5:$AB$323,Y11)) | B11: =IF(Y11="","",INDEX($AD$5:$AD$323,Y11)) | E11: =IF($A11="","",_xlfn.TEXTJOIN(" / ",TRUE(),IF(SUMIFS($AP$5:$AP$323,$AA$5:$AA$323,$Z11,$AF$5:$AF$323,"ARMIDA")>0,IFERROR("ARMIDA-"&INDEX($AE$5:$AE$323,MATCH($Z11&"ARMIDA",$AA$5:$AA$323&$AF$5:$AF$323,0)),"ARMIDA"),""),IF(SUMIFS($AP$5:$AP$323,$AA$5:$AA$323,$Z11,$AF$5:$AF$323,"AURIGA")>0,IFERROR("AURIGA-"&INDEX($AE$5:$AE$323,MATCH($Z11&"AURIGA",$AA$5:$AA$323&$AF$5:$AF$323,0)),"AURIGA"),""),IF(SUMIFS($AP$5:$AP$323,$AA$5:$AA$323,$Z11,$AF$5:$AF$323,"AURORA")>0,IFERROR("AURORA-"&INDEX($AE$5:$AE$323,MATCH($Z11&"AURORA",$AA$5:$AA$323&$AF$5:$AF$323,0)),"AURORA"),""),IF(SUMIFS($AP$5:$AP$323,$AA$5:$AA$323,$Z11,$AF$5:$AF$323,"CITICA")>0,IFERROR("CITICA-"&INDEX($AE$5:$AE$323,MATCH($Z11&"CITICA",$AA$5:$AA$323&$AF$5:$AF$323,0)),"CITICA"),""),IF(SUMIFS($AP$5:$AP$323,$AA$5:$AA$323,$Z11,$AF$5:$AF$323,"GM")>0,IFERROR("GM-"&INDEX($AE$5:$AE$323,MATCH($Z11&"GM",$AA$5:$AA$323&$AF$5:$AF$323,0)),"GM"),""),IF(SUMIFS($AP$5:$AP$323,$AA$5:$AA$323,$Z11,$AF$5:$AF$323,"TORRE BALZAK")>0,IFERROR("TORRE BALZAK-"&INDEX($AE$5:$AE$323,MATCH($Z11&"TORRE BALZAK",$AA$5:$AA$323&$AF$5:$AF$323,0)),"TORRE BALZAK"),""),IF(SUMIFS($AP$5:$AP$323,$AA$5:$AA$323,$Z11,$AF$5:$AF$323,"TORRE OLMA")>0,IFERROR("TORRE OLMA-"&INDEX($AE$5:$AE$323,MATCH($Z11&"TORRE OLMA",$AA$5:$AA$323&$AF$5:$AF$323,0)),"TORRE OLMA"),""),IF(SUMIFS($AP$5:$AP$323,$AA$5:$AA$323,$Z11,$AF$5:$AF$323,"OTROS")>0,IFERROR("OTROS-"&INDEX($AE$5:$AE$323,MATCH($Z11&"OTROS",$AA$5:$AA$323&$AF$5:$AF$323,0)),"OTROS"),""))) | F11: =IF($A11="","",IFERROR(INDEX($BK$5:$BK$323,MATCH($Z11,$AA$5:$AA$323,0)),"-")) | G11: =IF($A11="","",IFERROR(INDEX($BL$5:$BL$323,MATCH($Z11,$AA$5:$AA$323,0)),"-")) | H11: =IF($A11="","",IFERROR(INDEX($BM$5:$BM$323,MATCH($Z11,$AA$5:$AA$323,0)),"-")) | I11: =IF($A11="","",IFERROR(INDEX($BN$5:$BN$323,MATCH($Z11,$AA$5:$AA$323,0)),"-")) | J11: =IF($A11="","",IFERROR(INDEX($BO$5:$BO$323,MATCH($Z11,$AA$5:$AA$323,0)),"-")) | K11: =IF($A11="","",IFERROR(INDEX($BP$5:$BP$323,MATCH($Z11,$AA$5:$AA$323,0)),"-")) | L11: =IF($A11="","",IFERROR(INDEX($BQ$5:$BQ$323,MATCH($Z11,$AA$5:$AA$323,0)),"-")) | M11: =IF($A11="","",(--(SUMIF($AA$5:$AA$323,$Z11,$AI$5:$AI$323)>0))+(--(SUMIF($AA$5:$AA$323,$Z11,$AJ$5:$AJ$323)>0))+(--(SUMIF($AA$5:$AA$323,$Z11,$AK$5:$AK$323)>0))+(--(SUMIF($AA$5:$AA$323,$Z11,$AL$5:$AL$323)>0))+(--(SUMIF($AA$5:$AA$323,$Z11,$AM$5:$AM$323)>0))+(--(SUMIF($AA$5:$AA$323,$Z11,$AN$5:$AN$323)>0))+(--(SUMIF($AA$5:$AA$323,$Z11,$AO$5:$AO$323)>0))) | N11: =IF($A11="","",MAX(0,M11-6)) | O11: =IF($A11="","",SUMIF($AA$5:$AA$323,$Z11,$AP$5:$AP$323)-M11) | P11: =IF($A11="","",SUMIF($AA$5:$AA$323,$Z11,$BG$5:$BG$323)) | Q11: =IF($A11="","",SUMIF($AA$5:$AA$323,$Z11,$BH$5:$BH$323)) | R11: =IF($A11="","",SUMIF($AA$5:$AA$323,$Z11,$BI$5:$BI$323)) | U11: =IF($A11="","",SUMIF($AA$5:$AA$323,$Z11,$BJ$5:$BJ$323)) | W11: =IF($A11="","",_xlfn.TEXTJOIN(" | ",TRUE(),IF(N11>0,"+ de 6 días: revisar adicionales",""),IF(O11>0,"Doble evento mismo día: revisar turno/pago",""),IF(SUMIF($AA$5:$AA$323,$Z11,$AX$5:$AX$323)>((--(SUMIF($AA$5:$AA$323,$Z11,$AQ$5:$AQ$323)>0))+(--(SUMIF($AA$5:$AA$323,$Z11,$AR$5:$AR$323)>0))+(--(SUMIF($AA$5:$AA$323,$Z11,$AS$5:$AS$323)>0))+(--(SUMIF($AA$5:$AA$323,$Z11,$AT$5:$AT$323)>0))+(--(SUMIF($AA$5:$AA$323,$Z11,$AU$5:$AU$323)>0))+(--(SUMIF($AA$5:$AA$323,$Z11,$AV$5:$AV$323)>0))+(--(SUMIF($AA$5:$AA$323,$Z11,$AW$5:$AW$323)>0))),"FL múltiple mismo día: revisar pago festivo",""),IF(SUMIF($AA$5:$AA$323,$Z11,$BF$5:$BF$323)>((--(SUMIF($AA$5:$AA$323,$Z11,$AY$5:$AY$323)>0))+(--(SUMIF($AA$5:$AA$323,$Z11,$AZ$5:$AZ$323)>0))+(--(SUMIF($AA$5:$AA$323,$Z11,$BA$5:$BA$323)>0))+(--(SUMIF($AA$5:$AA$323,$Z11,$BB$5:$BB$323)>0))+(--(SUMIF($AA$5:$AA$323,$Z11,$BC$5:$BC$323)>0))+(--(SUMIF($AA$5:$AA$323,$Z11,$BD$5:$BD$323)>0))+(--(SUMIF($AA$5:$AA$323,$Z11,$BE$5:$BE$323)>0))),"DL múltiple mismo día: revisar pago descanso",""))) | Y11: =IFERROR(MATCH(7,$AH$5:$AH$323,0),"") | Z11: =IF(Y11="","",INDEX($AA$5:$AA$323,Y11)) | AA11: =IF(AC11="","","M:"&AC11) | AB11: =IF(Asistencia!A12="","",Asistencia!A12) | AC11: =IF(Asistencia!A12="","",SUBSTITUTE(SUBSTITUTE(SUBSTITUTE(SUBSTITUTE(SUBSTITUTE(SUBSTITUTE(SUBSTITUTE(UPPER(TRIM(Asistencia!A12)),"Á","A"),"É","E"),"Í","I"),"Ó","O"),"Ú","U"),"Ñ","N")," "," ")) | AD11: =IF(Asistencia!E12="","",Asistencia!E12) | AE11: =IF(Asistencia!D12="","",UPPER(TRIM(Asistencia!D12))) | AF11: ARMIDA | AG11: =IF(AND(AA11<>"",COUNTIF($AA$5:AA11,AA11)=1),1,0) -> 0 | AH11: =IF(AG11=1,SUM($AG$5:AG11),"") | AI11: =IF(OR(EXACT(Asistencia!F12,"A"),EXACT(Asistencia!F12,"R"),EXACT(Asistencia!F12,"DL"),EXACT(Asistencia!F12,"FL"),EXACT(Asistencia!F12,"FE"),EXACT(Asistencia!F12,"PCS"),EXACT(Asistencia!F12,"V")),1,0) -> 0 | AJ11: =IF(OR(EXACT(Asistencia!G12,"A"),EXACT(Asistencia!G12,"R"),EXACT(Asistencia!G12,"DL"),EXACT(Asistencia!G12,"FL"),EXACT(Asistencia!G12,"FE"),EXACT(Asistencia!G12,"PCS"),EXACT(Asistencia!G12,"V")),1,0) -> 0 | AK11: =IF(OR(EXACT(Asistencia!H12,"A"),EXACT(Asistencia!H12,"R"),EXACT(Asistencia!H12,"DL"),EXACT(Asistencia!H12,"FL"),EXACT(Asistencia!H12,"FE"),EXACT(Asistencia!H12,"PCS"),EXACT(Asistencia!H12,"V")),1,0) -> 0 | AL11: =IF(OR(EXACT(Asistencia!I12,"A"),EXACT(Asistencia!I12,"R"),EXACT(Asistencia!I12,"DL"),EXACT(Asistencia!I12,"FL"),EXACT(Asistencia!I12,"FE"),EXACT(Asistencia!I12,"PCS"),EXACT(Asistencia!I12,"V")),1,0) -> 0 | AM11: =IF(OR(EXACT(Asistencia!J12,"A"),EXACT(Asistencia!J12,"R"),EXACT(Asistencia!J12,"DL"),EXACT(Asistencia!J12,"FL"),EXACT(Asistencia!J12,"FE"),EXACT(Asistencia!J12,"PCS"),EXACT(Asistencia!J12,"V")),1,0) -> 0 | AN11: =IF(OR(EXACT(Asistencia!K12,"A"),EXACT(Asistencia!K12,"R"),EXACT(Asistencia!K12,"DL"),EXACT(Asistencia!K12,"FL"),EXACT(Asistencia!K12,"FE"),EXACT(Asistencia!K12,"PCS"),EXACT(Asistencia!K12,"V")),1,0) -> 0 | AO11: =IF(OR(EXACT(Asistencia!L12,"A"),EXACT(Asistencia!L12,"R"),EXACT(Asistencia!L12,"DL"),EXACT(Asistencia!L12,"FL"),EXACT(Asistencia!L12,"FE"),EXACT(Asistencia!L12,"PCS"),EXACT(Asistencia!L12,"V")),1,0) -> 0 | AP11: =SUM(AI11:AO11) -> 0 | AQ11: =IF(EXACT(Asistencia!F12,"FL"),1,0) -> 0 | AR11: =IF(EXACT(Asistencia!G12,"FL"),1,0) -> 0 | AS11: =IF(EXACT(Asistencia!H12,"FL"),1,0) -> 0 | AT11: =IF(EXACT(Asistencia!I12,"FL"),1,0) -> 0 | AU11: =IF(EXACT(Asistencia!J12,"FL"),1,0) -> 0 | AV11: =IF(EXACT(Asistencia!K12,"FL"),1,0) -> 0 | AW11: =IF(EXACT(Asistencia!L12,"FL"),1,0) -> 0 | AX11: =SUM(AQ11:AW11) -> 0 | AY11: =IF(EXACT(Asistencia!F12,"DL"),1,0) -> 0 | AZ11: =IF(EXACT(Asistencia!G12,"DL"),1,0) -> 0 | BA11: =IF(EXACT(Asistencia!H12,"DL"),1,0) -> 0 | BB11: =IF(EXACT(Asistencia!I12,"DL"),1,0) -> 0 | BC11: =IF(EXACT(Asistencia!J12,"DL"),1,0) -> 0 | BD11: =IF(EXACT(Asistencia!K12,"DL"),1,0) -> 0 | BE11: =IF(EXACT(Asistencia!L12,"DL"),1,0) -> 0 | BF11: =SUM(AY11:BE11) -> 0 | BG11: =IF(ISNUMBER(Asistencia!M12),Asistencia!M12,0) -> 0 | BH11: =IF(ISNUMBER(Asistencia!N12),Asistencia!N12,0) -> 0 | BI11: =IF(ISNUMBER(Asistencia!O12),Asistencia!O12,0) -> 0 | BJ11: =IF(ISNUMBER(Asistencia!P12),Asistencia!P12,0) -> 0 | BK11: =IF(Asistencia!F12="","",Asistencia!F12) | BL11: =IF(Asistencia!G12="","",Asistencia!G12) | BM11: =IF(Asistencia!H12="","",Asistencia!H12) | BN11: =IF(Asistencia!I12="","",Asistencia!I12) | BO11: =IF(Asistencia!J12="","",Asistencia!J12) | BP11: =IF(Asistencia!K12="","",Asistencia!K12) | BQ11: =IF(Asistencia!L12="","",Asistencia!L12)
A12: =IF(Y12="","",INDEX($AB$5:$AB$323,Y12)) | B12: =IF(Y12="","",INDEX($AD$5:$AD$323,Y12)) | E12: =IF($A12="","",_xlfn.TEXTJOIN(" / ",TRUE(),IF(SUMIFS($AP$5:$AP$323,$AA$5:$AA$323,$Z12,$AF$5:$AF$323,"ARMIDA")>0,IFERROR("ARMIDA-"&INDEX($AE$5:$AE$323,MATCH($Z12&"ARMIDA",$AA$5:$AA$323&$AF$5:$AF$323,0)),"ARMIDA"),""),IF(SUMIFS($AP$5:$AP$323,$AA$5:$AA$323,$Z12,$AF$5:$AF$323,"AURIGA")>0,IFERROR("AURIGA-"&INDEX($AE$5:$AE$323,MATCH($Z12&"AURIGA",$AA$5:$AA$323&$AF$5:$AF$323,0)),"AURIGA"),""),IF(SUMIFS($AP$5:$AP$323,$AA$5:$AA$323,$Z12,$AF$5:$AF$323,"AURORA")>0,IFERROR("AURORA-"&INDEX($AE$5:$AE$323,MATCH($Z12&"AURORA",$AA$5:$AA$323&$AF$5:$AF$323,0)),"AURORA"),""),IF(SUMIFS($AP$5:$AP$323,$AA$5:$AA$323,$Z12,$AF$5:$AF$323,"CITICA")>0,IFERROR("CITICA-"&INDEX($AE$5:$AE$323,MATCH($Z12&"CITICA",$AA$5:$AA$323&$AF$5:$AF$323,0)),"CITICA"),""),IF(SUMIFS($AP$5:$AP$323,$AA$5:$AA$323,$Z12,$AF$5:$AF$323,"GM")>0,IFERROR("GM-"&INDEX($AE$5:$AE$323,MATCH($Z12&"GM",$AA$5:$AA$323&$AF$5:$AF$323,0)),"GM"),""),IF(SUMIFS($AP$5:$AP$323,$AA$5:$AA$323,$Z12,$AF$5:$AF$323,"TORRE BALZAK")>0,IFERROR("TORRE BALZAK-"&INDEX($AE$5:$AE$323,MATCH($Z12&"TORRE BALZAK",$AA$5:$AA$323&$AF$5:$AF$323,0)),"TORRE BALZAK"),""),IF(SUMIFS($AP$5:$AP$323,$AA$5:$AA$323,$Z12,$AF$5:$AF$323,"TORRE OLMA")>0,IFERROR("TORRE OLMA-"&INDEX($AE$5:$AE$323,MATCH($Z12&"TORRE OLMA",$AA$5:$AA$323&$AF$5:$AF$323,0)),"TORRE OLMA"),""),IF(SUMIFS($AP$5:$AP$323,$AA$5:$AA$323,$Z12,$AF$5:$AF$323,"OTROS")>0,IFERROR("OTROS-"&INDEX($AE$5:$AE$323,MATCH($Z12&"OTROS",$AA$5:$AA$323&$AF$5:$AF$323,0)),"OTROS"),""))) | F12: =IF($A12="","",IFERROR(INDEX($BK$5:$BK$323,MATCH($Z12,$AA$5:$AA$323,0)),"-")) | G12: =IF($A12="","",IFERROR(INDEX($BL$5:$BL$323,MATCH($Z12,$AA$5:$AA$323,0)),"-")) | H12: =IF($A12="","",IFERROR(INDEX($BM$5:$BM$323,MATCH($Z12,$AA$5:$AA$323,0)),"-")) | I12: =IF($A12="","",IFERROR(INDEX($BN$5:$BN$323,MATCH($Z12,$AA$5:$AA$323,0)),"-")) | J12: =IF($A12="","",IFERROR(INDEX($BO$5:$BO$323,MATCH($Z12,$AA$5:$AA$323,0)),"-")) | K12: =IF($A12="","",IFERROR(INDEX($BP$5:$BP$323,MATCH($Z12,$AA$5:$AA$323,0)),"-")) | L12: =IF($A12="","",IFERROR(INDEX($BQ$5:$BQ$323,MATCH($Z12,$AA$5:$AA$323,0)),"-")) | M12: =IF($A12="","",(--(SUMIF($AA$5:$AA$323,$Z12,$AI$5:$AI$323)>0))+(--(SUMIF($AA$5:$AA$323,$Z12,$AJ$5:$AJ$323)>0))+(--(SUMIF($AA$5:$AA$323,$Z12,$AK$5:$AK$323)>0))+(--(SUMIF($AA$5:$AA$323,$Z12,$AL$5:$AL$323)>0))+(--(SUMIF($AA$5:$AA$323,$Z12,$AM$5:$AM$323)>0))+(--(SUMIF($AA$5:$AA$323,$Z12,$AN$5:$AN$323)>0))+(--(SUMIF($AA$5:$AA$323,$Z12,$AO$5:$AO$323)>0))) | N12: =IF($A12="","",MAX(0,M12-6)) | O12: =IF($A12="","",SUMIF($AA$5:$AA$323,$Z12,$AP$5:$AP$323)-M12) | P12: =IF($A12="","",SUMIF($AA$5:$AA$323,$Z12,$BG$5:$BG$323)) | Q12: =IF($A12="","",SUMIF($AA$5:$AA$323,$Z12,$BH$5:$BH$323)) | R12: =IF($A12="","",SUMIF($AA$5:$AA$323,$Z12,$BI$5:$BI$323)) | U12: =IF($A12="","",SUMIF($AA$5:$AA$323,$Z12,$BJ$5:$BJ$323)) | W12: =IF($A12="","",_xlfn.TEXTJOIN(" | ",TRUE(),IF(N12>0,"+ de 6 días: revisar adicionales",""),IF(O12>0,"Doble evento mismo día: revisar turno/pago",""),IF(SUMIF($AA$5:$AA$323,$Z12,$AX$5:$AX$323)>((--(SUMIF($AA$5:$AA$323,$Z12,$AQ$5:$AQ$323)>0))+(--(SUMIF($AA$5:$AA$323,$Z12,$AR$5:$AR$323)>0))+(--(SUMIF($AA$5:$AA$323,$Z12,$AS$5:$AS$323)>0))+(--(SUMIF($AA$5:$AA$323,$Z12,$AT$5:$AT$323)>0))+(--(SUMIF($AA$5:$AA$323,$Z12,$AU$5:$AU$323)>0))+(--(SUMIF($AA$5:$AA$323,$Z12,$AV$5:$AV$323)>0))+(--(SUMIF($AA$5:$AA$323,$Z12,$AW$5:$AW$323)>0))),"FL múltiple mismo día: revisar pago festivo",""),IF(SUMIF($AA$5:$AA$323,$Z12,$BF$5:$BF$323)>((--(SUMIF($AA$5:$AA$323,$Z12,$AY$5:$AY$323)>0))+(--(SUMIF($AA$5:$AA$323,$Z12,$AZ$5:$AZ$323)>0))+(--(SUMIF($AA$5:$AA$323,$Z12,$BA$5:$BA$323)>0))+(--(SUMIF($AA$5:$AA$323,$Z12,$BB$5:$BB$323)>0))+(--(SUMIF($AA$5:$AA$323,$Z12,$BC$5:$BC$323)>0))+(--(SUMIF($AA$5:$AA$323,$Z12,$BD$5:$BD$323)>0))+(--(SUMIF($AA$5:$AA$323,$Z12,$BE$5:$BE$323)>0))),"DL múltiple mismo día: revisar pago descanso",""))) | Y12: =IFERROR(MATCH(8,$AH$5:$AH$323,0),"") | Z12: =IF(Y12="","",INDEX($AA$5:$AA$323,Y12)) | AA12: =IF(AC12="","","M:"&AC12) | AB12: =IF(Asistencia!A13="","",Asistencia!A13) | AC12: =IF(Asistencia!A13="","",SUBSTITUTE(SUBSTITUTE(SUBSTITUTE(SUBSTITUTE(SUBSTITUTE(SUBSTITUTE(SUBSTITUTE(UPPER(TRIM(Asistencia!A13)),"Á","A"),"É","E"),"Í","I"),"Ó","O"),"Ú","U"),"Ñ","N")," "," ")) | AD12: =IF(Asistencia!E13="","",Asistencia!E13) | AE12: =IF(Asistencia!D13="","",UPPER(TRIM(Asistencia!D13))) | AF12: ARMIDA | AG12: =IF(AND(AA12<>"",COUNTIF($AA$5:AA12,AA12)=1),1,0) -> 0 | AH12: =IF(AG12=1,SUM($AG$5:AG12),"") | AI12: =IF(OR(EXACT(Asistencia!F13,"A"),EXACT(Asistencia!F13,"R"),EXACT(Asistencia!F13,"DL"),EXACT(Asistencia!F13,"FL"),EXACT(Asistencia!F13,"FE"),EXACT(Asistencia!F13,"PCS"),EXACT(Asistencia!F13,"V")),1,0) -> 0 | AJ12: =IF(OR(EXACT(Asistencia!G13,"A"),EXACT(Asistencia!G13,"R"),EXACT(Asistencia!G13,"DL"),EXACT(Asistencia!G13,"FL"),EXACT(Asistencia!G13,"FE"),EXACT(Asistencia!G13,"PCS"),EXACT(Asistencia!G13,"V")),1,0) -> 0 | AK12: =IF(OR(EXACT(Asistencia!H13,"A"),EXACT(Asistencia!H13,"R"),EXACT(Asistencia!H13,"DL"),EXACT(Asistencia!H13,"FL"),EXACT(Asistencia!H13,"FE"),EXACT(Asistencia!H13,"PCS"),EXACT(Asistencia!H13,"V")),1,0) -> 0 | AL12: =IF(OR(EXACT(Asistencia!I13,"A"),EXACT(Asistencia!I13,"R"),EXACT(Asistencia!I13,"DL"),EXACT(Asistencia!I13,"FL"),EXACT(Asistencia!I13,"FE"),EXACT(Asistencia!I13,"PCS"),EXACT(Asistencia!I13,"V")),1,0) -> 0 | AM12: =IF(OR(EXACT(Asistencia!J13,"A"),EXACT(Asistencia!J13,"R"),EXACT(Asistencia!J13,"DL"),EXACT(Asistencia!J13,"FL"),EXACT(Asistencia!J13,"FE"),EXACT(Asistencia!J13,"PCS"),EXACT(Asistencia!J13,"V")),1,0) -> 0 | AN12: =IF(OR(EXACT(Asistencia!K13,"A"),EXACT(Asistencia!K13,"R"),EXACT(Asistencia!K13,"DL"),EXACT(Asistencia!K13,"FL"),EXACT(Asistencia!K13,"FE"),EXACT(Asistencia!K13,"PCS"),EXACT(Asistencia!K13,"V")),1,0) -> 0 | AO12: =IF(OR(EXACT(Asistencia!L13,"A"),EXACT(Asistencia!L13,"R"),EXACT(Asistencia!L13,"DL"),EXACT(Asistencia!L13,"FL"),EXACT(Asistencia!L13,"FE"),EXACT(Asistencia!L13,"PCS"),EXACT(Asistencia!L13,"V")),1,0) -> 0 | AP12: =SUM(AI12:AO12) -> 0 | AQ12: =IF(EXACT(Asistencia!F13,"FL"),1,0) -> 0 | AR12: =IF(EXACT(Asistencia!G13,"FL"),1,0) -> 0 | AS12: =IF(EXACT(Asistencia!H13,"FL"),1,0) -> 0 | AT12: =IF(EXACT(Asistencia!I13,"FL"),1,0) -> 0 | AU12: =IF(EXACT(Asistencia!J13,"FL"),1,0) -> 0 | AV12: =IF(EXACT(Asistencia!K13,"FL"),1,0) -> 0 | AW12: =IF(EXACT(Asistencia!L13,"FL"),1,0) -> 0 | AX12: =SUM(AQ12:AW12) -> 0 | AY12: =IF(EXACT(Asistencia!F13,"DL"),1,0) -> 0 | AZ12: =IF(EXACT(Asistencia!G13,"DL"),1,0) -> 0 | BA12: =IF(EXACT(Asistencia!H13,"DL"),1,0) -> 0 | BB12: =IF(EXACT(Asistencia!I13,"DL"),1,0) -> 0 | BC12: =IF(EXACT(Asistencia!J13,"DL"),1,0) -> 0 | BD12: =IF(EXACT(Asistencia!K13,"DL"),1,0) -> 0 | BE12: =IF(EXACT(Asistencia!L13,"DL"),1,0) -> 0 | BF12: =SUM(AY12:BE12) -> 0 | BG12: =IF(ISNUMBER(Asistencia!M13),Asistencia!M13,0) -> 0 | BH12: =IF(ISNUMBER(Asistencia!N13),Asistencia!N13,0) -> 0 | BI12: =IF(ISNUMBER(Asistencia!O13),Asistencia!O13,0) -> 0 | BJ12: =IF(ISNUMBER(Asistencia!P13),Asistencia!P13,0) -> 0 | BK12: =IF(Asistencia!F13="","",Asistencia!F13) | BL12: =IF(Asistencia!G13="","",Asistencia!G13) | BM12: =IF(Asistencia!H13="","",Asistencia!H13) | BN12: =IF(Asistencia!I13="","",Asistencia!I13) | BO12: =IF(Asistencia!J13="","",Asistencia!J13) | BP12: =IF(Asistencia!K13="","",Asistencia!K13) | BQ12: =IF(Asistencia!L13="","",Asistencia!L13)
A13: =IF(Y13="","",INDEX($AB$5:$AB$323,Y13)) | B13: =IF(Y13="","",INDEX($AD$5:$AD$323,Y13)) | E13: =IF($A13="","",_xlfn.TEXTJOIN(" / ",TRUE(),IF(SUMIFS($AP$5:$AP$323,$AA$5:$AA$323,$Z13,$AF$5:$AF$323,"ARMIDA")>0,IFERROR("ARMIDA-"&INDEX($AE$5:$AE$323,MATCH($Z13&"ARMIDA",$AA$5:$AA$323&$AF$5:$AF$323,0)),"ARMIDA"),""),IF(SUMIFS($AP$5:$AP$323,$AA$5:$AA$323,$Z13,$AF$5:$AF$323,"AURIGA")>0,IFERROR("AURIGA-"&INDEX($AE$5:$AE$323,MATCH($Z13&"AURIGA",$AA$5:$AA$323&$AF$5:$AF$323,0)),"AURIGA"),""),IF(SUMIFS($AP$5:$AP$323,$AA$5:$AA$323,$Z13,$AF$5:$AF$323,"AURORA")>0,IFERROR("AURORA-"&INDEX($AE$5:$AE$323,MATCH($Z13&"AURORA",$AA$5:$AA$323&$AF$5:$AF$323,0)),"AURORA"),""),IF(SUMIFS($AP$5:$AP$323,$AA$5:$AA$323,$Z13,$AF$5:$AF$323,"CITICA")>0,IFERROR("CITICA-"&INDEX($AE$5:$AE$323,MATCH($Z13&"CITICA",$AA$5:$AA$323&$AF$5:$AF$323,0)),"CITICA"),""),IF(SUMIFS($AP$5:$AP$323,$AA$5:$AA$323,$Z13,$AF$5:$AF$323,"GM")>0,IFERROR("GM-"&INDEX($AE$5:$AE$323,MATCH($Z13&"GM",$AA$5:$AA$323&$AF$5:$AF$323,0)),"GM"),""),IF(SUMIFS($AP$5:$AP$323,$AA$5:$AA$323,$Z13,$AF$5:$AF$323,"TORRE BALZAK")>0,IFERROR("TORRE BALZAK-"&INDEX($AE$5:$AE$323,MATCH($Z13&"TORRE BALZAK",$AA$5:$AA$323&$AF$5:$AF$323,0)),"TORRE BALZAK"),""),IF(SUMIFS($AP$5:$AP$323,$AA$5:$AA$323,$Z13,$AF$5:$AF$323,"TORRE OLMA")>0,IFERROR("TORRE OLMA-"&INDEX($AE$5:$AE$323,MATCH($Z13&"TORRE OLMA",$AA$5:$AA$323&$AF$5:$AF$323,0)),"TORRE OLMA"),""),IF(SUMIFS($AP$5:$AP$323,$AA$5:$AA$323,$Z13,$AF$5:$AF$323,"OTROS")>0,IFERROR("OTROS-"&INDEX($AE$5:$AE$323,MATCH($Z13&"OTROS",$AA$5:$AA$323&$AF$5:$AF$323,0)),"OTROS"),""))) | F13: =IF($A13="","",IFERROR(INDEX($BK$5:$BK$323,MATCH($Z13,$AA$5:$AA$323,0)),"-")) | G13: =IF($A13="","",IFERROR(INDEX($BL$5:$BL$323,MATCH($Z13,$AA$5:$AA$323,0)),"-")) | H13: =IF($A13="","",IFERROR(INDEX($BM$5:$BM$323,MATCH($Z13,$AA$5:$AA$323,0)),"-")) | I13: =IF($A13="","",IFERROR(INDEX($BN$5:$BN$323,MATCH($Z13,$AA$5:$AA$323,0)),"-")) | J13: =IF($A13="","",IFERROR(INDEX($BO$5:$BO$323,MATCH($Z13,$AA$5:$AA$323,0)),"-")) | K13: =IF($A13="","",IFERROR(INDEX($BP$5:$BP$323,MATCH($Z13,$AA$5:$AA$323,0)),"-")) | L13: =IF($A13="","",IFERROR(INDEX($BQ$5:$BQ$323,MATCH($Z13,$AA$5:$AA$323,0)),"-")) | M13: =IF($A13="","",(--(SUMIF($AA$5:$AA$323,$Z13,$AI$5:$AI$323)>0))+(--(SUMIF($AA$5:$AA$323,$Z13,$AJ$5:$AJ$323)>0))+(--(SUMIF($AA$5:$AA$323,$Z13,$AK$5:$AK$323)>0))+(--(SUMIF($AA$5:$AA$323,$Z13,$AL$5:$AL$323)>0))+(--(SUMIF($AA$5:$AA$323,$Z13,$AM$5:$AM$323)>0))+(--(SUMIF($AA$5:$AA$323,$Z13,$AN$5:$AN$323)>0))+(--(SUMIF($AA$5:$AA$323,$Z13,$AO$5:$AO$323)>0))) | N13: =IF($A13="","",MAX(0,M13-6)) | O13: =IF($A13="","",SUMIF($AA$5:$AA$323,$Z13,$AP$5:$AP$323)-M13) | P13: =IF($A13="","",SUMIF($AA$5:$AA$323,$Z13,$BG$5:$BG$323)) | Q13: =IF($A13="","",SUMIF($AA$5:$AA$323,$Z13,$BH$5:$BH$323)) | R13: =IF($A13="","",SUMIF($AA$5:$AA$323,$Z13,$BI$5:$BI$323)) | U13: =IF($A13="","",SUMIF($AA$5:$AA$323,$Z13,$BJ$5:$BJ$323)) | W13: =IF($A13="","",_xlfn.TEXTJOIN(" | ",TRUE(),IF(N13>0,"+ de 6 días: revisar adicionales",""),IF(O13>0,"Doble evento mismo día: revisar turno/pago",""),IF(SUMIF($AA$5:$AA$323,$Z13,$AX$5:$AX$323)>((--(SUMIF($AA$5:$AA$323,$Z13,$AQ$5:$AQ$323)>0))+(--(SUMIF($AA$5:$AA$323,$Z13,$AR$5:$AR$323)>0))+(--(SUMIF($AA$5:$AA$323,$Z13,$AS$5:$AS$323)>0))+(--(SUMIF($AA$5:$AA$323,$Z13,$AT$5:$AT$323)>0))+(--(SUMIF($AA$5:$AA$323,$Z13,$AU$5:$AU$323)>0))+(--(SUMIF($AA$5:$AA$323,$Z13,$AV$5:$AV$323)>0))+(--(SUMIF($AA$5:$AA$323,$Z13,$AW$5:$AW$323)>0))),"FL múltiple mismo día: revisar pago festivo",""),IF(SUMIF($AA$5:$AA$323,$Z13,$BF$5:$BF$323)>((--(SUMIF($AA$5:$AA$323,$Z13,$AY$5:$AY$323)>0))+(--(SUMIF($AA$5:$AA$323,$Z13,$AZ$5:$AZ$323)>0))+(--(SUMIF($AA$5:$AA$323,$Z13,$BA$5:$BA$323)>0))+(--(SUMIF($AA$5:$AA$323,$Z13,$BB$5:$BB$323)>0))+(--(SUMIF($AA$5:$AA$323,$Z13,$BC$5:$BC$323)>0))+(--(SUMIF($AA$5:$AA$323,$Z13,$BD$5:$BD$323)>0))+(--(SUMIF($AA$5:$AA$323,$Z13,$BE$5:$BE$323)>0))),"DL múltiple mismo día: revisar pago descanso",""))) | Y13: =IFERROR(MATCH(9,$AH$5:$AH$323,0),"") | Z13: =IF(Y13="","",INDEX($AA$5:$AA$323,Y13)) | AA13: =IF(AC13="","","M:"&AC13) | AB13: =IF(Asistencia!A14="","",Asistencia!A14) | AC13: =IF(Asistencia!A14="","",SUBSTITUTE(SUBSTITUTE(SUBSTITUTE(SUBSTITUTE(SUBSTITUTE(SUBSTITUTE(SUBSTITUTE(UPPER(TRIM(Asistencia!A14)),"Á","A"),"É","E"),"Í","I"),"Ó","O"),"Ú","U"),"Ñ","N")," "," ")) | AD13: =IF(Asistencia!E14="","",Asistencia!E14) | AE13: =IF(Asistencia!D14="","",UPPER(TRIM(Asistencia!D14))) | AF13: ARMIDA | AG13: =IF(AND(AA13<>"",COUNTIF($AA$5:AA13,AA13)=1),1,0) -> 0 | AH13: =IF(AG13=1,SUM($AG$5:AG13),"") | AI13: =IF(OR(EXACT(Asistencia!F14,"A"),EXACT(Asistencia!F14,"R"),EXACT(Asistencia!F14,"DL"),EXACT(Asistencia!F14,"FL"),EXACT(Asistencia!F14,"FE"),EXACT(Asistencia!F14,"PCS"),EXACT(Asistencia!F14,"V")),1,0) -> 0 | AJ13: =IF(OR(EXACT(Asistencia!G14,"A"),EXACT(Asistencia!G14,"R"),EXACT(Asistencia!G14,"DL"),EXACT(Asistencia!G14,"FL"),EXACT(Asistencia!G14,"FE"),EXACT(Asistencia!G14,"PCS"),EXACT(Asistencia!G14,"V")),1,0) -> 0 | AK13: =IF(OR(EXACT(Asistencia!H14,"A"),EXACT(Asistencia!H14,"R"),EXACT(Asistencia!H14,"DL"),EXACT(Asistencia!H14,"FL"),EXACT(Asistencia!H14,"FE"),EXACT(Asistencia!H14,"PCS"),EXACT(Asistencia!H14,"V")),1,0) -> 0 | AL13: =IF(OR(EXACT(Asistencia!I14,"A"),EXACT(Asistencia!I14,"R"),EXACT(Asistencia!I14,"DL"),EXACT(Asistencia!I14,"FL"),EXACT(Asistencia!I14,"FE"),EXACT(Asistencia!I14,"PCS"),EXACT(Asistencia!I14,"V")),1,0) -> 0 | AM13: =IF(OR(EXACT(Asistencia!J14,"A"),EXACT(Asistencia!J14,"R"),EXACT(Asistencia!J14,"DL"),EXACT(Asistencia!J14,"FL"),EXACT(Asistencia!J14,"FE"),EXACT(Asistencia!J14,"PCS"),EXACT(Asistencia!J14,"V")),1,0) -> 0 | AN13: =IF(OR(EXACT(Asistencia!K14,"A"),EXACT(Asistencia!K14,"R"),EXACT(Asistencia!K14,"DL"),EXACT(Asistencia!K14,"FL"),EXACT(Asistencia!K14,"FE"),EXACT(Asistencia!K14,"PCS"),EXACT(Asistencia!K14,"V")),1,0) -> 0 | AO13: =IF(OR(EXACT(Asistencia!L14,"A"),EXACT(Asistencia!L14,"R"),EXACT(Asistencia!L14,"DL"),EXACT(Asistencia!L14,"FL"),EXACT(Asistencia!L14,"FE"),EXACT(Asistencia!L14,"PCS"),EXACT(Asistencia!L14,"V")),1,0) -> 0 | AP13: =SUM(AI13:AO13) -> 0 | AQ13: =IF(EXACT(Asistencia!F14,"FL"),1,0) -> 0 | AR13: =IF(EXACT(Asistencia!G14,"FL"),1,0) -> 0 | AS13: =IF(EXACT(Asistencia!H14,"FL"),1,0) -> 0 | AT13: =IF(EXACT(Asistencia!I14,"FL"),1,0) -> 0 | AU13: =IF(EXACT(Asistencia!J14,"FL"),1,0) -> 0 | AV13: =IF(EXACT(Asistencia!K14,"FL"),1,0) -> 0 | AW13: =IF(EXACT(Asistencia!L14,"FL"),1,0) -> 0 | AX13: =SUM(AQ13:AW13) -> 0 | AY13: =IF(EXACT(Asistencia!F14,"DL"),1,0) -> 0 | AZ13: =IF(EXACT(Asistencia!G14,"DL"),1,0) -> 0 | BA13: =IF(EXACT(Asistencia!H14,"DL"),1,0) -> 0 | BB13: =IF(EXACT(Asistencia!I14,"DL"),1,0) -> 0 | BC13: =IF(EXACT(Asistencia!J14,"DL"),1,0) -> 0 | BD13: =IF(EXACT(Asistencia!K14,"DL"),1,0) -> 0 | BE13: =IF(EXACT(Asistencia!L14,"DL"),1,0) -> 0 | BF13: =SUM(AY13:BE13) -> 0 | BG13: =IF(ISNUMBER(Asistencia!M14),Asistencia!M14,0) -> 0 | BH13: =IF(ISNUMBER(Asistencia!N14),Asistencia!N14,0) -> 0 | BI13: =IF(ISNUMBER(Asistencia!O14),Asistencia!O14,0) -> 0 | BJ13: =IF(ISNUMBER(Asistencia!P14),Asistencia!P14,0) -> 0 | BK13: =IF(Asistencia!F14="","",Asistencia!F14) | BL13: =IF(Asistencia!G14="","",Asistencia!G14) | BM13: =IF(Asistencia!H14="","",Asistencia!H14) | BN13: =IF(Asistencia!I14="","",Asistencia!I14) | BO13: =IF(Asistencia!J14="","",Asistencia!J14) | BP13: =IF(Asistencia!K14="","",Asistencia!K14) | BQ13: =IF(Asistencia!L14="","",Asistencia!L14)
A14: =IF(Y14="","",INDEX($AB$5:$AB$323,Y14)) | B14: =IF(Y14="","",INDEX($AD$5:$AD$323,Y14)) | E14: =IF($A14="","",_xlfn.TEXTJOIN(" / ",TRUE(),IF(SUMIFS($AP$5:$AP$323,$AA$5:$AA$323,$Z14,$AF$5:$AF$323,"ARMIDA")>0,IFERROR("ARMIDA-"&INDEX($AE$5:$AE$323,MATCH($Z14&"ARMIDA",$AA$5:$AA$323&$AF$5:$AF$323,0)),"ARMIDA"),""),IF(SUMIFS($AP$5:$AP$323,$AA$5:$AA$323,$Z14,$AF$5:$AF$323,"AURIGA")>0,IFERROR("AURIGA-"&INDEX($AE$5:$AE$323,MATCH($Z14&"AURIGA",$AA$5:$AA$323&$AF$5:$AF$323,0)),"AURIGA"),""),IF(SUMIFS($AP$5:$AP$323,$AA$5:$AA$323,$Z14,$AF$5:$AF$323,"AURORA")>0,IFERROR("AURORA-"&INDEX($AE$5:$AE$323,MATCH($Z14&"AURORA",$AA$5:$AA$323&$AF$5:$AF$323,0)),"AURORA"),""),IF(SUMIFS($AP$5:$AP$323,$AA$5:$AA$323,$Z14,$AF$5:$AF$323,"CITICA")>0,IFERROR("CITICA-"&INDEX($AE$5:$AE$323,MATCH($Z14&"CITICA",$AA$5:$AA$323&$AF$5:$AF$323,0)),"CITICA"),""),IF(SUMIFS($AP$5:$AP$323,$AA$5:$AA$323,$Z14,$AF$5:$AF$323,"GM")>0,IFERROR("GM-"&INDEX($AE$5:$AE$323,MATCH($Z14&"GM",$AA$5:$AA$323&$AF$5:$AF$323,0)),"GM"),""),IF(SUMIFS($AP$5:$AP$323,$AA$5:$AA$323,$Z14,$AF$5:$AF$323,"TORRE BALZAK")>0,IFERROR("TORRE BALZAK-"&INDEX($AE$5:$AE$323,MATCH($Z14&"TORRE BALZAK",$AA$5:$AA$323&$AF$5:$AF$323,0)),"TORRE BALZAK"),""),IF(SUMIFS($AP$5:$AP$323,$AA$5:$AA$323,$Z14,$AF$5:$AF$323,"TORRE OLMA")>0,IFERROR("TORRE OLMA-"&INDEX($AE$5:$AE$323,MATCH($Z14&"TORRE OLMA",$AA$5:$AA$323&$AF$5:$AF$323,0)),"TORRE OLMA"),""),IF(SUMIFS($AP$5:$AP$323,$AA$5:$AA$323,$Z14,$AF$5:$AF$323,"OTROS")>0,IFERROR("OTROS-"&INDEX($AE$5:$AE$323,MATCH($Z14&"OTROS",$AA$5:$AA$323&$AF$5:$AF$323,0)),"OTROS"),""))) | F14: =IF($A14="","",IFERROR(INDEX($BK$5:$BK$323,MATCH($Z14,$AA$5:$AA$323,0)),"-")) | G14: =IF($A14="","",IFERROR(INDEX($BL$5:$BL$323,MATCH($Z14,$AA$5:$AA$323,0)),"-")) | H14: =IF($A14="","",IFERROR(INDEX($BM$5:$BM$323,MATCH($Z14,$AA$5:$AA$323,0)),"-")) | I14: =IF($A14="","",IFERROR(INDEX($BN$5:$BN$323,MATCH($Z14,$AA$5:$AA$323,0)),"-")) | J14: =IF($A14="","",IFERROR(INDEX($BO$5:$BO$323,MATCH($Z14,$AA$5:$AA$323,0)),"-")) | K14: =IF($A14="","",IFERROR(INDEX($BP$5:$BP$323,MATCH($Z14,$AA$5:$AA$323,0)),"-")) | L14: =IF($A14="","",IFERROR(INDEX($BQ$5:$BQ$323,MATCH($Z14,$AA$5:$AA$323,0)),"-")) | M14: =IF($A14="","",(--(SUMIF($AA$5:$AA$323,$Z14,$AI$5:$AI$323)>0))+(--(SUMIF($AA$5:$AA$323,$Z14,$AJ$5:$AJ$323)>0))+(--(SUMIF($AA$5:$AA$323,$Z14,$AK$5:$AK$323)>0))+(--(SUMIF($AA$5:$AA$323,$Z14,$AL$5:$AL$323)>0))+(--(SUMIF($AA$5:$AA$323,$Z14,$AM$5:$AM$323)>0))+(--(SUMIF($AA$5:$AA$323,$Z14,$AN$5:$AN$323)>0))+(--(SUMIF($AA$5:$AA$323,$Z14,$AO$5:$AO$323)>0))) | N14: =IF($A14="","",MAX(0,M14-6)) | O14: =IF($A14="","",SUMIF($AA$5:$AA$323,$Z14,$AP$5:$AP$323)-M14) | P14: =IF($A14="","",SUMIF($AA$5:$AA$323,$Z14,$BG$5:$BG$323)) | Q14: =IF($A14="","",SUMIF($AA$5:$AA$323,$Z14,$BH$5:$BH$323)) | R14: =IF($A14="","",SUMIF($AA$5:$AA$323,$Z14,$BI$5:$BI$323)) | U14: =IF($A14="","",SUMIF($AA$5:$AA$323,$Z14,$BJ$5:$BJ$323)) | W14: =IF($A14="","",_xlfn.TEXTJOIN(" | ",TRUE(),IF(N14>0,"+ de 6 días: revisar adicionales",""),IF(O14>0,"Doble evento mismo día: revisar turno/pago",""),IF(SUMIF($AA$5:$AA$323,$Z14,$AX$5:$AX$323)>((--(SUMIF($AA$5:$AA$323,$Z14,$AQ$5:$AQ$323)>0))+(--(SUMIF($AA$5:$AA$323,$Z14,$AR$5:$AR$323)>0))+(--(SUMIF($AA$5:$AA$323,$Z14,$AS$5:$AS$323)>0))+(--(SUMIF($AA$5:$AA$323,$Z14,$AT$5:$AT$323)>0))+(--(SUMIF($AA$5:$AA$323,$Z14,$AU$5:$AU$323)>0))+(--(SUMIF($AA$5:$AA$323,$Z14,$AV$5:$AV$323)>0))+(--(SUMIF($AA$5:$AA$323,$Z14,$AW$5:$AW$323)>0))),"FL múltiple mismo día: revisar pago festivo",""),IF(SUMIF($AA$5:$AA$323,$Z14,$BF$5:$BF$323)>((--(SUMIF($AA$5:$AA$323,$Z14,$AY$5:$AY$323)>0))+(--(SUMIF($AA$5:$AA$323,$Z14,$AZ$5:$AZ$323)>0))+(--(SUMIF($AA$5:$AA$323,$Z14,$BA$5:$BA$323)>0))+(--(SUMIF($AA$5:$AA$323,$Z14,$BB$5:$BB$323)>0))+(--(SUMIF($AA$5:$AA$323,$Z14,$BC$5:$BC$323)>0))+(--(SUMIF($AA$5:$AA$323,$Z14,$BD$5:$BD$323)>0))+(--(SUMIF($AA$5:$AA$323,$Z14,$BE$5:$BE$323)>0))),"DL múltiple mismo día: revisar pago descanso",""))) | Y14: =IFERROR(MATCH(10,$AH$5:$AH$323,0),"") | Z14: =IF(Y14="","",INDEX($AA$5:$AA$323,Y14)) | AA14: =IF(AC14="","","M:"&AC14) | AB14: =IF(Asistencia!A15="","",Asistencia!A15) | AC14: =IF(Asistencia!A15="","",SUBSTITUTE(SUBSTITUTE(SUBSTITUTE(SUBSTITUTE(SUBSTITUTE(SUBSTITUTE(SUBSTITUTE(UPPER(TRIM(Asistencia!A15)),"Á","A"),"É","E"),"Í","I"),"Ó","O"),"Ú","U"),"Ñ","N")," "," ")) | AD14: =IF(Asistencia!E15="","",Asistencia!E15) | AE14: =IF(Asistencia!D15="","",UPPER(TRIM(Asistencia!D15))) | AF14: ARMIDA | AG14: =IF(AND(AA14<>"",COUNTIF($AA$5:AA14,AA14)=1),1,0) -> 0 | AH14: =IF(AG14=1,SUM($AG$5:AG14),"") | AI14: =IF(OR(EXACT(Asistencia!F15,"A"),EXACT(Asistencia!F15,"R"),EXACT(Asistencia!F15,"DL"),EXACT(Asistencia!F15,"FL"),EXACT(Asistencia!F15,"FE"),EXACT(Asistencia!F15,"PCS"),EXACT(Asistencia!F15,"V")),1,0) -> 0 | AJ14: =IF(OR(EXACT(Asistencia!G15,"A"),EXACT(Asistencia!G15,"R"),EXACT(Asistencia!G15,"DL"),EXACT(Asistencia!G15,"FL"),EXACT(Asistencia!G15,"FE"),EXACT(Asistencia!G15,"PCS"),EXACT(Asistencia!G15,"V")),1,0) -> 0 | AK14: =IF(OR(EXACT(Asistencia!H15,"A"),EXACT(Asistencia!H15,"R"),EXACT(Asistencia!H15,"DL"),EXACT(Asistencia!H15,"FL"),EXACT(Asistencia!H15,"FE"),EXACT(Asistencia!H15,"PCS"),EXACT(Asistencia!H15,"V")),1,0) -> 0 | AL14: =IF(OR(EXACT(Asistencia!I15,"A"),EXACT(Asistencia!I15,"R"),EXACT(Asistencia!I15,"DL"),EXACT(Asistencia!I15,"FL"),EXACT(Asistencia!I15,"FE"),EXACT(Asistencia!I15,"PCS"),EXACT(Asistencia!I15,"V")),1,0) -> 0 | AM14: =IF(OR(EXACT(Asistencia!J15,"A"),EXACT(Asistencia!J15,"R"),EXACT(Asistencia!J15,"DL"),EXACT(Asistencia!J15,"FL"),EXACT(Asistencia!J15,"FE"),EXACT(Asistencia!J15,"PCS"),EXACT(Asistencia!J15,"V")),1,0) -> 0 | AN14: =IF(OR(EXACT(Asistencia!K15,"A"),EXACT(Asistencia!K15,"R"),EXACT(Asistencia!K15,"DL"),EXACT(Asistencia!K15,"FL"),EXACT(Asistencia!K15,"FE"),EXACT(Asistencia!K15,"PCS"),EXACT(Asistencia!K15,"V")),1,0) -> 0 | AO14: =IF(OR(EXACT(Asistencia!L15,"A"),EXACT(Asistencia!L15,"R"),EXACT(Asistencia!L15,"DL"),EXACT(Asistencia!L15,"FL"),EXACT(Asistencia!L15,"FE"),EXACT(Asistencia!L15,"PCS"),EXACT(Asistencia!L15,"V")),1,0) -> 0 | AP14: =SUM(AI14:AO14) -> 0 | AQ14: =IF(EXACT(Asistencia!F15,"FL"),1,0) -> 0 | AR14: =IF(EXACT(Asistencia!G15,"FL"),1,0) -> 0 | AS14: =IF(EXACT(Asistencia!H15,"FL"),1,0) -> 0 | AT14: =IF(EXACT(Asistencia!I15,"FL"),1,0) -> 0 | AU14: =IF(EXACT(Asistencia!J15,"FL"),1,0) -> 0 | AV14: =IF(EXACT(Asistencia!K15,"FL"),1,0) -> 0 | AW14: =IF(EXACT(Asistencia!L15,"FL"),1,0) -> 0 | AX14: =SUM(AQ14:AW14) -> 0 | AY14: =IF(EXACT(Asistencia!F15,"DL"),1,0) -> 0 | AZ14: =IF(EXACT(Asistencia!G15,"DL"),1,0) -> 0 | BA14: =IF(EXACT(Asistencia!H15,"DL"),1,0) -> 0 | BB14: =IF(EXACT(Asistencia!I15,"DL"),1,0) -> 0 | BC14: =IF(EXACT(Asistencia!J15,"DL"),1,0) -> 0 | BD14: =IF(EXACT(Asistencia!K15,"DL"),1,0) -> 0 | BE14: =IF(EXACT(Asistencia!L15,"DL"),1,0) -> 0 | BF14: =SUM(AY14:BE14) -> 0 | BG14: =IF(ISNUMBER(Asistencia!M15),Asistencia!M15,0) -> 0 | BH14: =IF(ISNUMBER(Asistencia!N15),Asistencia!N15,0) -> 0 | BI14: =IF(ISNUMBER(Asistencia!O15),Asistencia!O15,0) -> 0 | BJ14: =IF(ISNUMBER(Asistencia!P15),Asistencia!P15,0) -> 0 | BK14: =IF(Asistencia!F15="","",Asistencia!F15) | BL14: =IF(Asistencia!G15="","",Asistencia!G15) | BM14: =IF(Asistencia!H15="","",Asistencia!H15) | BN14: =IF(Asistencia!I15="","",Asistencia!I15) | BO14: =IF(Asistencia!J15="","",Asistencia!J15) | BP14: =IF(Asistencia!K15="","",Asistencia!K15) | BQ14: =IF(Asistencia!L15="","",Asistencia!L15)
A15: =IF(Y15="","",INDEX($AB$5:$AB$323,Y15)) | B15: =IF(Y15="","",INDEX($AD$5:$AD$323,Y15)) | E15: =IF($A15="","",_xlfn.TEXTJOIN(" / ",TRUE(),IF(SUMIFS($AP$5:$AP$323,$AA$5:$AA$323,$Z15,$AF$5:$AF$323,"ARMIDA")>0,IFERROR("ARMIDA-"&INDEX($AE$5:$AE$323,MATCH($Z15&"ARMIDA",$AA$5:$AA$323&$AF$5:$AF$323,0)),"ARMIDA"),""),IF(SUMIFS($AP$5:$AP$323,$AA$5:$AA$323,$Z15,$AF$5:$AF$323,"AURIGA")>0,IFERROR("AURIGA-"&INDEX($AE$5:$AE$323,MATCH($Z15&"AURIGA",$AA$5:$AA$323&$AF$5:$AF$323,0)),"AURIGA"),""),IF(SUMIFS($AP$5:$AP$323,$AA$5:$AA$323,$Z15,$AF$5:$AF$323,"AURORA")>0,IFERROR("AURORA-"&INDEX($AE$5:$AE$323,MATCH($Z15&"AURORA",$AA$5:$AA$323&$AF$5:$AF$323,0)),"AURORA"),""),IF(SUMIFS($AP$5:$AP$323,$AA$5:$AA$323,$Z15,$AF$5:$AF$323,"CITICA")>0,IFERROR("CITICA-"&INDEX($AE$5:$AE$323,MATCH($Z15&"CITICA",$AA$5:$AA$323&$AF$5:$AF$323,0)),"CITICA"),""),IF(SUMIFS($AP$5:$AP$323,$AA$5:$AA$323,$Z15,$AF$5:$AF$323,"GM")>0,IFERROR("GM-"&INDEX($AE$5:$AE$323,MATCH($Z15&"GM",$AA$5:$AA$323&$AF$5:$AF$323,0)),"GM"),""),IF(SUMIFS($AP$5:$AP$323,$AA$5:$AA$323,$Z15,$AF$5:$AF$323,"TORRE BALZAK")>0,IFERROR("TORRE BALZAK-"&INDEX($AE$5:$AE$323,MATCH($Z15&"TORRE BALZAK",$AA$5:$AA$323&$AF$5:$AF$323,0)),"TORRE BALZAK"),""),IF(SUMIFS($AP$5:$AP$323,$AA$5:$AA$323,$Z15,$AF$5:$AF$323,"TORRE OLMA")>0,IFERROR("TORRE OLMA-"&INDEX($AE$5:$AE$323,MATCH($Z15&"TORRE OLMA",$AA$5:$AA$323&$AF$5:$AF$323,0)),"TORRE OLMA"),""),IF(SUMIFS($AP$5:$AP$323,$AA$5:$AA$323,$Z15,$AF$5:$AF$323,"OTROS")>0,IFERROR("OTROS-"&INDEX($AE$5:$AE$323,MATCH($Z15&"OTROS",$AA$5:$AA$323&$AF$5:$AF$323,0)),"OTROS"),""))) | F15: =IF($A15="","",IFERROR(INDEX($BK$5:$BK$323,MATCH($Z15,$AA$5:$AA$323,0)),"-")) | G15: =IF($A15="","",IFERROR(INDEX($BL$5:$BL$323,MATCH($Z15,$AA$5:$AA$323,0)),"-")) | H15: =IF($A15="","",IFERROR(INDEX($BM$5:$BM$323,MATCH($Z15,$AA$5:$AA$323,0)),"-")) | I15: =IF($A15="","",IFERROR(INDEX($BN$5:$BN$323,MATCH($Z15,$AA$5:$AA$323,0)),"-")) | J15: =IF($A15="","",IFERROR(INDEX($BO$5:$BO$323,MATCH($Z15,$AA$5:$AA$323,0)),"-")) | K15: =IF($A15="","",IFERROR(INDEX($BP$5:$BP$323,MATCH($Z15,$AA$5:$AA$323,0)),"-")) | L15: =IF($A15="","",IFERROR(INDEX($BQ$5:$BQ$323,MATCH($Z15,$AA$5:$AA$323,0)),"-")) | M15: =IF($A15="","",(--(SUMIF($AA$5:$AA$323,$Z15,$AI$5:$AI$323)>0))+(--(SUMIF($AA$5:$AA$323,$Z15,$AJ$5:$AJ$323)>0))+(--(SUMIF($AA$5:$AA$323,$Z15,$AK$5:$AK$323)>0))+(--(SUMIF($AA$5:$AA$323,$Z15,$AL$5:$AL$323)>0))+(--(SUMIF($AA$5:$AA$323,$Z15,$AM$5:$AM$323)>0))+(--(SUMIF($AA$5:$AA$323,$Z15,$AN$5:$AN$323)>0))+(--(SUMIF($AA$5:$AA$323,$Z15,$AO$5:$AO$323)>0))) | N15: =IF($A15="","",MAX(0,M15-6)) | O15: =IF($A15="","",SUMIF($AA$5:$AA$323,$Z15,$AP$5:$AP$323)-M15) | P15: =IF($A15="","",SUMIF($AA$5:$AA$323,$Z15,$BG$5:$BG$323)) | Q15: =IF($A15="","",SUMIF($AA$5:$AA$323,$Z15,$BH$5:$BH$323)) | R15: =IF($A15="","",SUMIF($AA$5:$AA$323,$Z15,$BI$5:$BI$323)) | U15: =IF($A15="","",SUMIF($AA$5:$AA$323,$Z15,$BJ$5:$BJ$323)) | W15: =IF($A15="","",_xlfn.TEXTJOIN(" | ",TRUE(),IF(N15>0,"+ de 6 días: revisar adicionales",""),IF(O15>0,"Doble evento mismo día: revisar turno/pago",""),IF(SUMIF($AA$5:$AA$323,$Z15,$AX$5:$AX$323)>((--(SUMIF($AA$5:$AA$323,$Z15,$AQ$5:$AQ$323)>0))+(--(SUMIF($AA$5:$AA$323,$Z15,$AR$5:$AR$323)>0))+(--(SUMIF($AA$5:$AA$323,$Z15,$AS$5:$AS$323)>0))+(--(SUMIF($AA$5:$AA$323,$Z15,$AT$5:$AT$323)>0))+(--(SUMIF($AA$5:$AA$323,$Z15,$AU$5:$AU$323)>0))+(--(SUMIF($AA$5:$AA$323,$Z15,$AV$5:$AV$323)>0))+(--(SUMIF($AA$5:$AA$323,$Z15,$AW$5:$AW$323)>0))),"FL múltiple mismo día: revisar pago festivo",""),IF(SUMIF($AA$5:$AA$323,$Z15,$BF$5:$BF$323)>((--(SUMIF($AA$5:$AA$323,$Z15,$AY$5:$AY$323)>0))+(--(SUMIF($AA$5:$AA$323,$Z15,$AZ$5:$AZ$323)>0))+(--(SUMIF($AA$5:$AA$323,$Z15,$BA$5:$BA$323)>0))+(--(SUMIF($AA$5:$AA$323,$Z15,$BB$5:$BB$323)>0))+(--(SUMIF($AA$5:$AA$323,$Z15,$BC$5:$BC$323)>0))+(--(SUMIF($AA$5:$AA$323,$Z15,$BD$5:$BD$323)>0))+(--(SUMIF($AA$5:$AA$323,$Z15,$BE$5:$BE$323)>0))),"DL múltiple mismo día: revisar pago descanso",""))) | Y15: =IFERROR(MATCH(11,$AH$5:$AH$323,0),"") | Z15: =IF(Y15="","",INDEX($AA$5:$AA$323,Y15)) | AA15: =IF(AC15="","","M:"&AC15) | AB15: =IF(Asistencia!A16="","",Asistencia!A16) | AC15: =IF(Asistencia!A16="","",SUBSTITUTE(SUBSTITUTE(SUBSTITUTE(SUBSTITUTE(SUBSTITUTE(SUBSTITUTE(SUBSTITUTE(UPPER(TRIM(Asistencia!A16)),"Á","A"),"É","E"),"Í","I"),"Ó","O"),"Ú","U"),"Ñ","N")," "," ")) | AD15: =IF(Asistencia!E16="","",Asistencia!E16) | AE15: =IF(Asistencia!D16="","",UPPER(TRIM(Asistencia!D16))) | AF15: ARMIDA | AG15: =IF(AND(AA15<>"",COUNTIF($AA$5:AA15,AA15)=1),1,0) -> 0 | AH15: =IF(AG15=1,SUM($AG$5:AG15),"") | AI15: =IF(OR(EXACT(Asistencia!F16,"A"),EXACT(Asistencia!F16,"R"),EXACT(Asistencia!F16,"DL"),EXACT(Asistencia!F16,"FL"),EXACT(Asistencia!F16,"FE"),EXACT(Asistencia!F16,"PCS"),EXACT(Asistencia!F16,"V")),1,0) -> 0 | AJ15: =IF(OR(EXACT(Asistencia!G16,"A"),EXACT(Asistencia!G16,"R"),EXACT(Asistencia!G16,"DL"),EXACT(Asistencia!G16,"FL"),EXACT(Asistencia!G16,"FE"),EXACT(Asistencia!G16,"PCS"),EXACT(Asistencia!G16,"V")),1,0) -> 0 | AK15: =IF(OR(EXACT(Asistencia!H16,"A"),EXACT(Asistencia!H16,"R"),EXACT(Asistencia!H16,"DL"),EXACT(Asistencia!H16,"FL"),EXACT(Asistencia!H16,"FE"),EXACT(Asistencia!H16,"PCS"),EXACT(Asistencia!H16,"V")),1,0) -> 0 | AL15: =IF(OR(EXACT(Asistencia!I16,"A"),EXACT(Asistencia!I16,"R"),EXACT(Asistencia!I16,"DL"),EXACT(Asistencia!I16,"FL"),EXACT(Asistencia!I16,"FE"),EXACT(Asistencia!I16,"PCS"),EXACT(Asistencia!I16,"V")),1,0) -> 0 | AM15: =IF(OR(EXACT(Asistencia!J16,"A"),EXACT(Asistencia!J16,"R"),EXACT(Asistencia!J16,"DL"),EXACT(Asistencia!J16,"FL"),EXACT(Asistencia!J16,"FE"),EXACT(Asistencia!J16,"PCS"),EXACT(Asistencia!J16,"V")),1,0) -> 0 | AN15: =IF(OR(EXACT(Asistencia!K16,"A"),EXACT(Asistencia!K16,"R"),EXACT(Asistencia!K16,"DL"),EXACT(Asistencia!K16,"FL"),EXACT(Asistencia!K16,"FE"),EXACT(Asistencia!K16,"PCS"),EXACT(Asistencia!K16,"V")),1,0) -> 0 | AO15: =IF(OR(EXACT(Asistencia!L16,"A"),EXACT(Asistencia!L16,"R"),EXACT(Asistencia!L16,"DL"),EXACT(Asistencia!L16,"FL"),EXACT(Asistencia!L16,"FE"),EXACT(Asistencia!L16,"PCS"),EXACT(Asistencia!L16,"V")),1,0) -> 0 | AP15: =SUM(AI15:AO15) -> 0 | AQ15: =IF(EXACT(Asistencia!F16,"FL"),1,0) -> 0 | AR15: =IF(EXACT(Asistencia!G16,"FL"),1,0) -> 0 | AS15: =IF(EXACT(Asistencia!H16,"FL"),1,0) -> 0 | AT15: =IF(EXACT(Asistencia!I16,"FL"),1,0) -> 0 | AU15: =IF(EXACT(Asistencia!J16,"FL"),1,0) -> 0 | AV15: =IF(EXACT(Asistencia!K16,"FL"),1,0) -> 0 | AW15: =IF(EXACT(Asistencia!L16,"FL"),1,0) -> 0 | AX15: =SUM(AQ15:AW15) -> 0 | AY15: =IF(EXACT(Asistencia!F16,"DL"),1,0) -> 0 | AZ15: =IF(EXACT(Asistencia!G16,"DL"),1,0) -> 0 | BA15: =IF(EXACT(Asistencia!H16,"DL"),1,0) -> 0 | BB15: =IF(EXACT(Asistencia!I16,"DL"),1,0) -> 0 | BC15: =IF(EXACT(Asistencia!J16,"DL"),1,0) -> 0 | BD15: =IF(EXACT(Asistencia!K16,"DL"),1,0) -> 0 | BE15: =IF(EXACT(Asistencia!L16,"DL"),1,0) -> 0 | BF15: =SUM(AY15:BE15) -> 0 | BG15: =IF(ISNUMBER(Asistencia!M16),Asistencia!M16,0) -> 0 | BH15: =IF(ISNUMBER(Asistencia!N16),Asistencia!N16,0) -> 0 | BI15: =IF(ISNUMBER(Asistencia!O16),Asistencia!O16,0) -> 0 | BJ15: =IF(ISNUMBER(Asistencia!P16),Asistencia!P16,0) -> 0 | BK15: =IF(Asistencia!F16="","",Asistencia!F16) | BL15: =IF(Asistencia!G16="","",Asistencia!G16) | BM15: =IF(Asistencia!H16="","",Asistencia!H16) | BN15: =IF(Asistencia!I16="","",Asistencia!I16) | BO15: =IF(Asistencia!J16="","",Asistencia!J16) | BP15: =IF(Asistencia!K16="","",Asistencia!K16) | BQ15: =IF(Asistencia!L16="","",Asistencia!L16)
A16: =IF(Y16="","",INDEX($AB$5:$AB$323,Y16)) | B16: =IF(Y16="","",INDEX($AD$5:$AD$323,Y16)) | E16: =IF($A16="","",_xlfn.TEXTJOIN(" / ",TRUE(),IF(SUMIFS($AP$5:$AP$323,$AA$5:$AA$323,$Z16,$AF$5:$AF$323,"ARMIDA")>0,IFERROR("ARMIDA-"&INDEX($AE$5:$AE$323,MATCH($Z16&"ARMIDA",$AA$5:$AA$323&$AF$5:$AF$323,0)),"ARMIDA"),""),IF(SUMIFS($AP$5:$AP$323,$AA$5:$AA$323,$Z16,$AF$5:$AF$323,"AURIGA")>0,IFERROR("AURIGA-"&INDEX($AE$5:$AE$323,MATCH($Z16&"AURIGA",$AA$5:$AA$323&$AF$5:$AF$323,0)),"AURIGA"),""),IF(SUMIFS($AP$5:$AP$323,$AA$5:$AA$323,$Z16,$AF$5:$AF$323,"AURORA")>0,IFERROR("AURORA-"&INDEX($AE$5:$AE$323,MATCH($Z16&"AURORA",$AA$5:$AA$323&$AF$5:$AF$323,0)),"AURORA"),""),IF(SUMIFS($AP$5:$AP$323,$AA$5:$AA$323,$Z16,$AF$5:$AF$323,"CITICA")>0,IFERROR("CITICA-"&INDEX($AE$5:$AE$323,MATCH($Z16&"CITICA",$AA$5:$AA$323&$AF$5:$AF$323,0)),"CITICA"),""),IF(SUMIFS($AP$5:$AP$323,$AA$5:$AA$323,$Z16,$AF$5:$AF$323,"GM")>0,IFERROR("GM-"&INDEX($AE$5:$AE$323,MATCH($Z16&"GM",$AA$5:$AA$323&$AF$5:$AF$323,0)),"GM"),""),IF(SUMIFS($AP$5:$AP$323,$AA$5:$AA$323,$Z16,$AF$5:$AF$323,"TORRE BALZAK")>0,IFERROR("TORRE BALZAK-"&INDEX($AE$5:$AE$323,MATCH($Z16&"TORRE BALZAK",$AA$5:$AA$323&$AF$5:$AF$323,0)),"TORRE BALZAK"),""),IF(SUMIFS($AP$5:$AP$323,$AA$5:$AA$323,$Z16,$AF$5:$AF$323,"TORRE OLMA")>0,IFERROR("TORRE OLMA-"&INDEX($AE$5:$AE$323,MATCH($Z16&"TORRE OLMA",$AA$5:$AA$323&$AF$5:$AF$323,0)),"TORRE OLMA"),""),IF(SUMIFS($AP$5:$AP$323,$AA$5:$AA$323,$Z16,$AF$5:$AF$323,"OTROS")>0,IFERROR("OTROS-"&INDEX($AE$5:$AE$323,MATCH($Z16&"OTROS",$AA$5:$AA$323&$AF$5:$AF$323,0)),"OTROS"),""))) | F16: =IF($A16="","",IFERROR(INDEX($BK$5:$BK$323,MATCH($Z16,$AA$5:$AA$323,0)),"-")) | G16: =IF($A16="","",IFERROR(INDEX($BL$5:$BL$323,MATCH($Z16,$AA$5:$AA$323,0)),"-")) | H16: =IF($A16="","",IFERROR(INDEX($BM$5:$BM$323,MATCH($Z16,$AA$5:$AA$323,0)),"-")) | I16: =IF($A16="","",IFERROR(INDEX($BN$5:$BN$323,MATCH($Z16,$AA$5:$AA$323,0)),"-")) | J16: =IF($A16="","",IFERROR(INDEX($BO$5:$BO$323,MATCH($Z16,$AA$5:$AA$323,0)),"-")) | K16: =IF($A16="","",IFERROR(INDEX($BP$5:$BP$323,MATCH($Z16,$AA$5:$AA$323,0)),"-")) | L16: =IF($A16="","",IFERROR(INDEX($BQ$5:$BQ$323,MATCH($Z16,$AA$5:$AA$323,0)),"-")) | M16: =IF($A16="","",(--(SUMIF($AA$5:$AA$323,$Z16,$AI$5:$AI$323)>0))+(--(SUMIF($AA$5:$AA$323,$Z16,$AJ$5:$AJ$323)>0))+(--(SUMIF($AA$5:$AA$323,$Z16,$AK$5:$AK$323)>0))+(--(SUMIF($AA$5:$AA$323,$Z16,$AL$5:$AL$323)>0))+(--(SUMIF($AA$5:$AA$323,$Z16,$AM$5:$AM$323)>0))+(--(SUMIF($AA$5:$AA$323,$Z16,$AN$5:$AN$323)>0))+(--(SUMIF($AA$5:$AA$323,$Z16,$AO$5:$AO$323)>0))) | N16: =IF($A16="","",MAX(0,M16-6)) | O16: =IF($A16="","",SUMIF($AA$5:$AA$323,$Z16,$AP$5:$AP$323)-M16) | P16: =IF($A16="","",SUMIF($AA$5:$AA$323,$Z16,$BG$5:$BG$323)) | Q16: =IF($A16="","",SUMIF($AA$5:$AA$323,$Z16,$BH$5:$BH$323)) | R16: =IF($A16="","",SUMIF($AA$5:$AA$323,$Z16,$BI$5:$BI$323)) | U16: =IF($A16="","",SUMIF($AA$5:$AA$323,$Z16,$BJ$5:$BJ$323)) | W16: =IF($A16="","",_xlfn.TEXTJOIN(" | ",TRUE(),IF(N16>0,"+ de 6 días: revisar adicionales",""),IF(O16>0,"Doble evento mismo día: revisar turno/pago",""),IF(SUMIF($AA$5:$AA$323,$Z16,$AX$5:$AX$323)>((--(SUMIF($AA$5:$AA$323,$Z16,$AQ$5:$AQ$323)>0))+(--(SUMIF($AA$5:$AA$323,$Z16,$AR$5:$AR$323)>0))+(--(SUMIF($AA$5:$AA$323,$Z16,$AS$5:$AS$323)>0))+(--(SUMIF($AA$5:$AA$323,$Z16,$AT$5:$AT$323)>0))+(--(SUMIF($AA$5:$AA$323,$Z16,$AU$5:$AU$323)>0))+(--(SUMIF($AA$5:$AA$323,$Z16,$AV$5:$AV$323)>0))+(--(SUMIF($AA$5:$AA$323,$Z16,$AW$5:$AW$323)>0))),"FL múltiple mismo día: revisar pago festivo",""),IF(SUMIF($AA$5:$AA$323,$Z16,$BF$5:$BF$323)>((--(SUMIF($AA$5:$AA$323,$Z16,$AY$5:$AY$323)>0))+(--(SUMIF($AA$5:$AA$323,$Z16,$AZ$5:$AZ$323)>0))+(--(SUMIF($AA$5:$AA$323,$Z16,$BA$5:$BA$323)>0))+(--(SUMIF($AA$5:$AA$323,$Z16,$BB$5:$BB$323)>0))+(--(SUMIF($AA$5:$AA$323,$Z16,$BC$5:$BC$323)>0))+(--(SUMIF($AA$5:$AA$323,$Z16,$BD$5:$BD$323)>0))+(--(SUMIF($AA$5:$AA$323,$Z16,$BE$5:$BE$323)>0))),"DL múltiple mismo día: revisar pago descanso",""))) | Y16: =IFERROR(MATCH(12,$AH$5:$AH$323,0),"") | Z16: =IF(Y16="","",INDEX($AA$5:$AA$323,Y16)) | AA16: =IF(AC16="","","M:"&AC16) | AB16: =IF(Asistencia!A17="","",Asistencia!A17) | AC16: =IF(Asistencia!A17="","",SUBSTITUTE(SUBSTITUTE(SUBSTITUTE(SUBSTITUTE(SUBSTITUTE(SUBSTITUTE(SUBSTITUTE(UPPER(TRIM(Asistencia!A17)),"Á","A"),"É","E"),"Í","I"),"Ó","O"),"Ú","U"),"Ñ","N")," "," ")) | AD16: =IF(Asistencia!E17="","",Asistencia!E17) | AE16: =IF(Asistencia!D17="","",UPPER(TRIM(Asistencia!D17))) | AF16: ARMIDA | AG16: =IF(AND(AA16<>"",COUNTIF($AA$5:AA16,AA16)=1),1,0) -> 0 | AH16: =IF(AG16=1,SUM($AG$5:AG16),"") | AI16: =IF(OR(EXACT(Asistencia!F17,"A"),EXACT(Asistencia!F17,"R"),EXACT(Asistencia!F17,"DL"),EXACT(Asistencia!F17,"FL"),EXACT(Asistencia!F17,"FE"),EXACT(Asistencia!F17,"PCS"),EXACT(Asistencia!F17,"V")),1,0) -> 0 | AJ16: =IF(OR(EXACT(Asistencia!G17,"A"),EXACT(Asistencia!G17,"R"),EXACT(Asistencia!G17,"DL"),EXACT(Asistencia!G17,"FL"),EXACT(Asistencia!G17,"FE"),EXACT(Asistencia!G17,"PCS"),EXACT(Asistencia!G17,"V")),1,0) -> 0 | AK16: =IF(OR(EXACT(Asistencia!H17,"A"),EXACT(Asistencia!H17,"R"),EXACT(Asistencia!H17,"DL"),EXACT(Asistencia!H17,"FL"),EXACT(Asistencia!H17,"FE"),EXACT(Asistencia!H17,"PCS"),EXACT(Asistencia!H17,"V")),1,0) -> 0 | AL16: =IF(OR(EXACT(Asistencia!I17,"A"),EXACT(Asistencia!I17,"R"),EXACT(Asistencia!I17,"DL"),EXACT(Asistencia!I17,"FL"),EXACT(Asistencia!I17,"FE"),EXACT(Asistencia!I17,"PCS"),EXACT(Asistencia!I17,"V")),1,0) -> 0 | AM16: =IF(OR(EXACT(Asistencia!J17,"A"),EXACT(Asistencia!J17,"R"),EXACT(Asistencia!J17,"DL"),EXACT(Asistencia!J17,"FL"),EXACT(Asistencia!J17,"FE"),EXACT(Asistencia!J17,"PCS"),EXACT(Asistencia!J17,"V")),1,0) -> 0 | AN16: =IF(OR(EXACT(Asistencia!K17,"A"),EXACT(Asistencia!K17,"R"),EXACT(Asistencia!K17,"DL"),EXACT(Asistencia!K17,"FL"),EXACT(Asistencia!K17,"FE"),EXACT(Asistencia!K17,"PCS"),EXACT(Asistencia!K17,"V")),1,0) -> 0 | AO16: =IF(OR(EXACT(Asistencia!L17,"A"),EXACT(Asistencia!L17,"R"),EXACT(Asistencia!L17,"DL"),EXACT(Asistencia!L17,"FL"),EXACT(Asistencia!L17,"FE"),EXACT(Asistencia!L17,"PCS"),EXACT(Asistencia!L17,"V")),1,0) -> 0 | AP16: =SUM(AI16:AO16) -> 0 | AQ16: =IF(EXACT(Asistencia!F17,"FL"),1,0) -> 0 | AR16: =IF(EXACT(Asistencia!G17,"FL"),1,0) -> 0 | AS16: =IF(EXACT(Asistencia!H17,"FL"),1,0) -> 0 | AT16: =IF(EXACT(Asistencia!I17,"FL"),1,0) -> 0 | AU16: =IF(EXACT(Asistencia!J17,"FL"),1,0) -> 0 | AV16: =IF(EXACT(Asistencia!K17,"FL"),1,0) -> 0 | AW16: =IF(EXACT(Asistencia!L17,"FL"),1,0) -> 0 | AX16: =SUM(AQ16:AW16) -> 0 | AY16: =IF(EXACT(Asistencia!F17,"DL"),1,0) -> 0 | AZ16: =IF(EXACT(Asistencia!G17,"DL"),1,0) -> 0 | BA16: =IF(EXACT(Asistencia!H17,"DL"),1,0) -> 0 | BB16: =IF(EXACT(Asistencia!I17,"DL"),1,0) -> 0 | BC16: =IF(EXACT(Asistencia!J17,"DL"),1,0) -> 0 | BD16: =IF(EXACT(Asistencia!K17,"DL"),1,0) -> 0 | BE16: =IF(EXACT(Asistencia!L17,"DL"),1,0) -> 0 | BF16: =SUM(AY16:BE16) -> 0 | BG16: =IF(ISNUMBER(Asistencia!M17),Asistencia!M17,0) -> 0 | BH16: =IF(ISNUMBER(Asistencia!N17),Asistencia!N17,0) -> 0 | BI16: =IF(ISNUMBER(Asistencia!O17),Asistencia!O17,0) -> 0 | BJ16: =IF(ISNUMBER(Asistencia!P17),Asistencia!P17,0) -> 0 | BK16: =IF(Asistencia!F17="","",Asistencia!F17) | BL16: =IF(Asistencia!G17="","",Asistencia!G17) | BM16: =IF(Asistencia!H17="","",Asistencia!H17) | BN16: =IF(Asistencia!I17="","",Asistencia!I17) | BO16: =IF(Asistencia!J17="","",Asistencia!J17) | BP16: =IF(Asistencia!K17="","",Asistencia!K17) | BQ16: =IF(Asistencia!L17="","",Asistencia!L17)
A17: =IF(Y17="","",INDEX($AB$5:$AB$323,Y17)) | B17: =IF(Y17="","",INDEX($AD$5:$AD$323,Y17)) | E17: =IF($A17="","",_xlfn.TEXTJOIN(" / ",TRUE(),IF(SUMIFS($AP$5:$AP$323,$AA$5:$AA$323,$Z17,$AF$5:$AF$323,"ARMIDA")>0,IFERROR("ARMIDA-"&INDEX($AE$5:$AE$323,MATCH($Z17&"ARMIDA",$AA$5:$AA$323&$AF$5:$AF$323,0)),"ARMIDA"),""),IF(SUMIFS($AP$5:$AP$323,$AA$5:$AA$323,$Z17,$AF$5:$AF$323,"AURIGA")>0,IFERROR("AURIGA-"&INDEX($AE$5:$AE$323,MATCH($Z17&"AURIGA",$AA$5:$AA$323&$AF$5:$AF$323,0)),"AURIGA"),""),IF(SUMIFS($AP$5:$AP$323,$AA$5:$AA$323,$Z17,$AF$5:$AF$323,"AURORA")>0,IFERROR("AURORA-"&INDEX($AE$5:$AE$323,MATCH($Z17&"AURORA",$AA$5:$AA$323&$AF$5:$AF$323,0)),"AURORA"),""),IF(SUMIFS($AP$5:$AP$323,$AA$5:$AA$323,$Z17,$AF$5:$AF$323,"CITICA")>0,IFERROR("CITICA-"&INDEX($AE$5:$AE$323,MATCH($Z17&"CITICA",$AA$5:$AA$323&$AF$5:$AF$323,0)),"CITICA"),""),IF(SUMIFS($AP$5:$AP$323,$AA$5:$AA$323,$Z17,$AF$5:$AF$323,"GM")>0,IFERROR("GM-"&INDEX($AE$5:$AE$323,MATCH($Z17&"GM",$AA$5:$AA$323&$AF$5:$AF$323,0)),"GM"),""),IF(SUMIFS($AP$5:$AP$323,$AA$5:$AA$323,$Z17,$AF$5:$AF$323,"TORRE BALZAK")>0,IFERROR("TORRE BALZAK-"&INDEX($AE$5:$AE$323,MATCH($Z17&"TORRE BALZAK",$AA$5:$AA$323&$AF$5:$AF$323,0)),"TORRE BALZAK"),""),IF(SUMIFS($AP$5:$AP$323,$AA$5:$AA$323,$Z17,$AF$5:$AF$323,"TORRE OLMA")>0,IFERROR("TORRE OLMA-"&INDEX($AE$5:$AE$323,MATCH($Z17&"TORRE OLMA",$AA$5:$AA$323&$AF$5:$AF$323,0)),"TORRE OLMA"),""),IF(SUMIFS($AP$5:$AP$323,$AA$5:$AA$323,$Z17,$AF$5:$AF$323,"OTROS")>0,IFERROR("OTROS-"&INDEX($AE$5:$AE$323,MATCH($Z17&"OTROS",$AA$5:$AA$323&$AF$5:$AF$323,0)),"OTROS"),""))) | F17: =IF($A17="","",IFERROR(INDEX($BK$5:$BK$323,MATCH($Z17,$AA$5:$AA$323,0)),"-")) | G17: =IF($A17="","",IFERROR(INDEX($BL$5:$BL$323,MATCH($Z17,$AA$5:$AA$323,0)),"-")) | H17: =IF($A17="","",IFERROR(INDEX($BM$5:$BM$323,MATCH($Z17,$AA$5:$AA$323,0)),"-")) | I17: =IF($A17="","",IFERROR(INDEX($BN$5:$BN$323,MATCH($Z17,$AA$5:$AA$323,0)),"-")) | J17: =IF($A17="","",IFERROR(INDEX($BO$5:$BO$323,MATCH($Z17,$AA$5:$AA$323,0)),"-")) | K17: =IF($A17="","",IFERROR(INDEX($BP$5:$BP$323,MATCH($Z17,$AA$5:$AA$323,0)),"-")) | L17: =IF($A17="","",IFERROR(INDEX($BQ$5:$BQ$323,MATCH($Z17,$AA$5:$AA$323,0)),"-")) | M17: =IF($A17="","",(--(SUMIF($AA$5:$AA$323,$Z17,$AI$5:$AI$323)>0))+(--(SUMIF($AA$5:$AA$323,$Z17,$AJ$5:$AJ$323)>0))+(--(SUMIF($AA$5:$AA$323,$Z17,$AK$5:$AK$323)>0))+(--(SUMIF($AA$5:$AA$323,$Z17,$AL$5:$AL$323)>0))+(--(SUMIF($AA$5:$AA$323,$Z17,$AM$5:$AM$323)>0))+(--(SUMIF($AA$5:$AA$323,$Z17,$AN$5:$AN$323)>0))+(--(SUMIF($AA$5:$AA$323,$Z17,$AO$5:$AO$323)>0))) | N17: =IF($A17="","",MAX(0,M17-6)) | O17: =IF($A17="","",SUMIF($AA$5:$AA$323,$Z17,$AP$5:$AP$323)-M17) | P17: =IF($A17="","",SUMIF($AA$5:$AA$323,$Z17,$BG$5:$BG$323)) | Q17: =IF($A17="","",SUMIF($AA$5:$AA$323,$Z17,$BH$5:$BH$323)) | R17: =IF($A17="","",SUMIF($AA$5:$AA$323,$Z17,$BI$5:$BI$323)) | U17: =IF($A17="","",SUMIF($AA$5:$AA$323,$Z17,$BJ$5:$BJ$323)) | W17: =IF($A17="","",_xlfn.TEXTJOIN(" | ",TRUE(),IF(N17>0,"+ de 6 días: revisar adicionales",""),IF(O17>0,"Doble evento mismo día: revisar turno/pago",""),IF(SUMIF($AA$5:$AA$323,$Z17,$AX$5:$AX$323)>((--(SUMIF($AA$5:$AA$323,$Z17,$AQ$5:$AQ$323)>0))+(--(SUMIF($AA$5:$AA$323,$Z17,$AR$5:$AR$323)>0))+(--(SUMIF($AA$5:$AA$323,$Z17,$AS$5:$AS$323)>0))+(--(SUMIF($AA$5:$AA$323,$Z17,$AT$5:$AT$323)>0))+(--(SUMIF($AA$5:$AA$323,$Z17,$AU$5:$AU$323)>0))+(--(SUMIF($AA$5:$AA$323,$Z17,$AV$5:$AV$323)>0))+(--(SUMIF($AA$5:$AA$323,$Z17,$AW$5:$AW$323)>0))),"FL múltiple mismo día: revisar pago festivo",""),IF(SUMIF($AA$5:$AA$323,$Z17,$BF$5:$BF$323)>((--(SUMIF($AA$5:$AA$323,$Z17,$AY$5:$AY$323)>0))+(--(SUMIF($AA$5:$AA$323,$Z17,$AZ$5:$AZ$323)>0))+(--(SUMIF($AA$5:$AA$323,$Z17,$BA$5:$BA$323)>0))+(--(SUMIF($AA$5:$AA$323,$Z17,$BB$5:$BB$323)>0))+(--(SUMIF($AA$5:$AA$323,$Z17,$BC$5:$BC$323)>0))+(--(SUMIF($AA$5:$AA$323,$Z17,$BD$5:$BD$323)>0))+(--(SUMIF($AA$5:$AA$323,$Z17,$BE$5:$BE$323)>0))),"DL múltiple mismo día: revisar pago descanso",""))) | Y17: =IFERROR(MATCH(13,$AH$5:$AH$323,0),"") | Z17: =IF(Y17="","",INDEX($AA$5:$AA$323,Y17)) | AA17: =IF(AC17="","","M:"&AC17) | AB17: =IF(Asistencia!A18="","",Asistencia!A18) | AC17: =IF(Asistencia!A18="","",SUBSTITUTE(SUBSTITUTE(SUBSTITUTE(SUBSTITUTE(SUBSTITUTE(SUBSTITUTE(SUBSTITUTE(UPPER(TRIM(Asistencia!A18)),"Á","A"),"É","E"),"Í","I"),"Ó","O"),"Ú","U"),"Ñ","N")," "," ")) | AD17: =IF(Asistencia!E18="","",Asistencia!E18) | AE17: =IF(Asistencia!D18="","",UPPER(TRIM(Asistencia!D18))) | AF17: ARMIDA | AG17: =IF(AND(AA17<>"",COUNTIF($AA$5:AA17,AA17)=1),1,0) -> 0 | AH17: =IF(AG17=1,SUM($AG$5:AG17),"") | AI17: =IF(OR(EXACT(Asistencia!F18,"A"),EXACT(Asistencia!F18,"R"),EXACT(Asistencia!F18,"DL"),EXACT(Asistencia!F18,"FL"),EXACT(Asistencia!F18,"FE"),EXACT(Asistencia!F18,"PCS"),EXACT(Asistencia!F18,"V")),1,0) -> 0 | AJ17: =IF(OR(EXACT(Asistencia!G18,"A"),EXACT(Asistencia!G18,"R"),EXACT(Asistencia!G18,"DL"),EXACT(Asistencia!G18,"FL"),EXACT(Asistencia!G18,"FE"),EXACT(Asistencia!G18,"PCS"),EXACT(Asistencia!G18,"V")),1,0) -> 0 | AK17: =IF(OR(EXACT(Asistencia!H18,"A"),EXACT(Asistencia!H18,"R"),EXACT(Asistencia!H18,"DL"),EXACT(Asistencia!H18,"FL"),EXACT(Asistencia!H18,"FE"),EXACT(Asistencia!H18,"PCS"),EXACT(Asistencia!H18,"V")),1,0) -> 0 | AL17: =IF(OR(EXACT(Asistencia!I18,"A"),EXACT(Asistencia!I18,"R"),EXACT(Asistencia!I18,"DL"),EXACT(Asistencia!I18,"FL"),EXACT(Asistencia!I18,"FE"),EXACT(Asistencia!I18,"PCS"),EXACT(Asistencia!I18,"V")),1,0) -> 0 | AM17: =IF(OR(EXACT(Asistencia!J18,"A"),EXACT(Asistencia!J18,"R"),EXACT(Asistencia!J18,"DL"),EXACT(Asistencia!J18,"FL"),EXACT(Asistencia!J18,"FE"),EXACT(Asistencia!J18,"PCS"),EXACT(Asistencia!J18,"V")),1,0) -> 0 | AN17: =IF(OR(EXACT(Asistencia!K18,"A"),EXACT(Asistencia!K18,"R"),EXACT(Asistencia!K18,"DL"),EXACT(Asistencia!K18,"FL"),EXACT(Asistencia!K18,"FE"),EXACT(Asistencia!K18,"PCS"),EXACT(Asistencia!K18,"V")),1,0) -> 0 | AO17: =IF(OR(EXACT(Asistencia!L18,"A"),EXACT(Asistencia!L18,"R"),EXACT(Asistencia!L18,"DL"),EXACT(Asistencia!L18,"FL"),EXACT(Asistencia!L18,"FE"),EXACT(Asistencia!L18,"PCS"),EXACT(Asistencia!L18,"V")),1,0) -> 0 | AP17: =SUM(AI17:AO17) -> 0 | AQ17: =IF(EXACT(Asistencia!F18,"FL"),1,0) -> 0 | AR17: =IF(EXACT(Asistencia!G18,"FL"),1,0) -> 0 | AS17: =IF(EXACT(Asistencia!H18,"FL"),1,0) -> 0 | AT17: =IF(EXACT(Asistencia!I18,"FL"),1,0) -> 0 | AU17: =IF(EXACT(Asistencia!J18,"FL"),1,0) -> 0 | AV17: =IF(EXACT(Asistencia!K18,"FL"),1,0) -> 0 | AW17: =IF(EXACT(Asistencia!L18,"FL"),1,0) -> 0 | AX17: =SUM(AQ17:AW17) -> 0 | AY17: =IF(EXACT(Asistencia!F18,"DL"),1,0) -> 0 | AZ17: =IF(EXACT(Asistencia!G18,"DL"),1,0) -> 0 | BA17: =IF(EXACT(Asistencia!H18,"DL"),1,0) -> 0 | BB17: =IF(EXACT(Asistencia!I18,"DL"),1,0) -> 0 | BC17: =IF(EXACT(Asistencia!J18,"DL"),1,0) -> 0 | BD17: =IF(EXACT(Asistencia!K18,"DL"),1,0) -> 0 | BE17: =IF(EXACT(Asistencia!L18,"DL"),1,0) -> 0 | BF17: =SUM(AY17:BE17) -> 0 | BG17: =IF(ISNUMBER(Asistencia!M18),Asistencia!M18,0) -> 0 | BH17: =IF(ISNUMBER(Asistencia!N18),Asistencia!N18,0) -> 0 | BI17: =IF(ISNUMBER(Asistencia!O18),Asistencia!O18,0) -> 0 | BJ17: =IF(ISNUMBER(Asistencia!P18),Asistencia!P18,0) -> 0 | BK17: =IF(Asistencia!F18="","",Asistencia!F18) | BL17: =IF(Asistencia!G18="","",Asistencia!G18) | BM17: =IF(Asistencia!H18="","",Asistencia!H18) | BN17: =IF(Asistencia!I18="","",Asistencia!I18) | BO17: =IF(Asistencia!J18="","",Asistencia!J18) | BP17: =IF(Asistencia!K18="","",Asistencia!K18) | BQ17: =IF(Asistencia!L18="","",Asistencia!L18)
A18: =IF(Y18="","",INDEX($AB$5:$AB$323,Y18)) | B18: =IF(Y18="","",INDEX($AD$5:$AD$323,Y18)) | E18: =IF($A18="","",_xlfn.TEXTJOIN(" / ",TRUE(),IF(SUMIFS($AP$5:$AP$323,$AA$5:$AA$323,$Z18,$AF$5:$AF$323,"ARMIDA")>0,IFERROR("ARMIDA-"&INDEX($AE$5:$AE$323,MATCH($Z18&"ARMIDA",$AA$5:$AA$323&$AF$5:$AF$323,0)),"ARMIDA"),""),IF(SUMIFS($AP$5:$AP$323,$AA$5:$AA$323,$Z18,$AF$5:$AF$323,"AURIGA")>0,IFERROR("AURIGA-"&INDEX($AE$5:$AE$323,MATCH($Z18&"AURIGA",$AA$5:$AA$323&$AF$5:$AF$323,0)),"AURIGA"),""),IF(SUMIFS($AP$5:$AP$323,$AA$5:$AA$323,$Z18,$AF$5:$AF$323,"AURORA")>0,IFERROR("AURORA-"&INDEX($AE$5:$AE$323,MATCH($Z18&"AURORA",$AA$5:$AA$323&$AF$5:$AF$323,0)),"AURORA"),""),IF(SUMIFS($AP$5:$AP$323,$AA$5:$AA$323,$Z18,$AF$5:$AF$323,"CITICA")>0,IFERROR("CITICA-"&INDEX($AE$5:$AE$323,MATCH($Z18&"CITICA",$AA$5:$AA$323&$AF$5:$AF$323,0)),"CITICA"),""),IF(SUMIFS($AP$5:$AP$323,$AA$5:$AA$323,$Z18,$AF$5:$AF$323,"GM")>0,IFERROR("GM-"&INDEX($AE$5:$AE$323,MATCH($Z18&"GM",$AA$5:$AA$323&$AF$5:$AF$323,0)),"GM"),""),IF(SUMIFS($AP$5:$AP$323,$AA$5:$AA$323,$Z18,$AF$5:$AF$323,"TORRE BALZAK")>0,IFERROR("TORRE BALZAK-"&INDEX($AE$5:$AE$323,MATCH($Z18&"TORRE BALZAK",$AA$5:$AA$323&$AF$5:$AF$323,0)),"TORRE BALZAK"),""),IF(SUMIFS($AP$5:$AP$323,$AA$5:$AA$323,$Z18,$AF$5:$AF$323,"TORRE OLMA")>0,IFERROR("TORRE OLMA-"&INDEX($AE$5:$AE$323,MATCH($Z18&"TORRE OLMA",$AA$5:$AA$323&$AF$5:$AF$323,0)),"TORRE OLMA"),""),IF(SUMIFS($AP$5:$AP$323,$AA$5:$AA$323,$Z18,$AF$5:$AF$323,"OTROS")>0,IFERROR("OTROS-"&INDEX($AE$5:$AE$323,MATCH($Z18&"OTROS",$AA$5:$AA$323&$AF$5:$AF$323,0)),"OTROS"),""))) | F18: =IF($A18="","",IFERROR(INDEX($BK$5:$BK$323,MATCH($Z18,$AA$5:$AA$323,0)),"-")) | G18: =IF($A18="","",IFERROR(INDEX($BL$5:$BL$323,MATCH($Z18,$AA$5:$AA$323,0)),"-")) | H18: =IF($A18="","",IFERROR(INDEX($BM$5:$BM$323,MATCH($Z18,$AA$5:$AA$323,0)),"-")) | I18: =IF($A18="","",IFERROR(INDEX($BN$5:$BN$323,MATCH($Z18,$AA$5:$AA$323,0)),"-")) | J18: =IF($A18="","",IFERROR(INDEX($BO$5:$BO$323,MATCH($Z18,$AA$5:$AA$323,0)),"-")) | K18: =IF($A18="","",IFERROR(INDEX($BP$5:$BP$323,MATCH($Z18,$AA$5:$AA$323,0)),"-")) | L18: =IF($A18="","",IFERROR(INDEX($BQ$5:$BQ$323,MATCH($Z18,$AA$5:$AA$323,0)),"-")) | M18: =IF($A18="","",(--(SUMIF($AA$5:$AA$323,$Z18,$AI$5:$AI$323)>0))+(--(SUMIF($AA$5:$AA$323,$Z18,$AJ$5:$AJ$323)>0))+(--(SUMIF($AA$5:$AA$323,$Z18,$AK$5:$AK$323)>0))+(--(SUMIF($AA$5:$AA$323,$Z18,$AL$5:$AL$323)>0))+(--(SUMIF($AA$5:$AA$323,$Z18,$AM$5:$AM$323)>0))+(--(SUMIF($AA$5:$AA$323,$Z18,$AN$5:$AN$323)>0))+(--(SUMIF($AA$5:$AA$323,$Z18,$AO$5:$AO$323)>0))) | N18: =IF($A18="","",MAX(0,M18-6)) | O18: =IF($A18="","",SUMIF($AA$5:$AA$323,$Z18,$AP$5:$AP$323)-M18) | P18: =IF($A18="","",SUMIF($AA$5:$AA$323,$Z18,$BG$5:$BG$323)) | Q18: =IF($A18="","",SUMIF($AA$5:$AA$323,$Z18,$BH$5:$BH$323)) | R18: =IF($A18="","",SUMIF($AA$5:$AA$323,$Z18,$BI$5:$BI$323)) | U18: =IF($A18="","",SUMIF($AA$5:$AA$323,$Z18,$BJ$5:$BJ$323)) | W18: =IF($A18="","",_xlfn.TEXTJOIN(" | ",TRUE(),IF(N18>0,"+ de 6 días: revisar adicionales",""),IF(O18>0,"Doble evento mismo día: revisar turno/pago",""),IF(SUMIF($AA$5:$AA$323,$Z18,$AX$5:$AX$323)>((--(SUMIF($AA$5:$AA$323,$Z18,$AQ$5:$AQ$323)>0))+(--(SUMIF($AA$5:$AA$323,$Z18,$AR$5:$AR$323)>0))+(--(SUMIF($AA$5:$AA$323,$Z18,$AS$5:$AS$323)>0))+(--(SUMIF($AA$5:$AA$323,$Z18,$AT$5:$AT$323)>0))+(--(SUMIF($AA$5:$AA$323,$Z18,$AU$5:$AU$323)>0))+(--(SUMIF($AA$5:$AA$323,$Z18,$AV$5:$AV$323)>0))+(--(SUMIF($AA$5:$AA$323,$Z18,$AW$5:$AW$323)>0))),"FL múltiple mismo día: revisar pago festivo",""),IF(SUMIF($AA$5:$AA$323,$Z18,$BF$5:$BF$323)>((--(SUMIF($AA$5:$AA$323,$Z18,$AY$5:$AY$323)>0))+(--(SUMIF($AA$5:$AA$323,$Z18,$AZ$5:$AZ$323)>0))+(--(SUMIF($AA$5:$AA$323,$Z18,$BA$5:$BA$323)>0))+(--(SUMIF($AA$5:$AA$323,$Z18,$BB$5:$BB$323)>0))+(--(SUMIF($AA$5:$AA$323,$Z18,$BC$5:$BC$323)>0))+(--(SUMIF($AA$5:$AA$323,$Z18,$BD$5:$BD$323)>0))+(--(SUMIF($AA$5:$AA$323,$Z18,$BE$5:$BE$323)>0))),"DL múltiple mismo día: revisar pago descanso",""))) | Y18: =IFERROR(MATCH(14,$AH$5:$AH$323,0),"") | Z18: =IF(Y18="","",INDEX($AA$5:$AA$323,Y18)) | AA18: =IF(AC18="","","M:"&AC18) | AB18: =IF(Asistencia!A19="","",Asistencia!A19) | AC18: =IF(Asistencia!A19="","",SUBSTITUTE(SUBSTITUTE(SUBSTITUTE(SUBSTITUTE(SUBSTITUTE(SUBSTITUTE(SUBSTITUTE(UPPER(TRIM(Asistencia!A19)),"Á","A"),"É","E"),"Í","I"),"Ó","O"),"Ú","U"),"Ñ","N")," "," ")) | AD18: =IF(Asistencia!E19="","",Asistencia!E19) | AE18: =IF(Asistencia!D19="","",UPPER(TRIM(Asistencia!D19))) | AF18: ARMIDA | AG18: =IF(AND(AA18<>"",COUNTIF($AA$5:AA18,AA18)=1),1,0) -> 0 | AH18: =IF(AG18=1,SUM($AG$5:AG18),"") | AI18: =IF(OR(EXACT(Asistencia!F19,"A"),EXACT(Asistencia!F19,"R"),EXACT(Asistencia!F19,"DL"),EXACT(Asistencia!F19,"FL"),EXACT(Asistencia!F19,"FE"),EXACT(Asistencia!F19,"PCS"),EXACT(Asistencia!F19,"V")),1,0) -> 0 | AJ18: =IF(OR(EXACT(Asistencia!G19,"A"),EXACT(Asistencia!G19,"R"),EXACT(Asistencia!G19,"DL"),EXACT(Asistencia!G19,"FL"),EXACT(Asistencia!G19,"FE"),EXACT(Asistencia!G19,"PCS"),EXACT(Asistencia!G19,"V")),1,0) -> 0 | AK18: =IF(OR(EXACT(Asistencia!H19,"A"),EXACT(Asistencia!H19,"R"),EXACT(Asistencia!H19,"DL"),EXACT(Asistencia!H19,"FL"),EXACT(Asistencia!H19,"FE"),EXACT(Asistencia!H19,"PCS"),EXACT(Asistencia!H19,"V")),1,0) -> 0 | AL18: =IF(OR(EXACT(Asistencia!I19,"A"),EXACT(Asistencia!I19,"R"),EXACT(Asistencia!I19,"DL"),EXACT(Asistencia!I19,"FL"),EXACT(Asistencia!I19,"FE"),EXACT(Asistencia!I19,"PCS"),EXACT(Asistencia!I19,"V")),1,0) -> 0 | AM18: =IF(OR(EXACT(Asistencia!J19,"A"),EXACT(Asistencia!J19,"R"),EXACT(Asistencia!J19,"DL"),EXACT(Asistencia!J19,"FL"),EXACT(Asistencia!J19,"FE"),EXACT(Asistencia!J19,"PCS"),EXACT(Asistencia!J19,"V")),1,0) -> 0 | AN18: =IF(OR(EXACT(Asistencia!K19,"A"),EXACT(Asistencia!K19,"R"),EXACT(Asistencia!K19,"DL"),EXACT(Asistencia!K19,"FL"),EXACT(Asistencia!K19,"FE"),EXACT(Asistencia!K19,"PCS"),EXACT(Asistencia!K19,"V")),1,0) -> 0 | AO18: =IF(OR(EXACT(Asistencia!L19,"A"),EXACT(Asistencia!L19,"R"),EXACT(Asistencia!L19,"DL"),EXACT(Asistencia!L19,"FL"),EXACT(Asistencia!L19,"FE"),EXACT(Asistencia!L19,"PCS"),EXACT(Asistencia!L19,"V")),1,0) -> 0 | AP18: =SUM(AI18:AO18) -> 0 | AQ18: =IF(EXACT(Asistencia!F19,"FL"),1,0) -> 0 | AR18: =IF(EXACT(Asistencia!G19,"FL"),1,0) -> 0 | AS18: =IF(EXACT(Asistencia!H19,"FL"),1,0) -> 0 | AT18: =IF(EXACT(Asistencia!I19,"FL"),1,0) -> 0 | AU18: =IF(EXACT(Asistencia!J19,"FL"),1,0) -> 0 | AV18: =IF(EXACT(Asistencia!K19,"FL"),1,0) -> 0 | AW18: =IF(EXACT(Asistencia!L19,"FL"),1,0) -> 0 | AX18: =SUM(AQ18:AW18) -> 0 | AY18: =IF(EXACT(Asistencia!F19,"DL"),1,0) -> 0 | AZ18: =IF(EXACT(Asistencia!G19,"DL"),1,0) -> 0 | BA18: =IF(EXACT(Asistencia!H19,"DL"),1,0) -> 0 | BB18: =IF(EXACT(Asistencia!I19,"DL"),1,0) -> 0 | BC18: =IF(EXACT(Asistencia!J19,"DL"),1,0) -> 0 | BD18: =IF(EXACT(Asistencia!K19,"DL"),1,0) -> 0 | BE18: =IF(EXACT(Asistencia!L19,"DL"),1,0) -> 0 | BF18: =SUM(AY18:BE18) -> 0 | BG18: =IF(ISNUMBER(Asistencia!M19),Asistencia!M19,0) -> 0 | BH18: =IF(ISNUMBER(Asistencia!N19),Asistencia!N19,0) -> 0 | BI18: =IF(ISNUMBER(Asistencia!O19),Asistencia!O19,0) -> 0 | BJ18: =IF(ISNUMBER(Asistencia!P19),Asistencia!P19,0) -> 0 | BK18: =IF(Asistencia!F19="","",Asistencia!F19) | BL18: =IF(Asistencia!G19="","",Asistencia!G19) | BM18: =IF(Asistencia!H19="","",Asistencia!H19) | BN18: =IF(Asistencia!I19="","",Asistencia!I19) | BO18: =IF(Asistencia!J19="","",Asistencia!J19) | BP18: =IF(Asistencia!K19="","",Asistencia!K19) | BQ18: =IF(Asistencia!L19="","",Asistencia!L19)
A19: =IF(Y19="","",INDEX($AB$5:$AB$323,Y19)) | B19: =IF(Y19="","",INDEX($AD$5:$AD$323,Y19)) | E19: =IF($A19="","",_xlfn.TEXTJOIN(" / ",TRUE(),IF(SUMIFS($AP$5:$AP$323,$AA$5:$AA$323,$Z19,$AF$5:$AF$323,"ARMIDA")>0,IFERROR("ARMIDA-"&INDEX($AE$5:$AE$323,MATCH($Z19&"ARMIDA",$AA$5:$AA$323&$AF$5:$AF$323,0)),"ARMIDA"),""),IF(SUMIFS($AP$5:$AP$323,$AA$5:$AA$323,$Z19,$AF$5:$AF$323,"AURIGA")>0,IFERROR("AURIGA-"&INDEX($AE$5:$AE$323,MATCH($Z19&"AURIGA",$AA$5:$AA$323&$AF$5:$AF$323,0)),"AURIGA"),""),IF(SUMIFS($AP$5:$AP$323,$AA$5:$AA$323,$Z19,$AF$5:$AF$323,"AURORA")>0,IFERROR("AURORA-"&INDEX($AE$5:$AE$323,MATCH($Z19&"AURORA",$AA$5:$AA$323&$AF$5:$AF$323,0)),"AURORA"),""),IF(SUMIFS($AP$5:$AP$323,$AA$5:$AA$323,$Z19,$AF$5:$AF$323,"CITICA")>0,IFERROR("CITICA-"&INDEX($AE$5:$AE$323,MATCH($Z19&"CITICA",$AA$5:$AA$323&$AF$5:$AF$323,0)),"CITICA"),""),IF(SUMIFS($AP$5:$AP$323,$AA$5:$AA$323,$Z19,$AF$5:$AF$323,"GM")>0,IFERROR("GM-"&INDEX($AE$5:$AE$323,MATCH($Z19&"GM",$AA$5:$AA$323&$AF$5:$AF$323,0)),"GM"),""),IF(SUMIFS($AP$5:$AP$323,$AA$5:$AA$323,$Z19,$AF$5:$AF$323,"TORRE BALZAK")>0,IFERROR("TORRE BALZAK-"&INDEX($AE$5:$AE$323,MATCH($Z19&"TORRE BALZAK",$AA$5:$AA$323&$AF$5:$AF$323,0)),"TORRE BALZAK"),""),IF(SUMIFS($AP$5:$AP$323,$AA$5:$AA$323,$Z19,$AF$5:$AF$323,"TORRE OLMA")>0,IFERROR("TORRE OLMA-"&INDEX($AE$5:$AE$323,MATCH($Z19&"TORRE OLMA",$AA$5:$AA$323&$AF$5:$AF$323,0)),"TORRE OLMA"),""),IF(SUMIFS($AP$5:$AP$323,$AA$5:$AA$323,$Z19,$AF$5:$AF$323,"OTROS")>0,IFERROR("OTROS-"&INDEX($AE$5:$AE$323,MATCH($Z19&"OTROS",$AA$5:$AA$323&$AF$5:$AF$323,0)),"OTROS"),""))) | F19: =IF($A19="","",IFERROR(INDEX($BK$5:$BK$323,MATCH($Z19,$AA$5:$AA$323,0)),"-")) | G19: =IF($A19="","",IFERROR(INDEX($BL$5:$BL$323,MATCH($Z19,$AA$5:$AA$323,0)),"-")) | H19: =IF($A19="","",IFERROR(INDEX($BM$5:$BM$323,MATCH($Z19,$AA$5:$AA$323,0)),"-")) | I19: =IF($A19="","",IFERROR(INDEX($BN$5:$BN$323,MATCH($Z19,$AA$5:$AA$323,0)),"-")) | J19: =IF($A19="","",IFERROR(INDEX($BO$5:$BO$323,MATCH($Z19,$AA$5:$AA$323,0)),"-")) | K19: =IF($A19="","",IFERROR(INDEX($BP$5:$BP$323,MATCH($Z19,$AA$5:$AA$323,0)),"-")) | L19: =IF($A19="","",IFERROR(INDEX($BQ$5:$BQ$323,MATCH($Z19,$AA$5:$AA$323,0)),"-")) | M19: =IF($A19="","",(--(SUMIF($AA$5:$AA$323,$Z19,$AI$5:$AI$323)>0))+(--(SUMIF($AA$5:$AA$323,$Z19,$AJ$5:$AJ$323)>0))+(--(SUMIF($AA$5:$AA$323,$Z19,$AK$5:$AK$323)>0))+(--(SUMIF($AA$5:$AA$323,$Z19,$AL$5:$AL$323)>0))+(--(SUMIF($AA$5:$AA$323,$Z19,$AM$5:$AM$323)>0))+(--(SUMIF($AA$5:$AA$323,$Z19,$AN$5:$AN$323)>0))+(--(SUMIF($AA$5:$AA$323,$Z19,$AO$5:$AO$323)>0))) | N19: =IF($A19="","",MAX(0,M19-6)) | O19: =IF($A19="","",SUMIF($AA$5:$AA$323,$Z19,$AP$5:$AP$323)-M19) | P19: =IF($A19="","",SUMIF($AA$5:$AA$323,$Z19,$BG$5:$BG$323)) | Q19: =IF($A19="","",SUMIF($AA$5:$AA$323,$Z19,$BH$5:$BH$323)) | R19: =IF($A19="","",SUMIF($AA$5:$AA$323,$Z19,$BI$5:$BI$323)) | U19: =IF($A19="","",SUMIF($AA$5:$AA$323,$Z19,$BJ$5:$BJ$323)) | W19: =IF($A19="","",_xlfn.TEXTJOIN(" | ",TRUE(),IF(N19>0,"+ de 6 días: revisar adicionales",""),IF(O19>0,"Doble evento mismo día: revisar turno/pago",""),IF(SUMIF($AA$5:$AA$323,$Z19,$AX$5:$AX$323)>((--(SUMIF($AA$5:$AA$323,$Z19,$AQ$5:$AQ$323)>0))+(--(SUMIF($AA$5:$AA$323,$Z19,$AR$5:$AR$323)>0))+(--(SUMIF($AA$5:$AA$323,$Z19,$AS$5:$AS$323)>0))+(--(SUMIF($AA$5:$AA$323,$Z19,$AT$5:$AT$323)>0))+(--(SUMIF($AA$5:$AA$323,$Z19,$AU$5:$AU$323)>0))+(--(SUMIF($AA$5:$AA$323,$Z19,$AV$5:$AV$323)>0))+(--(SUMIF($AA$5:$AA$323,$Z19,$AW$5:$AW$323)>0))),"FL múltiple mismo día: revisar pago festivo",""),IF(SUMIF($AA$5:$AA$323,$Z19,$BF$5:$BF$323)>((--(SUMIF($AA$5:$AA$323,$Z19,$AY$5:$AY$323)>0))+(--(SUMIF($AA$5:$AA$323,$Z19,$AZ$5:$AZ$323)>0))+(--(SUMIF($AA$5:$AA$323,$Z19,$BA$5:$BA$323)>0))+(--(SUMIF($AA$5:$AA$323,$Z19,$BB$5:$BB$323)>0))+(--(SUMIF($AA$5:$AA$323,$Z19,$BC$5:$BC$323)>0))+(--(SUMIF($AA$5:$AA$323,$Z19,$BD$5:$BD$323)>0))+(--(SUMIF($AA$5:$AA$323,$Z19,$BE$5:$BE$323)>0))),"DL múltiple mismo día: revisar pago descanso",""))) | Y19: =IFERROR(MATCH(15,$AH$5:$AH$323,0),"") | Z19: =IF(Y19="","",INDEX($AA$5:$AA$323,Y19)) | AA19: =IF(AC19="","","M:"&AC19) | AB19: =IF(Asistencia!A20="","",Asistencia!A20) | AC19: =IF(Asistencia!A20="","",SUBSTITUTE(SUBSTITUTE(SUBSTITUTE(SUBSTITUTE(SUBSTITUTE(SUBSTITUTE(SUBSTITUTE(UPPER(TRIM(Asistencia!A20)),"Á","A"),"É","E"),"Í","I"),"Ó","O"),"Ú","U"),"Ñ","N")," "," ")) | AD19: =IF(Asistencia!E20="","",Asistencia!E20) | AE19: =IF(Asistencia!D20="","",UPPER(TRIM(Asistencia!D20))) | AF19: ARMIDA | AG19: =IF(AND(AA19<>"",COUNTIF($AA$5:AA19,AA19)=1),1,0) -> 0 | AH19: =IF(AG19=1,SUM($AG$5:AG19),"") | AI19: =IF(OR(EXACT(Asistencia!F20,"A"),EXACT(Asistencia!F20,"R"),EXACT(Asistencia!F20,"DL"),EXACT(Asistencia!F20,"FL"),EXACT(Asistencia!F20,"FE"),EXACT(Asistencia!F20,"PCS"),EXACT(Asistencia!F20,"V")),1,0) -> 0 | AJ19: =IF(OR(EXACT(Asistencia!G20,"A"),EXACT(Asistencia!G20,"R"),EXACT(Asistencia!G20,"DL"),EXACT(Asistencia!G20,"FL"),EXACT(Asistencia!G20,"FE"),EXACT(Asistencia!G20,"PCS"),EXACT(Asistencia!G20,"V")),1,0) -> 0 | AK19: =IF(OR(EXACT(Asistencia!H20,"A"),EXACT(Asistencia!H20,"R"),EXACT(Asistencia!H20,"DL"),EXACT(Asistencia!H20,"FL"),EXACT(Asistencia!H20,"FE"),EXACT(Asistencia!H20,"PCS"),EXACT(Asistencia!H20,"V")),1,0) -> 0 | AL19: =IF(OR(EXACT(Asistencia!I20,"A"),EXACT(Asistencia!I20,"R"),EXACT(Asistencia!I20,"DL"),EXACT(Asistencia!I20,"FL"),EXACT(Asistencia!I20,"FE"),EXACT(Asistencia!I20,"PCS"),EXACT(Asistencia!I20,"V")),1,0) -> 0 | AM19: =IF(OR(EXACT(Asistencia!J20,"A"),EXACT(Asistencia!J20,"R"),EXACT(Asistencia!J20,"DL"),EXACT(Asistencia!J20,"FL"),EXACT(Asistencia!J20,"FE"),EXACT(Asistencia!J20,"PCS"),EXACT(Asistencia!J20,"V")),1,0) -> 0 | AN19: =IF(OR(EXACT(Asistencia!K20,"A"),EXACT(Asistencia!K20,"R"),EXACT(Asistencia!K20,"DL"),EXACT(Asistencia!K20,"FL"),EXACT(Asistencia!K20,"FE"),EXACT(Asistencia!K20,"PCS"),EXACT(Asistencia!K20,"V")),1,0) -> 0 | AO19: =IF(OR(EXACT(Asistencia!L20,"A"),EXACT(Asistencia!L20,"R"),EXACT(Asistencia!L20,"DL"),EXACT(Asistencia!L20,"FL"),EXACT(Asistencia!L20,"FE"),EXACT(Asistencia!L20,"PCS"),EXACT(Asistencia!L20,"V")),1,0) -> 0 | AP19: =SUM(AI19:AO19) -> 0 | AQ19: =IF(EXACT(Asistencia!F20,"FL"),1,0) -> 0 | AR19: =IF(EXACT(Asistencia!G20,"FL"),1,0) -> 0 | AS19: =IF(EXACT(Asistencia!H20,"FL"),1,0) -> 0 | AT19: =IF(EXACT(Asistencia!I20,"FL"),1,0) -> 0 | AU19: =IF(EXACT(Asistencia!J20,"FL"),1,0) -> 0 | AV19: =IF(EXACT(Asistencia!K20,"FL"),1,0) -> 0 | AW19: =IF(EXACT(Asistencia!L20,"FL"),1,0) -> 0 | AX19: =SUM(AQ19:AW19) -> 0 | AY19: =IF(EXACT(Asistencia!F20,"DL"),1,0) -> 0 | AZ19: =IF(EXACT(Asistencia!G20,"DL"),1,0) -> 0 | BA19: =IF(EXACT(Asistencia!H20,"DL"),1,0) -> 0 | BB19: =IF(EXACT(Asistencia!I20,"DL"),1,0) -> 0 | BC19: =IF(EXACT(Asistencia!J20,"DL"),1,0) -> 0 | BD19: =IF(EXACT(Asistencia!K20,"DL"),1,0) -> 0 | BE19: =IF(EXACT(Asistencia!L20,"DL"),1,0) -> 0 | BF19: =SUM(AY19:BE19) -> 0 | BG19: =IF(ISNUMBER(Asistencia!M20),Asistencia!M20,0) -> 0 | BH19: =IF(ISNUMBER(Asistencia!N20),Asistencia!N20,0) -> 0 | BI19: =IF(ISNUMBER(Asistencia!O20),Asistencia!O20,0) -> 0 | BJ19: =IF(ISNUMBER(Asistencia!P20),Asistencia!P20,0) -> 0 | BK19: =IF(Asistencia!F20="","",Asistencia!F20) | BL19: =IF(Asistencia!G20="","",Asistencia!G20) | BM19: =IF(Asistencia!H20="","",Asistencia!H20) | BN19: =IF(Asistencia!I20="","",Asistencia!I20) | BO19: =IF(Asistencia!J20="","",Asistencia!J20) | BP19: =IF(Asistencia!K20="","",Asistencia!K20) | BQ19: =IF(Asistencia!L20="","",Asistencia!L20)
A20: =IF(Y20="","",INDEX($AB$5:$AB$323,Y20)) | B20: =IF(Y20="","",INDEX($AD$5:$AD$323,Y20)) | E20: =IF($A20="","",_xlfn.TEXTJOIN(" / ",TRUE(),IF(SUMIFS($AP$5:$AP$323,$AA$5:$AA$323,$Z20,$AF$5:$AF$323,"ARMIDA")>0,IFERROR("ARMIDA-"&INDEX($AE$5:$AE$323,MATCH($Z20&"ARMIDA",$AA$5:$AA$323&$AF$5:$AF$323,0)),"ARMIDA"),""),IF(SUMIFS($AP$5:$AP$323,$AA$5:$AA$323,$Z20,$AF$5:$AF$323,"AURIGA")>0,IFERROR("AURIGA-"&INDEX($AE$5:$AE$323,MATCH($Z20&"AURIGA",$AA$5:$AA$323&$AF$5:$AF$323,0)),"AURIGA"),""),IF(SUMIFS($AP$5:$AP$323,$AA$5:$AA$323,$Z20,$AF$5:$AF$323,"AURORA")>0,IFERROR("AURORA-"&INDEX($AE$5:$AE$323,MATCH($Z20&"AURORA",$AA$5:$AA$323&$AF$5:$AF$323,0)),"AURORA"),""),IF(SUMIFS($AP$5:$AP$323,$AA$5:$AA$323,$Z20,$AF$5:$AF$323,"CITICA")>0,IFERROR("CITICA-"&INDEX($AE$5:$AE$323,MATCH($Z20&"CITICA",$AA$5:$AA$323&$AF$5:$AF$323,0)),"CITICA"),""),IF(SUMIFS($AP$5:$AP$323,$AA$5:$AA$323,$Z20,$AF$5:$AF$323,"GM")>0,IFERROR("GM-"&INDEX($AE$5:$AE$323,MATCH($Z20&"GM",$AA$5:$AA$323&$AF$5:$AF$323,0)),"GM"),""),IF(SUMIFS($AP$5:$AP$323,$AA$5:$AA$323,$Z20,$AF$5:$AF$323,"TORRE BALZAK")>0,IFERROR("TORRE BALZAK-"&INDEX($AE$5:$AE$323,MATCH($Z20&"TORRE BALZAK",$AA$5:$AA$323&$AF$5:$AF$323,0)),"TORRE BALZAK"),""),IF(SUMIFS($AP$5:$AP$323,$AA$5:$AA$323,$Z20,$AF$5:$AF$323,"TORRE OLMA")>0,IFERROR("TORRE OLMA-"&INDEX($AE$5:$AE$323,MATCH($Z20&"TORRE OLMA",$AA$5:$AA$323&$AF$5:$AF$323,0)),"TORRE OLMA"),""),IF(SUMIFS($AP$5:$AP$323,$AA$5:$AA$323,$Z20,$AF$5:$AF$323,"OTROS")>0,IFERROR("OTROS-"&INDEX($AE$5:$AE$323,MATCH($Z20&"OTROS",$AA$5:$AA$323&$AF$5:$AF$323,0)),"OTROS"),""))) | F20: =IF($A20="","",IFERROR(INDEX($BK$5:$BK$323,MATCH($Z20,$AA$5:$AA$323,0)),"-")) | G20: =IF($A20="","",IFERROR(INDEX($BL$5:$BL$323,MATCH($Z20,$AA$5:$AA$323,0)),"-")) | H20: =IF($A20="","",IFERROR(INDEX($BM$5:$BM$323,MATCH($Z20,$AA$5:$AA$323,0)),"-")) | I20: =IF($A20="","",IFERROR(INDEX($BN$5:$BN$323,MATCH($Z20,$AA$5:$AA$323,0)),"-")) | J20: =IF($A20="","",IFERROR(INDEX($BO$5:$BO$323,MATCH($Z20,$AA$5:$AA$323,0)),"-")) | K20: =IF($A20="","",IFERROR(INDEX($BP$5:$BP$323,MATCH($Z20,$AA$5:$AA$323,0)),"-")) | L20: =IF($A20="","",IFERROR(INDEX($BQ$5:$BQ$323,MATCH($Z20,$AA$5:$AA$323,0)),"-")) | M20: =IF($A20="","",(--(SUMIF($AA$5:$AA$323,$Z20,$AI$5:$AI$323)>0))+(--(SUMIF($AA$5:$AA$323,$Z20,$AJ$5:$AJ$323)>0))+(--(SUMIF($AA$5:$AA$323,$Z20,$AK$5:$AK$323)>0))+(--(SUMIF($AA$5:$AA$323,$Z20,$AL$5:$AL$323)>0))+(--(SUMIF($AA$5:$AA$323,$Z20,$AM$5:$AM$323)>0))+(--(SUMIF($AA$5:$AA$323,$Z20,$AN$5:$AN$323)>0))+(--(SUMIF($AA$5:$AA$323,$Z20,$AO$5:$AO$323)>0))) | N20: =IF($A20="","",MAX(0,M20-6)) | O20: =IF($A20="","",SUMIF($AA$5:$AA$323,$Z20,$AP$5:$AP$323)-M20) | P20: =IF($A20="","",SUMIF($AA$5:$AA$323,$Z20,$BG$5:$BG$323)) | Q20: =IF($A20="","",SUMIF($AA$5:$AA$323,$Z20,$BH$5:$BH$323)) | R20: =IF($A20="","",SUMIF($AA$5:$AA$323,$Z20,$BI$5:$BI$323)) | U20: =IF($A20="","",SUMIF($AA$5:$AA$323,$Z20,$BJ$5:$BJ$323)) | W20: =IF($A20="","",_xlfn.TEXTJOIN(" | ",TRUE(),IF(N20>0,"+ de 6 días: revisar adicionales",""),IF(O20>0,"Doble evento mismo día: revisar turno/pago",""),IF(SUMIF($AA$5:$AA$323,$Z20,$AX$5:$AX$323)>((--(SUMIF($AA$5:$AA$323,$Z20,$AQ$5:$AQ$323)>0))+(--(SUMIF($AA$5:$AA$323,$Z20,$AR$5:$AR$323)>0))+(--(SUMIF($AA$5:$AA$323,$Z20,$AS$5:$AS$323)>0))+(--(SUMIF($AA$5:$AA$323,$Z20,$AT$5:$AT$323)>0))+(--(SUMIF($AA$5:$AA$323,$Z20,$AU$5:$AU$323)>0))+(--(SUMIF($AA$5:$AA$323,$Z20,$AV$5:$AV$323)>0))+(--(SUMIF($AA$5:$AA$323,$Z20,$AW$5:$AW$323)>0))),"FL múltiple mismo día: revisar pago festivo",""),IF(SUMIF($AA$5:$AA$323,$Z20,$BF$5:$BF$323)>((--(SUMIF($AA$5:$AA$323,$Z20,$AY$5:$AY$323)>0))+(--(SUMIF($AA$5:$AA$323,$Z20,$AZ$5:$AZ$323)>0))+(--(SUMIF($AA$5:$AA$323,$Z20,$BA$5:$BA$323)>0))+(--(SUMIF($AA$5:$AA$323,$Z20,$BB$5:$BB$323)>0))+(--(SUMIF($AA$5:$AA$323,$Z20,$BC$5:$BC$323)>0))+(--(SUMIF($AA$5:$AA$323,$Z20,$BD$5:$BD$323)>0))+(--(SUMIF($AA$5:$AA$323,$Z20,$BE$5:$BE$323)>0))),"DL múltiple mismo día: revisar pago descanso",""))) | Y20: =IFERROR(MATCH(16,$AH$5:$AH$323,0),"") | Z20: =IF(Y20="","",INDEX($AA$5:$AA$323,Y20)) | AA20: =IF(AC20="","","M:"&AC20) | AB20: =IF(Asistencia!A21="","",Asistencia!A21) | AC20: =IF(Asistencia!A21="","",SUBSTITUTE(SUBSTITUTE(SUBSTITUTE(SUBSTITUTE(SUBSTITUTE(SUBSTITUTE(SUBSTITUTE(UPPER(TRIM(Asistencia!A21)),"Á","A"),"É","E"),"Í","I"),"Ó","O"),"Ú","U"),"Ñ","N")," "," ")) | AD20: =IF(Asistencia!E21="","",Asistencia!E21) | AE20: =IF(Asistencia!D21="","",UPPER(TRIM(Asistencia!D21))) | AF20: ARMIDA | AG20: =IF(AND(AA20<>"",COUNTIF($AA$5:AA20,AA20)=1),1,0) -> 0 | AH20: =IF(AG20=1,SUM($AG$5:AG20),"") | AI20: =IF(OR(EXACT(Asistencia!F21,"A"),EXACT(Asistencia!F21,"R"),EXACT(Asistencia!F21,"DL"),EXACT(Asistencia!F21,"FL"),EXACT(Asistencia!F21,"FE"),EXACT(Asistencia!F21,"PCS"),EXACT(Asistencia!F21,"V")),1,0) -> 0 | AJ20: =IF(OR(EXACT(Asistencia!G21,"A"),EXACT(Asistencia!G21,"R"),EXACT(Asistencia!G21,"DL"),EXACT(Asistencia!G21,"FL"),EXACT(Asistencia!G21,"FE"),EXACT(Asistencia!G21,"PCS"),EXACT(Asistencia!G21,"V")),1,0) -> 0 | AK20: =IF(OR(EXACT(Asistencia!H21,"A"),EXACT(Asistencia!H21,"R"),EXACT(Asistencia!H21,"DL"),EXACT(Asistencia!H21,"FL"),EXACT(Asistencia!H21,"FE"),EXACT(Asistencia!H21,"PCS"),EXACT(Asistencia!H21,"V")),1,0) -> 0 | AL20: =IF(OR(EXACT(Asistencia!I21,"A"),EXACT(Asistencia!I21,"R"),EXACT(Asistencia!I21,"DL"),EXACT(Asistencia!I21,"FL"),EXACT(Asistencia!I21,"FE"),EXACT(Asistencia!I21,"PCS"),EXACT(Asistencia!I21,"V")),1,0) -> 0 | AM20: =IF(OR(EXACT(Asistencia!J21,"A"),EXACT(Asistencia!J21,"R"),EXACT(Asistencia!J21,"DL"),EXACT(Asistencia!J21,"FL"),EXACT(Asistencia!J21,"FE"),EXACT(Asistencia!J21,"PCS"),EXACT(Asistencia!J21,"V")),1,0) -> 0 | AN20: =IF(OR(EXACT(Asistencia!K21,"A"),EXACT(Asistencia!K21,"R"),EXACT(Asistencia!K21,"DL"),EXACT(Asistencia!K21,"FL"),EXACT(Asistencia!K21,"FE"),EXACT(Asistencia!K21,"PCS"),EXACT(Asistencia!K21,"V")),1,0) -> 0 | AO20: =IF(OR(EXACT(Asistencia!L21,"A"),EXACT(Asistencia!L21,"R"),EXACT(Asistencia!L21,"DL"),EXACT(Asistencia!L21,"FL"),EXACT(Asistencia!L21,"FE"),EXACT(Asistencia!L21,"PCS"),EXACT(Asistencia!L21,"V")),1,0) -> 0 | AP20: =SUM(AI20:AO20) -> 0 | AQ20: =IF(EXACT(Asistencia!F21,"FL"),1,0) -> 0 | AR20: =IF(EXACT(Asistencia!G21,"FL"),1,0) -> 0 | AS20: =IF(EXACT(Asistencia!H21,"FL"),1,0) -> 0 | AT20: =IF(EXACT(Asistencia!I21,"FL"),1,0) -> 0 | AU20: =IF(EXACT(Asistencia!J21,"FL"),1,0) -> 0 | AV20: =IF(EXACT(Asistencia!K21,"FL"),1,0) -> 0 | AW20: =IF(EXACT(Asistencia!L21,"FL"),1,0) -> 0 | AX20: =SUM(AQ20:AW20) -> 0 | AY20: =IF(EXACT(Asistencia!F21,"DL"),1,0) -> 0 | AZ20: =IF(EXACT(Asistencia!G21,"DL"),1,0) -> 0 | BA20: =IF(EXACT(Asistencia!H21,"DL"),1,0) -> 0 | BB20: =IF(EXACT(Asistencia!I21,"DL"),1,0) -> 0 | BC20: =IF(EXACT(Asistencia!J21,"DL"),1,0) -> 0 | BD20: =IF(EXACT(Asistencia!K21,"DL"),1,0) -> 0 | BE20: =IF(EXACT(Asistencia!L21,"DL"),1,0) -> 0 | BF20: =SUM(AY20:BE20) -> 0 | BG20: =IF(ISNUMBER(Asistencia!M21),Asistencia!M21,0) -> 0 | BH20: =IF(ISNUMBER(Asistencia!N21),Asistencia!N21,0) -> 0 | BI20: =IF(ISNUMBER(Asistencia!O21),Asistencia!O21,0) -> 0 | BJ20: =IF(ISNUMBER(Asistencia!P21),Asistencia!P21,0) -> 0 | BK20: =IF(Asistencia!F21="","",Asistencia!F21) | BL20: =IF(Asistencia!G21="","",Asistencia!G21) | BM20: =IF(Asistencia!H21="","",Asistencia!H21) | BN20: =IF(Asistencia!I21="","",Asistencia!I21) | BO20: =IF(Asistencia!J21="","",Asistencia!J21) | BP20: =IF(Asistencia!K21="","",Asistencia!K21) | BQ20: =IF(Asistencia!L21="","",Asistencia!L21)
A21: =IF(Y21="","",INDEX($AB$5:$AB$323,Y21)) | B21: =IF(Y21="","",INDEX($AD$5:$AD$323,Y21)) | E21: =IF($A21="","",_xlfn.TEXTJOIN(" / ",TRUE(),IF(SUMIFS($AP$5:$AP$323,$AA$5:$AA$323,$Z21,$AF$5:$AF$323,"ARMIDA")>0,IFERROR("ARMIDA-"&INDEX($AE$5:$AE$323,MATCH($Z21&"ARMIDA",$AA$5:$AA$323&$AF$5:$AF$323,0)),"ARMIDA"),""),IF(SUMIFS($AP$5:$AP$323,$AA$5:$AA$323,$Z21,$AF$5:$AF$323,"AURIGA")>0,IFERROR("AURIGA-"&INDEX($AE$5:$AE$323,MATCH($Z21&"AURIGA",$AA$5:$AA$323&$AF$5:$AF$323,0)),"AURIGA"),""),IF(SUMIFS($AP$5:$AP$323,$AA$5:$AA$323,$Z21,$AF$5:$AF$323,"AURORA")>0,IFERROR("AURORA-"&INDEX($AE$5:$AE$323,MATCH($Z21&"AURORA",$AA$5:$AA$323&$AF$5:$AF$323,0)),"AURORA"),""),IF(SUMIFS($AP$5:$AP$323,$AA$5:$AA$323,$Z21,$AF$5:$AF$323,"CITICA")>0,IFERROR("CITICA-"&INDEX($AE$5:$AE$323,MATCH($Z21&"CITICA",$AA$5:$AA$323&$AF$5:$AF$323,0)),"CITICA"),""),IF(SUMIFS($AP$5:$AP$323,$AA$5:$AA$323,$Z21,$AF$5:$AF$323,"GM")>0,IFERROR("GM-"&INDEX($AE$5:$AE$323,MATCH($Z21&"GM",$AA$5:$AA$323&$AF$5:$AF$323,0)),"GM"),""),IF(SUMIFS($AP$5:$AP$323,$AA$5:$AA$323,$Z21,$AF$5:$AF$323,"TORRE BALZAK")>0,IFERROR("TORRE BALZAK-"&INDEX($AE$5:$AE$323,MATCH($Z21&"TORRE BALZAK",$AA$5:$AA$323&$AF$5:$AF$323,0)),"TORRE BALZAK"),""),IF(SUMIFS($AP$5:$AP$323,$AA$5:$AA$323,$Z21,$AF$5:$AF$323,"TORRE OLMA")>0,IFERROR("TORRE OLMA-"&INDEX($AE$5:$AE$323,MATCH($Z21&"TORRE OLMA",$AA$5:$AA$323&$AF$5:$AF$323,0)),"TORRE OLMA"),""),IF(SUMIFS($AP$5:$AP$323,$AA$5:$AA$323,$Z21,$AF$5:$AF$323,"OTROS")>0,IFERROR("OTROS-"&INDEX($AE$5:$AE$323,MATCH($Z21&"OTROS",$AA$5:$AA$323&$AF$5:$AF$323,0)),"OTROS"),""))) | F21: =IF($A21="","",IFERROR(INDEX($BK$5:$BK$323,MATCH($Z21,$AA$5:$AA$323,0)),"-")) | G21: =IF($A21="","",IFERROR(INDEX($BL$5:$BL$323,MATCH($Z21,$AA$5:$AA$323,0)),"-")) | H21: =IF($A21="","",IFERROR(INDEX($BM$5:$BM$323,MATCH($Z21,$AA$5:$AA$323,0)),"-")) | I21: =IF($A21="","",IFERROR(INDEX($BN$5:$BN$323,MATCH($Z21,$AA$5:$AA$323,0)),"-")) | J21: =IF($A21="","",IFERROR(INDEX($BO$5:$BO$323,MATCH($Z21,$AA$5:$AA$323,0)),"-")) | K21: =IF($A21="","",IFERROR(INDEX($BP$5:$BP$323,MATCH($Z21,$AA$5:$AA$323,0)),"-")) | L21: =IF($A21="","",IFERROR(INDEX($BQ$5:$BQ$323,MATCH($Z21,$AA$5:$AA$323,0)),"-")) | M21: =IF($A21="","",(--(SUMIF($AA$5:$AA$323,$Z21,$AI$5:$AI$323)>0))+(--(SUMIF($AA$5:$AA$323,$Z21,$AJ$5:$AJ$323)>0))+(--(SUMIF($AA$5:$AA$323,$Z21,$AK$5:$AK$323)>0))+(--(SUMIF($AA$5:$AA$323,$Z21,$AL$5:$AL$323)>0))+(--(SUMIF($AA$5:$AA$323,$Z21,$AM$5:$AM$323)>0))+(--(SUMIF($AA$5:$AA$323,$Z21,$AN$5:$AN$323)>0))+(--(SUMIF($AA$5:$AA$323,$Z21,$AO$5:$AO$323)>0))) | N21: =IF($A21="","",MAX(0,M21-6)) | O21: =IF($A21="","",SUMIF($AA$5:$AA$323,$Z21,$AP$5:$AP$323)-M21) | P21: =IF($A21="","",SUMIF($AA$5:$AA$323,$Z21,$BG$5:$BG$323)) | Q21: =IF($A21="","",SUMIF($AA$5:$AA$323,$Z21,$BH$5:$BH$323)) | R21: =IF($A21="","",SUMIF($AA$5:$AA$323,$Z21,$BI$5:$BI$323)) | U21: =IF($A21="","",SUMIF($AA$5:$AA$323,$Z21,$BJ$5:$BJ$323)) | W21: =IF($A21="","",_xlfn.TEXTJOIN(" | ",TRUE(),IF(N21>0,"+ de 6 días: revisar adicionales",""),IF(O21>0,"Doble evento mismo día: revisar turno/pago",""),IF(SUMIF($AA$5:$AA$323,$Z21,$AX$5:$AX$323)>((--(SUMIF($AA$5:$AA$323,$Z21,$AQ$5:$AQ$323)>0))+(--(SUMIF($AA$5:$AA$323,$Z21,$AR$5:$AR$323)>0))+(--(SUMIF($AA$5:$AA$323,$Z21,$AS$5:$AS$323)>0))+(--(SUMIF($AA$5:$AA$323,$Z21,$AT$5:$AT$323)>0))+(--(SUMIF($AA$5:$AA$323,$Z21,$AU$5:$AU$323)>0))+(--(SUMIF($AA$5:$AA$323,$Z21,$AV$5:$AV$323)>0))+(--(SUMIF($AA$5:$AA$323,$Z21,$AW$5:$AW$323)>0))),"FL múltiple mismo día: revisar pago festivo",""),IF(SUMIF($AA$5:$AA$323,$Z21,$BF$5:$BF$323)>((--(SUMIF($AA$5:$AA$323,$Z21,$AY$5:$AY$323)>0))+(--(SUMIF($AA$5:$AA$323,$Z21,$AZ$5:$AZ$323)>0))+(--(SUMIF($AA$5:$AA$323,$Z21,$BA$5:$BA$323)>0))+(--(SUMIF($AA$5:$AA$323,$Z21,$BB$5:$BB$323)>0))+(--(SUMIF($AA$5:$AA$323,$Z21,$BC$5:$BC$323)>0))+(--(SUMIF($AA$5:$AA$323,$Z21,$BD$5:$BD$323)>0))+(--(SUMIF($AA$5:$AA$323,$Z21,$BE$5:$BE$323)>0))),"DL múltiple mismo día: revisar pago descanso",""))) | Y21: =IFERROR(MATCH(17,$AH$5:$AH$323,0),"") | Z21: =IF(Y21="","",INDEX($AA$5:$AA$323,Y21)) | AA21: =IF(AC21="","","M:"&AC21) | AB21: =IF(Asistencia!A22="","",Asistencia!A22) | AC21: =IF(Asistencia!A22="","",SUBSTITUTE(SUBSTITUTE(SUBSTITUTE(SUBSTITUTE(SUBSTITUTE(SUBSTITUTE(SUBSTITUTE(UPPER(TRIM(Asistencia!A22)),"Á","A"),"É","E"),"Í","I"),"Ó","O"),"Ú","U"),"Ñ","N")," "," ")) | AD21: =IF(Asistencia!E22="","",Asistencia!E22) | AE21: =IF(Asistencia!D22="","",UPPER(TRIM(Asistencia!D22))) | AF21: ARMIDA | AG21: =IF(AND(AA21<>"",COUNTIF($AA$5:AA21,AA21)=1),1,0) -> 0 | AH21: =IF(AG21=1,SUM($AG$5:AG21),"") | AI21: =IF(OR(EXACT(Asistencia!F22,"A"),EXACT(Asistencia!F22,"R"),EXACT(Asistencia!F22,"DL"),EXACT(Asistencia!F22,"FL"),EXACT(Asistencia!F22,"FE"),EXACT(Asistencia!F22,"PCS"),EXACT(Asistencia!F22,"V")),1,0) -> 0 | AJ21: =IF(OR(EXACT(Asistencia!G22,"A"),EXACT(Asistencia!G22,"R"),EXACT(Asistencia!G22,"DL"),EXACT(Asistencia!G22,"FL"),EXACT(Asistencia!G22,"FE"),EXACT(Asistencia!G22,"PCS"),EXACT(Asistencia!G22,"V")),1,0) -> 0 | AK21: =IF(OR(EXACT(Asistencia!H22,"A"),EXACT(Asistencia!H22,"R"),EXACT(Asistencia!H22,"DL"),EXACT(Asistencia!H22,"FL"),EXACT(Asistencia!H22,"FE"),EXACT(Asistencia!H22,"PCS"),EXACT(Asistencia!H22,"V")),1,0) -> 0 | AL21: =IF(OR(EXACT(Asistencia!I22,"A"),EXACT(Asistencia!I22,"R"),EXACT(Asistencia!I22,"DL"),EXACT(Asistencia!I22,"FL"),EXACT(Asistencia!I22,"FE"),EXACT(Asistencia!I22,"PCS"),EXACT(Asistencia!I22,"V")),1,0) -> 0 | AM21: =IF(OR(EXACT(Asistencia!J22,"A"),EXACT(Asistencia!J22,"R"),EXACT(Asistencia!J22,"DL"),EXACT(Asistencia!J22,"FL"),EXACT(Asistencia!J22,"FE"),EXACT(Asistencia!J22,"PCS"),EXACT(Asistencia!J22,"V")),1,0) -> 0 | AN21: =IF(OR(EXACT(Asistencia!K22,"A"),EXACT(Asistencia!K22,"R"),EXACT(Asistencia!K22,"DL"),EXACT(Asistencia!K22,"FL"),EXACT(Asistencia!K22,"FE"),EXACT(Asistencia!K22,"PCS"),EXACT(Asistencia!K22,"V")),1,0) -> 0 | AO21: =IF(OR(EXACT(Asistencia!L22,"A"),EXACT(Asistencia!L22,"R"),EXACT(Asistencia!L22,"DL"),EXACT(Asistencia!L22,"FL"),EXACT(Asistencia!L22,"FE"),EXACT(Asistencia!L22,"PCS"),EXACT(Asistencia!L22,"V")),1,0) -> 0 | AP21: =SUM(AI21:AO21) -> 0 | AQ21: =IF(EXACT(Asistencia!F22,"FL"),1,0) -> 0 | AR21: =IF(EXACT(Asistencia!G22,"FL"),1,0) -> 0 | AS21: =IF(EXACT(Asistencia!H22,"FL"),1,0) -> 0 | AT21: =IF(EXACT(Asistencia!I22,"FL"),1,0) -> 0 | AU21: =IF(EXACT(Asistencia!J22,"FL"),1,0) -> 0 | AV21: =IF(EXACT(Asistencia!K22,"FL"),1,0) -> 0 | AW21: =IF(EXACT(Asistencia!L22,"FL"),1,0) -> 0 | AX21: =SUM(AQ21:AW21) -> 0 | AY21: =IF(EXACT(Asistencia!F22,"DL"),1,0) -> 0 | AZ21: =IF(EXACT(Asistencia!G22,"DL"),1,0) -> 0 | BA21: =IF(EXACT(Asistencia!H22,"DL"),1,0) -> 0 | BB21: =IF(EXACT(Asistencia!I22,"DL"),1,0) -> 0 | BC21: =IF(EXACT(Asistencia!J22,"DL"),1,0) -> 0 | BD21: =IF(EXACT(Asistencia!K22,"DL"),1,0) -> 0 | BE21: =IF(EXACT(Asistencia!L22,"DL"),1,0) -> 0 | BF21: =SUM(AY21:BE21) -> 0 | BG21: =IF(ISNUMBER(Asistencia!M22),Asistencia!M22,0) -> 0 | BH21: =IF(ISNUMBER(Asistencia!N22),Asistencia!N22,0) -> 0 | BI21: =IF(ISNUMBER(Asistencia!O22),Asistencia!O22,0) -> 0 | BJ21: =IF(ISNUMBER(Asistencia!P22),Asistencia!P22,0) -> 0 | BK21: =IF(Asistencia!F22="","",Asistencia!F22) | BL21: =IF(Asistencia!G22="","",Asistencia!G22) | BM21: =IF(Asistencia!H22="","",Asistencia!H22) | BN21: =IF(Asistencia!I22="","",Asistencia!I22) | BO21: =IF(Asistencia!J22="","",Asistencia!J22) | BP21: =IF(Asistencia!K22="","",Asistencia!K22) | BQ21: =IF(Asistencia!L22="","",Asistencia!L22)
A22: =IF(Y22="","",INDEX($AB$5:$AB$323,Y22)) | B22: =IF(Y22="","",INDEX($AD$5:$AD$323,Y22)) | E22: =IF($A22="","",_xlfn.TEXTJOIN(" / ",TRUE(),IF(SUMIFS($AP$5:$AP$323,$AA$5:$AA$323,$Z22,$AF$5:$AF$323,"ARMIDA")>0,IFERROR("ARMIDA-"&INDEX($AE$5:$AE$323,MATCH($Z22&"ARMIDA",$AA$5:$AA$323&$AF$5:$AF$323,0)),"ARMIDA"),""),IF(SUMIFS($AP$5:$AP$323,$AA$5:$AA$323,$Z22,$AF$5:$AF$323,"AURIGA")>0,IFERROR("AURIGA-"&INDEX($AE$5:$AE$323,MATCH($Z22&"AURIGA",$AA$5:$AA$323&$AF$5:$AF$323,0)),"AURIGA"),""),IF(SUMIFS($AP$5:$AP$323,$AA$5:$AA$323,$Z22,$AF$5:$AF$323,"AURORA")>0,IFERROR("AURORA-"&INDEX($AE$5:$AE$323,MATCH($Z22&"AURORA",$AA$5:$AA$323&$AF$5:$AF$323,0)),"AURORA"),""),IF(SUMIFS($AP$5:$AP$323,$AA$5:$AA$323,$Z22,$AF$5:$AF$323,"CITICA")>0,IFERROR("CITICA-"&INDEX($AE$5:$AE$323,MATCH($Z22&"CITICA",$AA$5:$AA$323&$AF$5:$AF$323,0)),"CITICA"),""),IF(SUMIFS($AP$5:$AP$323,$AA$5:$AA$323,$Z22,$AF$5:$AF$323,"GM")>0,IFERROR("GM-"&INDEX($AE$5:$AE$323,MATCH($Z22&"GM",$AA$5:$AA$323&$AF$5:$AF$323,0)),"GM"),""),IF(SUMIFS($AP$5:$AP$323,$AA$5:$AA$323,$Z22,$AF$5:$AF$323,"TORRE BALZAK")>0,IFERROR("TORRE BALZAK-"&INDEX($AE$5:$AE$323,MATCH($Z22&"TORRE BALZAK",$AA$5:$AA$323&$AF$5:$AF$323,0)),"TORRE BALZAK"),""),IF(SUMIFS($AP$5:$AP$323,$AA$5:$AA$323,$Z22,$AF$5:$AF$323,"TORRE OLMA")>0,IFERROR("TORRE OLMA-"&INDEX($AE$5:$AE$323,MATCH($Z22&"TORRE OLMA",$AA$5:$AA$323&$AF$5:$AF$323,0)),"TORRE OLMA"),""),IF(SUMIFS($AP$5:$AP$323,$AA$5:$AA$323,$Z22,$AF$5:$AF$323,"OTROS")>0,IFERROR("OTROS-"&INDEX($AE$5:$AE$323,MATCH($Z22&"OTROS",$AA$5:$AA$323&$AF$5:$AF$323,0)),"OTROS"),""))) | F22: =IF($A22="","",IFERROR(INDEX($BK$5:$BK$323,MATCH($Z22,$AA$5:$AA$323,0)),"-")) | G22: =IF($A22="","",IFERROR(INDEX($BL$5:$BL$323,MATCH($Z22,$AA$5:$AA$323,0)),"-")) | H22: =IF($A22="","",IFERROR(INDEX($BM$5:$BM$323,MATCH($Z22,$AA$5:$AA$323,0)),"-")) | I22: =IF($A22="","",IFERROR(INDEX($BN$5:$BN$323,MATCH($Z22,$AA$5:$AA$323,0)),"-")) | J22: =IF($A22="","",IFERROR(INDEX($BO$5:$BO$323,MATCH($Z22,$AA$5:$AA$323,0)),"-")) | K22: =IF($A22="","",IFERROR(INDEX($BP$5:$BP$323,MATCH($Z22,$AA$5:$AA$323,0)),"-")) | L22: =IF($A22="","",IFERROR(INDEX($BQ$5:$BQ$323,MATCH($Z22,$AA$5:$AA$323,0)),"-")) | M22: =IF($A22="","",(--(SUMIF($AA$5:$AA$323,$Z22,$AI$5:$AI$323)>0))+(--(SUMIF($AA$5:$AA$323,$Z22,$AJ$5:$AJ$323)>0))+(--(SUMIF($AA$5:$AA$323,$Z22,$AK$5:$AK$323)>0))+(--(SUMIF($AA$5:$AA$323,$Z22,$AL$5:$AL$323)>0))+(--(SUMIF($AA$5:$AA$323,$Z22,$AM$5:$AM$323)>0))+(--(SUMIF($AA$5:$AA$323,$Z22,$AN$5:$AN$323)>0))+(--(SUMIF($AA$5:$AA$323,$Z22,$AO$5:$AO$323)>0))) | N22: =IF($A22="","",MAX(0,M22-6)) | O22: =IF($A22="","",SUMIF($AA$5:$AA$323,$Z22,$AP$5:$AP$323)-M22) | P22: =IF($A22="","",SUMIF($AA$5:$AA$323,$Z22,$BG$5:$BG$323)) | Q22: =IF($A22="","",SUMIF($AA$5:$AA$323,$Z22,$BH$5:$BH$323)) | R22: =IF($A22="","",SUMIF($AA$5:$AA$323,$Z22,$BI$5:$BI$323)) | U22: =IF($A22="","",SUMIF($AA$5:$AA$323,$Z22,$BJ$5:$BJ$323)) | W22: =IF($A22="","",_xlfn.TEXTJOIN(" | ",TRUE(),IF(N22>0,"+ de 6 días: revisar adicionales",""),IF(O22>0,"Doble evento mismo día: revisar turno/pago",""),IF(SUMIF($AA$5:$AA$323,$Z22,$AX$5:$AX$323)>((--(SUMIF($AA$5:$AA$323,$Z22,$AQ$5:$AQ$323)>0))+(--(SUMIF($AA$5:$AA$323,$Z22,$AR$5:$AR$323)>0))+(--(SUMIF($AA$5:$AA$323,$Z22,$AS$5:$AS$323)>0))+(--(SUMIF($AA$5:$AA$323,$Z22,$AT$5:$AT$323)>0))+(--(SUMIF($AA$5:$AA$323,$Z22,$AU$5:$AU$323)>0))+(--(SUMIF($AA$5:$AA$323,$Z22,$AV$5:$AV$323)>0))+(--(SUMIF($AA$5:$AA$323,$Z22,$AW$5:$AW$323)>0))),"FL múltiple mismo día: revisar pago festivo",""),IF(SUMIF($AA$5:$AA$323,$Z22,$BF$5:$BF$323)>((--(SUMIF($AA$5:$AA$323,$Z22,$AY$5:$AY$323)>0))+(--(SUMIF($AA$5:$AA$323,$Z22,$AZ$5:$AZ$323)>0))+(--(SUMIF($AA$5:$AA$323,$Z22,$BA$5:$BA$323)>0))+(--(SUMIF($AA$5:$AA$323,$Z22,$BB$5:$BB$323)>0))+(--(SUMIF($AA$5:$AA$323,$Z22,$BC$5:$BC$323)>0))+(--(SUMIF($AA$5:$AA$323,$Z22,$BD$5:$BD$323)>0))+(--(SUMIF($AA$5:$AA$323,$Z22,$BE$5:$BE$323)>0))),"DL múltiple mismo día: revisar pago descanso",""))) | Y22: =IFERROR(MATCH(18,$AH$5:$AH$323,0),"") | Z22: =IF(Y22="","",INDEX($AA$5:$AA$323,Y22)) | AA22: =IF(AC22="","","M:"&AC22) | AB22: =IF(Asistencia!A23="","",Asistencia!A23) | AC22: =IF(Asistencia!A23="","",SUBSTITUTE(SUBSTITUTE(SUBSTITUTE(SUBSTITUTE(SUBSTITUTE(SUBSTITUTE(SUBSTITUTE(UPPER(TRIM(Asistencia!A23)),"Á","A"),"É","E"),"Í","I"),"Ó","O"),"Ú","U"),"Ñ","N")," "," ")) | AD22: =IF(Asistencia!E23="","",Asistencia!E23) | AE22: =IF(Asistencia!D23="","",UPPER(TRIM(Asistencia!D23))) | AF22: ARMIDA | AG22: =IF(AND(AA22<>"",COUNTIF($AA$5:AA22,AA22)=1),1,0) -> 0 | AH22: =IF(AG22=1,SUM($AG$5:AG22),"") | AI22: =IF(OR(EXACT(Asistencia!F23,"A"),EXACT(Asistencia!F23,"R"),EXACT(Asistencia!F23,"DL"),EXACT(Asistencia!F23,"FL"),EXACT(Asistencia!F23,"FE"),EXACT(Asistencia!F23,"PCS"),EXACT(Asistencia!F23,"V")),1,0) -> 0 | AJ22: =IF(OR(EXACT(Asistencia!G23,"A"),EXACT(Asistencia!G23,"R"),EXACT(Asistencia!G23,"DL"),EXACT(Asistencia!G23,"FL"),EXACT(Asistencia!G23,"FE"),EXACT(Asistencia!G23,"PCS"),EXACT(Asistencia!G23,"V")),1,0) -> 0 | AK22: =IF(OR(EXACT(Asistencia!H23,"A"),EXACT(Asistencia!H23,"R"),EXACT(Asistencia!H23,"DL"),EXACT(Asistencia!H23,"FL"),EXACT(Asistencia!H23,"FE"),EXACT(Asistencia!H23,"PCS"),EXACT(Asistencia!H23,"V")),1,0) -> 0 | AL22: =IF(OR(EXACT(Asistencia!I23,"A"),EXACT(Asistencia!I23,"R"),EXACT(Asistencia!I23,"DL"),EXACT(Asistencia!I23,"FL"),EXACT(Asistencia!I23,"FE"),EXACT(Asistencia!I23,"PCS"),EXACT(Asistencia!I23,"V")),1,0) -> 0 | AM22: =IF(OR(EXACT(Asistencia!J23,"A"),EXACT(Asistencia!J23,"R"),EXACT(Asistencia!J23,"DL"),EXACT(Asistencia!J23,"FL"),EXACT(Asistencia!J23,"FE"),EXACT(Asistencia!J23,"PCS"),EXACT(Asistencia!J23,"V")),1,0) -> 0 | AN22: =IF(OR(EXACT(Asistencia!K23,"A"),EXACT(Asistencia!K23,"R"),EXACT(Asistencia!K23,"DL"),EXACT(Asistencia!K23,"FL"),EXACT(Asistencia!K23,"FE"),EXACT(Asistencia!K23,"PCS"),EXACT(Asistencia!K23,"V")),1,0) -> 0 | AO22: =IF(OR(EXACT(Asistencia!L23,"A"),EXACT(Asistencia!L23,"R"),EXACT(Asistencia!L23,"DL"),EXACT(Asistencia!L23,"FL"),EXACT(Asistencia!L23,"FE"),EXACT(Asistencia!L23,"PCS"),EXACT(Asistencia!L23,"V")),1,0) -> 0 | AP22: =SUM(AI22:AO22) -> 0 | AQ22: =IF(EXACT(Asistencia!F23,"FL"),1,0) -> 0 | AR22: =IF(EXACT(Asistencia!G23,"FL"),1,0) -> 0 | AS22: =IF(EXACT(Asistencia!H23,"FL"),1,0) -> 0 | AT22: =IF(EXACT(Asistencia!I23,"FL"),1,0) -> 0 | AU22: =IF(EXACT(Asistencia!J23,"FL"),1,0) -> 0 | AV22: =IF(EXACT(Asistencia!K23,"FL"),1,0) -> 0 | AW22: =IF(EXACT(Asistencia!L23,"FL"),1,0) -> 0 | AX22: =SUM(AQ22:AW22) -> 0 | AY22: =IF(EXACT(Asistencia!F23,"DL"),1,0) -> 0 | AZ22: =IF(EXACT(Asistencia!G23,"DL"),1,0) -> 0 | BA22: =IF(EXACT(Asistencia!H23,"DL"),1,0) -> 0 | BB22: =IF(EXACT(Asistencia!I23,"DL"),1,0) -> 0 | BC22: =IF(EXACT(Asistencia!J23,"DL"),1,0) -> 0 | BD22: =IF(EXACT(Asistencia!K23,"DL"),1,0) -> 0 | BE22: =IF(EXACT(Asistencia!L23,"DL"),1,0) -> 0 | BF22: =SUM(AY22:BE22) -> 0 | BG22: =IF(ISNUMBER(Asistencia!M23),Asistencia!M23,0) -> 0 | BH22: =IF(ISNUMBER(Asistencia!N23),Asistencia!N23,0) -> 0 | BI22: =IF(ISNUMBER(Asistencia!O23),Asistencia!O23,0) -> 0 | BJ22: =IF(ISNUMBER(Asistencia!P23),Asistencia!P23,0) -> 0 | BK22: =IF(Asistencia!F23="","",Asistencia!F23) | BL22: =IF(Asistencia!G23="","",Asistencia!G23) | BM22: =IF(Asistencia!H23="","",Asistencia!H23) | BN22: =IF(Asistencia!I23="","",Asistencia!I23) | BO22: =IF(Asistencia!J23="","",Asistencia!J23) | BP22: =IF(Asistencia!K23="","",Asistencia!K23) | BQ22: =IF(Asistencia!L23="","",Asistencia!L23)
A23: =IF(Y23="","",INDEX($AB$5:$AB$323,Y23)) | B23: =IF(Y23="","",INDEX($AD$5:$AD$323,Y23)) | E23: =IF($A23="","",_xlfn.TEXTJOIN(" / ",TRUE(),IF(SUMIFS($AP$5:$AP$323,$AA$5:$AA$323,$Z23,$AF$5:$AF$323,"ARMIDA")>0,IFERROR("ARMIDA-"&INDEX($AE$5:$AE$323,MATCH($Z23&"ARMIDA",$AA$5:$AA$323&$AF$5:$AF$323,0)),"ARMIDA"),""),IF(SUMIFS($AP$5:$AP$323,$AA$5:$AA$323,$Z23,$AF$5:$AF$323,"AURIGA")>0,IFERROR("AURIGA-"&INDEX($AE$5:$AE$323,MATCH($Z23&"AURIGA",$AA$5:$AA$323&$AF$5:$AF$323,0)),"AURIGA"),""),IF(SUMIFS($AP$5:$AP$323,$AA$5:$AA$323,$Z23,$AF$5:$AF$323,"AURORA")>0,IFERROR("AURORA-"&INDEX($AE$5:$AE$323,MATCH($Z23&"AURORA",$AA$5:$AA$323&$AF$5:$AF$323,0)),"AURORA"),""),IF(SUMIFS($AP$5:$AP$323,$AA$5:$AA$323,$Z23,$AF$5:$AF$323,"CITICA")>0,IFERROR("CITICA-"&INDEX($AE$5:$AE$323,MATCH($Z23&"CITICA",$AA$5:$AA$323&$AF$5:$AF$323,0)),"CITICA"),""),IF(SUMIFS($AP$5:$AP$323,$AA$5:$AA$323,$Z23,$AF$5:$AF$323,"GM")>0,IFERROR("GM-"&INDEX($AE$5:$AE$323,MATCH($Z23&"GM",$AA$5:$AA$323&$AF$5:$AF$323,0)),"GM"),""),IF(SUMIFS($AP$5:$AP$323,$AA$5:$AA$323,$Z23,$AF$5:$AF$323,"TORRE BALZAK")>0,IFERROR("TORRE BALZAK-"&INDEX($AE$5:$AE$323,MATCH($Z23&"TORRE BALZAK",$AA$5:$AA$323&$AF$5:$AF$323,0)),"TORRE BALZAK"),""),IF(SUMIFS($AP$5:$AP$323,$AA$5:$AA$323,$Z23,$AF$5:$AF$323,"TORRE OLMA")>0,IFERROR("TORRE OLMA-"&INDEX($AE$5:$AE$323,MATCH($Z23&"TORRE OLMA",$AA$5:$AA$323&$AF$5:$AF$323,0)),"TORRE OLMA"),""),IF(SUMIFS($AP$5:$AP$323,$AA$5:$AA$323,$Z23,$AF$5:$AF$323,"OTROS")>0,IFERROR("OTROS-"&INDEX($AE$5:$AE$323,MATCH($Z23&"OTROS",$AA$5:$AA$323&$AF$5:$AF$323,0)),"OTROS"),""))) | F23: =IF($A23="","",IFERROR(INDEX($BK$5:$BK$323,MATCH($Z23,$AA$5:$AA$323,0)),"-")) | G23: =IF($A23="","",IFERROR(INDEX($BL$5:$BL$323,MATCH($Z23,$AA$5:$AA$323,0)),"-")) | H23: =IF($A23="","",IFERROR(INDEX($BM$5:$BM$323,MATCH($Z23,$AA$5:$AA$323,0)),"-")) | I23: =IF($A23="","",IFERROR(INDEX($BN$5:$BN$323,MATCH($Z23,$AA$5:$AA$323,0)),"-")) | J23: =IF($A23="","",IFERROR(INDEX($BO$5:$BO$323,MATCH($Z23,$AA$5:$AA$323,0)),"-")) | K23: =IF($A23="","",IFERROR(INDEX($BP$5:$BP$323,MATCH($Z23,$AA$5:$AA$323,0)),"-")) | L23: =IF($A23="","",IFERROR(INDEX($BQ$5:$BQ$323,MATCH($Z23,$AA$5:$AA$323,0)),"-")) | M23: =IF($A23="","",(--(SUMIF($AA$5:$AA$323,$Z23,$AI$5:$AI$323)>0))+(--(SUMIF($AA$5:$AA$323,$Z23,$AJ$5:$AJ$323)>0))+(--(SUMIF($AA$5:$AA$323,$Z23,$AK$5:$AK$323)>0))+(--(SUMIF($AA$5:$AA$323,$Z23,$AL$5:$AL$323)>0))+(--(SUMIF($AA$5:$AA$323,$Z23,$AM$5:$AM$323)>0))+(--(SUMIF($AA$5:$AA$323,$Z23,$AN$5:$AN$323)>0))+(--(SUMIF($AA$5:$AA$323,$Z23,$AO$5:$AO$323)>0))) | N23: =IF($A23="","",MAX(0,M23-6)) | O23: =IF($A23="","",SUMIF($AA$5:$AA$323,$Z23,$AP$5:$AP$323)-M23) | P23: =IF($A23="","",SUMIF($AA$5:$AA$323,$Z23,$BG$5:$BG$323)) | Q23: =IF($A23="","",SUMIF($AA$5:$AA$323,$Z23,$BH$5:$BH$323)) | R23: =IF($A23="","",SUMIF($AA$5:$AA$323,$Z23,$BI$5:$BI$323)) | U23: =IF($A23="","",SUMIF($AA$5:$AA$323,$Z23,$BJ$5:$BJ$323)) | W23: =IF($A23="","",_xlfn.TEXTJOIN(" | ",TRUE(),IF(N23>0,"+ de 6 días: revisar adicionales",""),IF(O23>0,"Doble evento mismo día: revisar turno/pago",""),IF(SUMIF($AA$5:$AA$323,$Z23,$AX$5:$AX$323)>((--(SUMIF($AA$5:$AA$323,$Z23,$AQ$5:$AQ$323)>0))+(--(SUMIF($AA$5:$AA$323,$Z23,$AR$5:$AR$323)>0))+(--(SUMIF($AA$5:$AA$323,$Z23,$AS$5:$AS$323)>0))+(--(SUMIF($AA$5:$AA$323,$Z23,$AT$5:$AT$323)>0))+(--(SUMIF($AA$5:$AA$323,$Z23,$AU$5:$AU$323)>0))+(--(SUMIF($AA$5:$AA$323,$Z23,$AV$5:$AV$323)>0))+(--(SUMIF($AA$5:$AA$323,$Z23,$AW$5:$AW$323)>0))),"FL múltiple mismo día: revisar pago festivo",""),IF(SUMIF($AA$5:$AA$323,$Z23,$BF$5:$BF$323)>((--(SUMIF($AA$5:$AA$323,$Z23,$AY$5:$AY$323)>0))+(--(SUMIF($AA$5:$AA$323,$Z23,$AZ$5:$AZ$323)>0))+(--(SUMIF($AA$5:$AA$323,$Z23,$BA$5:$BA$323)>0))+(--(SUMIF($AA$5:$AA$323,$Z23,$BB$5:$BB$323)>0))+(--(SUMIF($AA$5:$AA$323,$Z23,$BC$5:$BC$323)>0))+(--(SUMIF($AA$5:$AA$323,$Z23,$BD$5:$BD$323)>0))+(--(SUMIF($AA$5:$AA$323,$Z23,$BE$5:$BE$323)>0))),"DL múltiple mismo día: revisar pago descanso",""))) | Y23: =IFERROR(MATCH(19,$AH$5:$AH$323,0),"") | Z23: =IF(Y23="","",INDEX($AA$5:$AA$323,Y23)) | AA23: =IF(AC23="","","M:"&AC23) | AB23: =IF(Asistencia!A24="","",Asistencia!A24) | AC23: =IF(Asistencia!A24="","",SUBSTITUTE(SUBSTITUTE(SUBSTITUTE(SUBSTITUTE(SUBSTITUTE(SUBSTITUTE(SUBSTITUTE(UPPER(TRIM(Asistencia!A24)),"Á","A"),"É","E"),"Í","I"),"Ó","O"),"Ú","U"),"Ñ","N")," "," ")) | AD23: =IF(Asistencia!E24="","",Asistencia!E24) | AE23: =IF(Asistencia!D24="","",UPPER(TRIM(Asistencia!D24))) | AF23: ARMIDA | AG23: =IF(AND(AA23<>"",COUNTIF($AA$5:AA23,AA23)=1),1,0) -> 0 | AH23: =IF(AG23=1,SUM($AG$5:AG23),"") | AI23: =IF(OR(EXACT(Asistencia!F24,"A"),EXACT(Asistencia!F24,"R"),EXACT(Asistencia!F24,"DL"),EXACT(Asistencia!F24,"FL"),EXACT(Asistencia!F24,"FE"),EXACT(Asistencia!F24,"PCS"),EXACT(Asistencia!F24,"V")),1,0) -> 0 | AJ23: =IF(OR(EXACT(Asistencia!G24,"A"),EXACT(Asistencia!G24,"R"),EXACT(Asistencia!G24,"DL"),EXACT(Asistencia!G24,"FL"),EXACT(Asistencia!G24,"FE"),EXACT(Asistencia!G24,"PCS"),EXACT(Asistencia!G24,"V")),1,0) -> 0 | AK23: =IF(OR(EXACT(Asistencia!H24,"A"),EXACT(Asistencia!H24,"R"),EXACT(Asistencia!H24,"DL"),EXACT(Asistencia!H24,"FL"),EXACT(Asistencia!H24,"FE"),EXACT(Asistencia!H24,"PCS"),EXACT(Asistencia!H24,"V")),1,0) -> 0 | AL23: =IF(OR(EXACT(Asistencia!I24,"A"),EXACT(Asistencia!I24,"R"),EXACT(Asistencia!I24,"DL"),EXACT(Asistencia!I24,"FL"),EXACT(Asistencia!I24,"FE"),EXACT(Asistencia!I24,"PCS"),EXACT(Asistencia!I24,"V")),1,0) -> 0 | AM23: =IF(OR(EXACT(Asistencia!J24,"A"),EXACT(Asistencia!J24,"R"),EXACT(Asistencia!J24,"DL"),EXACT(Asistencia!J24,"FL"),EXACT(Asistencia!J24,"FE"),EXACT(Asistencia!J24,"PCS"),EXACT(Asistencia!J24,"V")),1,0) -> 0 | AN23: =IF(OR(EXACT(Asistencia!K24,"A"),EXACT(Asistencia!K24,"R"),EXACT(Asistencia!K24,"DL"),EXACT(Asistencia!K24,"FL"),EXACT(Asistencia!K24,"FE"),EXACT(Asistencia!K24,"PCS"),EXACT(Asistencia!K24,"V")),1,0) -> 0 | AO23: =IF(OR(EXACT(Asistencia!L24,"A"),EXACT(Asistencia!L24,"R"),EXACT(Asistencia!L24,"DL"),EXACT(Asistencia!L24,"FL"),EXACT(Asistencia!L24,"FE"),EXACT(Asistencia!L24,"PCS"),EXACT(Asistencia!L24,"V")),1,0) -> 0 | AP23: =SUM(AI23:AO23) -> 0 | AQ23: =IF(EXACT(Asistencia!F24,"FL"),1,0) -> 0 | AR23: =IF(EXACT(Asistencia!G24,"FL"),1,0) -> 0 | AS23: =IF(EXACT(Asistencia!H24,"FL"),1,0) -> 0 | AT23: =IF(EXACT(Asistencia!I24,"FL"),1,0) -> 0 | AU23: =IF(EXACT(Asistencia!J24,"FL"),1,0) -> 0 | AV23: =IF(EXACT(Asistencia!K24,"FL"),1,0) -> 0 | AW23: =IF(EXACT(Asistencia!L24,"FL"),1,0) -> 0 | AX23: =SUM(AQ23:AW23) -> 0 | AY23: =IF(EXACT(Asistencia!F24,"DL"),1,0) -> 0 | AZ23: =IF(EXACT(Asistencia!G24,"DL"),1,0) -> 0 | BA23: =IF(EXACT(Asistencia!H24,"DL"),1,0) -> 0 | BB23: =IF(EXACT(Asistencia!I24,"DL"),1,0) -> 0 | BC23: =IF(EXACT(Asistencia!J24,"DL"),1,0) -> 0 | BD23: =IF(EXACT(Asistencia!K24,"DL"),1,0) -> 0 | BE23: =IF(EXACT(Asistencia!L24,"DL"),1,0) -> 0 | BF23: =SUM(AY23:BE23) -> 0 | BG23: =IF(ISNUMBER(Asistencia!M24),Asistencia!M24,0) -> 0 | BH23: =IF(ISNUMBER(Asistencia!N24),Asistencia!N24,0) -> 0 | BI23: =IF(ISNUMBER(Asistencia!O24),Asistencia!O24,0) -> 0 | BJ23: =IF(ISNUMBER(Asistencia!P24),Asistencia!P24,0) -> 0 | BK23: =IF(Asistencia!F24="","",Asistencia!F24) | BL23: =IF(Asistencia!G24="","",Asistencia!G24) | BM23: =IF(Asistencia!H24="","",Asistencia!H24) | BN23: =IF(Asistencia!I24="","",Asistencia!I24) | BO23: =IF(Asistencia!J24="","",Asistencia!J24) | BP23: =IF(Asistencia!K24="","",Asistencia!K24) | BQ23: =IF(Asistencia!L24="","",Asistencia!L24)
A24: =IF(Y24="","",INDEX($AB$5:$AB$323,Y24)) | B24: =IF(Y24="","",INDEX($AD$5:$AD$323,Y24)) | E24: =IF($A24="","",_xlfn.TEXTJOIN(" / ",TRUE(),IF(SUMIFS($AP$5:$AP$323,$AA$5:$AA$323,$Z24,$AF$5:$AF$323,"ARMIDA")>0,IFERROR("ARMIDA-"&INDEX($AE$5:$AE$323,MATCH($Z24&"ARMIDA",$AA$5:$AA$323&$AF$5:$AF$323,0)),"ARMIDA"),""),IF(SUMIFS($AP$5:$AP$323,$AA$5:$AA$323,$Z24,$AF$5:$AF$323,"AURIGA")>0,IFERROR("AURIGA-"&INDEX($AE$5:$AE$323,MATCH($Z24&"AURIGA",$AA$5:$AA$323&$AF$5:$AF$323,0)),"AURIGA"),""),IF(SUMIFS($AP$5:$AP$323,$AA$5:$AA$323,$Z24,$AF$5:$AF$323,"AURORA")>0,IFERROR("AURORA-"&INDEX($AE$5:$AE$323,MATCH($Z24&"AURORA",$AA$5:$AA$323&$AF$5:$AF$323,0)),"AURORA"),""),IF(SUMIFS($AP$5:$AP$323,$AA$5:$AA$323,$Z24,$AF$5:$AF$323,"CITICA")>0,IFERROR("CITICA-"&INDEX($AE$5:$AE$323,MATCH($Z24&"CITICA",$AA$5:$AA$323&$AF$5:$AF$323,0)),"CITICA"),""),IF(SUMIFS($AP$5:$AP$323,$AA$5:$AA$323,$Z24,$AF$5:$AF$323,"GM")>0,IFERROR("GM-"&INDEX($AE$5:$AE$323,MATCH($Z24&"GM",$AA$5:$AA$323&$AF$5:$AF$323,0)),"GM"),""),IF(SUMIFS($AP$5:$AP$323,$AA$5:$AA$323,$Z24,$AF$5:$AF$323,"TORRE BALZAK")>0,IFERROR("TORRE BALZAK-"&INDEX($AE$5:$AE$323,MATCH($Z24&"TORRE BALZAK",$AA$5:$AA$323&$AF$5:$AF$323,0)),"TORRE BALZAK"),""),IF(SUMIFS($AP$5:$AP$323,$AA$5:$AA$323,$Z24,$AF$5:$AF$323,"TORRE OLMA")>0,IFERROR("TORRE OLMA-"&INDEX($AE$5:$AE$323,MATCH($Z24&"TORRE OLMA",$AA$5:$AA$323&$AF$5:$AF$323,0)),"TORRE OLMA"),""),IF(SUMIFS($AP$5:$AP$323,$AA$5:$AA$323,$Z24,$AF$5:$AF$323,"OTROS")>0,IFERROR("OTROS-"&INDEX($AE$5:$AE$323,MATCH($Z24&"OTROS",$AA$5:$AA$323&$AF$5:$AF$323,0)),"OTROS"),""))) | F24: =IF($A24="","",IFERROR(INDEX($BK$5:$BK$323,MATCH($Z24,$AA$5:$AA$323,0)),"-")) | G24: =IF($A24="","",IFERROR(INDEX($BL$5:$BL$323,MATCH($Z24,$AA$5:$AA$323,0)),"-")) | H24: =IF($A24="","",IFERROR(INDEX($BM$5:$BM$323,MATCH($Z24,$AA$5:$AA$323,0)),"-")) | I24: =IF($A24="","",IFERROR(INDEX($BN$5:$BN$323,MATCH($Z24,$AA$5:$AA$323,0)),"-")) | J24: =IF($A24="","",IFERROR(INDEX($BO$5:$BO$323,MATCH($Z24,$AA$5:$AA$323,0)),"-")) | K24: =IF($A24="","",IFERROR(INDEX($BP$5:$BP$323,MATCH($Z24,$AA$5:$AA$323,0)),"-")) | L24: =IF($A24="","",IFERROR(INDEX($BQ$5:$BQ$323,MATCH($Z24,$AA$5:$AA$323,0)),"-")) | M24: =IF($A24="","",(--(SUMIF($AA$5:$AA$323,$Z24,$AI$5:$AI$323)>0))+(--(SUMIF($AA$5:$AA$323,$Z24,$AJ$5:$AJ$323)>0))+(--(SUMIF($AA$5:$AA$323,$Z24,$AK$5:$AK$323)>0))+(--(SUMIF($AA$5:$AA$323,$Z24,$AL$5:$AL$323)>0))+(--(SUMIF($AA$5:$AA$323,$Z24,$AM$5:$AM$323)>0))+(--(SUMIF($AA$5:$AA$323,$Z24,$AN$5:$AN$323)>0))+(--(SUMIF($AA$5:$AA$323,$Z24,$AO$5:$AO$323)>0))) | N24: =IF($A24="","",MAX(0,M24-6)) | O24: =IF($A24="","",SUMIF($AA$5:$AA$323,$Z24,$AP$5:$AP$323)-M24) | P24: =IF($A24="","",SUMIF($AA$5:$AA$323,$Z24,$BG$5:$BG$323)) | Q24: =IF($A24="","",SUMIF($AA$5:$AA$323,$Z24,$BH$5:$BH$323)) | R24: =IF($A24="","",SUMIF($AA$5:$AA$323,$Z24,$BI$5:$BI$323)) | U24: =IF($A24="","",SUMIF($AA$5:$AA$323,$Z24,$BJ$5:$BJ$323)) | W24: =IF($A24="","",_xlfn.TEXTJOIN(" | ",TRUE(),IF(N24>0,"+ de 6 días: revisar adicionales",""),IF(O24>0,"Doble evento mismo día: revisar turno/pago",""),IF(SUMIF($AA$5:$AA$323,$Z24,$AX$5:$AX$323)>((--(SUMIF($AA$5:$AA$323,$Z24,$AQ$5:$AQ$323)>0))+(--(SUMIF($AA$5:$AA$323,$Z24,$AR$5:$AR$323)>0))+(--(SUMIF($AA$5:$AA$323,$Z24,$AS$5:$AS$323)>0))+(--(SUMIF($AA$5:$AA$323,$Z24,$AT$5:$AT$323)>0))+(--(SUMIF($AA$5:$AA$323,$Z24,$AU$5:$AU$323)>0))+(--(SUMIF($AA$5:$AA$323,$Z24,$AV$5:$AV$323)>0))+(--(SUMIF($AA$5:$AA$323,$Z24,$AW$5:$AW$323)>0))),"FL múltiple mismo día: revisar pago festivo",""),IF(SUMIF($AA$5:$AA$323,$Z24,$BF$5:$BF$323)>((--(SUMIF($AA$5:$AA$323,$Z24,$AY$5:$AY$323)>0))+(--(SUMIF($AA$5:$AA$323,$Z24,$AZ$5:$AZ$323)>0))+(--(SUMIF($AA$5:$AA$323,$Z24,$BA$5:$BA$323)>0))+(--(SUMIF($AA$5:$AA$323,$Z24,$BB$5:$BB$323)>0))+(--(SUMIF($AA$5:$AA$323,$Z24,$BC$5:$BC$323)>0))+(--(SUMIF($AA$5:$AA$323,$Z24,$BD$5:$BD$323)>0))+(--(SUMIF($AA$5:$AA$323,$Z24,$BE$5:$BE$323)>0))),"DL múltiple mismo día: revisar pago descanso",""))) | Y24: =IFERROR(MATCH(20,$AH$5:$AH$323,0),"") | Z24: =IF(Y24="","",INDEX($AA$5:$AA$323,Y24)) | AA24: =IF(AC24="","","M:"&AC24) | AB24: =IF(Asistencia!A25="","",Asistencia!A25) | AC24: =IF(Asistencia!A25="","",SUBSTITUTE(SUBSTITUTE(SUBSTITUTE(SUBSTITUTE(SUBSTITUTE(SUBSTITUTE(SUBSTITUTE(UPPER(TRIM(Asistencia!A25)),"Á","A"),"É","E"),"Í","I"),"Ó","O"),"Ú","U"),"Ñ","N")," "," ")) | AD24: =IF(Asistencia!E25="","",Asistencia!E25) | AE24: =IF(Asistencia!D25="","",UPPER(TRIM(Asistencia!D25))) | AF24: ARMIDA | AG24: =IF(AND(AA24<>"",COUNTIF($AA$5:AA24,AA24)=1),1,0) -> 0 | AH24: =IF(AG24=1,SUM($AG$5:AG24),"") | AI24: =IF(OR(EXACT(Asistencia!F25,"A"),EXACT(Asistencia!F25,"R"),EXACT(Asistencia!F25,"DL"),EXACT(Asistencia!F25,"FL"),EXACT(Asistencia!F25,"FE"),EXACT(Asistencia!F25,"PCS"),EXACT(Asistencia!F25,"V")),1,0) -> 0 | AJ24: =IF(OR(EXACT(Asistencia!G25,"A"),EXACT(Asistencia!G25,"R"),EXACT(Asistencia!G25,"DL"),EXACT(Asistencia!G25,"FL"),EXACT(Asistencia!G25,"FE"),EXACT(Asistencia!G25,"PCS"),EXACT(Asistencia!G25,"V")),1,0) -> 0 | AK24: =IF(OR(EXACT(Asistencia!H25,"A"),EXACT(Asistencia!H25,"R"),EXACT(Asistencia!H25,"DL"),EXACT(Asistencia!H25,"FL"),EXACT(Asistencia!H25,"FE"),EXACT(Asistencia!H25,"PCS"),EXACT(Asistencia!H25,"V")),1,0) -> 0 | AL24: =IF(OR(EXACT(Asistencia!I25,"A"),EXACT(Asistencia!I25,"R"),EXACT(Asistencia!I25,"DL"),EXACT(Asistencia!I25,"FL"),EXACT(Asistencia!I25,"FE"),EXACT(Asistencia!I25,"PCS"),EXACT(Asistencia!I25,"V")),1,0) -> 0 | AM24: =IF(OR(EXACT(Asistencia!J25,"A"),EXACT(Asistencia!J25,"R"),EXACT(Asistencia!J25,"DL"),EXACT(Asistencia!J25,"FL"),EXACT(Asistencia!J25,"FE"),EXACT(Asistencia!J25,"PCS"),EXACT(Asistencia!J25,"V")),1,0) -> 0 | AN24: =IF(OR(EXACT(Asistencia!K25,"A"),EXACT(Asistencia!K25,"R"),EXACT(Asistencia!K25,"DL"),EXACT(Asistencia!K25,"FL"),EXACT(Asistencia!K25,"FE"),EXACT(Asistencia!K25,"PCS"),EXACT(Asistencia!K25,"V")),1,0) -> 0 | AO24: =IF(OR(EXACT(Asistencia!L25,"A"),EXACT(Asistencia!L25,"R"),EXACT(Asistencia!L25,"DL"),EXACT(Asistencia!L25,"FL"),EXACT(Asistencia!L25,"FE"),EXACT(Asistencia!L25,"PCS"),EXACT(Asistencia!L25,"V")),1,0) -> 0 | AP24: =SUM(AI24:AO24) -> 0 | AQ24: =IF(EXACT(Asistencia!F25,"FL"),1,0) -> 0 | AR24: =IF(EXACT(Asistencia!G25,"FL"),1,0) -> 0 | AS24: =IF(EXACT(Asistencia!H25,"FL"),1,0) -> 0 | AT24: =IF(EXACT(Asistencia!I25,"FL"),1,0) -> 0 | AU24: =IF(EXACT(Asistencia!J25,"FL"),1,0) -> 0 | AV24: =IF(EXACT(Asistencia!K25,"FL"),1,0) -> 0 | AW24: =IF(EXACT(Asistencia!L25,"FL"),1,0) -> 0 | AX24: =SUM(AQ24:AW24) -> 0 | AY24: =IF(EXACT(Asistencia!F25,"DL"),1,0) -> 0 | AZ24: =IF(EXACT(Asistencia!G25,"DL"),1,0) -> 0 | BA24: =IF(EXACT(Asistencia!H25,"DL"),1,0) -> 0 | BB24: =IF(EXACT(Asistencia!I25,"DL"),1,0) -> 0 | BC24: =IF(EXACT(Asistencia!J25,"DL"),1,0) -> 0 | BD24: =IF(EXACT(Asistencia!K25,"DL"),1,0) -> 0 | BE24: =IF(EXACT(Asistencia!L25,"DL"),1,0) -> 0 | BF24: =SUM(AY24:BE24) -> 0 | BG24: =IF(ISNUMBER(Asistencia!M25),Asistencia!M25,0) -> 0 | BH24: =IF(ISNUMBER(Asistencia!N25),Asistencia!N25,0) -> 0 | BI24: =IF(ISNUMBER(Asistencia!O25),Asistencia!O25,0) -> 0 | BJ24: =IF(ISNUMBER(Asistencia!P25),Asistencia!P25,0) -> 0 | BK24: =IF(Asistencia!F25="","",Asistencia!F25) | BL24: =IF(Asistencia!G25="","",Asistencia!G25) | BM24: =IF(Asistencia!H25="","",Asistencia!H25) | BN24: =IF(Asistencia!I25="","",Asistencia!I25) | BO24: =IF(Asistencia!J25="","",Asistencia!J25) | BP24: =IF(Asistencia!K25="","",Asistencia!K25) | BQ24: =IF(Asistencia!L25="","",Asistencia!L25)
A25: =IF(Y25="","",INDEX($AB$5:$AB$323,Y25)) | B25: =IF(Y25="","",INDEX($AD$5:$AD$323,Y25)) | E25: =IF($A25="","",_xlfn.TEXTJOIN(" / ",TRUE(),IF(SUMIFS($AP$5:$AP$323,$AA$5:$AA$323,$Z25,$AF$5:$AF$323,"ARMIDA")>0,IFERROR("ARMIDA-"&INDEX($AE$5:$AE$323,MATCH($Z25&"ARMIDA",$AA$5:$AA$323&$AF$5:$AF$323,0)),"ARMIDA"),""),IF(SUMIFS($AP$5:$AP$323,$AA$5:$AA$323,$Z25,$AF$5:$AF$323,"AURIGA")>0,IFERROR("AURIGA-"&INDEX($AE$5:$AE$323,MATCH($Z25&"AURIGA",$AA$5:$AA$323&$AF$5:$AF$323,0)),"AURIGA"),""),IF(SUMIFS($AP$5:$AP$323,$AA$5:$AA$323,$Z25,$AF$5:$AF$323,"AURORA")>0,IFERROR("AURORA-"&INDEX($AE$5:$AE$323,MATCH($Z25&"AURORA",$AA$5:$AA$323&$AF$5:$AF$323,0)),"AURORA"),""),IF(SUMIFS($AP$5:$AP$323,$AA$5:$AA$323,$Z25,$AF$5:$AF$323,"CITICA")>0,IFERROR("CITICA-"&INDEX($AE$5:$AE$323,MATCH($Z25&"CITICA",$AA$5:$AA$323&$AF$5:$AF$323,0)),"CITICA"),""),IF(SUMIFS($AP$5:$AP$323,$AA$5:$AA$323,$Z25,$AF$5:$AF$323,"GM")>0,IFERROR("GM-"&INDEX($AE$5:$AE$323,MATCH($Z25&"GM",$AA$5:$AA$323&$AF$5:$AF$323,0)),"GM"),""),IF(SUMIFS($AP$5:$AP$323,$AA$5:$AA$323,$Z25,$AF$5:$AF$323,"TORRE BALZAK")>0,IFERROR("TORRE BALZAK-"&INDEX($AE$5:$AE$323,MATCH($Z25&"TORRE BALZAK",$AA$5:$AA$323&$AF$5:$AF$323,0)),"TORRE BALZAK"),""),IF(SUMIFS($AP$5:$AP$323,$AA$5:$AA$323,$Z25,$AF$5:$AF$323,"TORRE OLMA")>0,IFERROR("TORRE OLMA-"&INDEX($AE$5:$AE$323,MATCH($Z25&"TORRE OLMA",$AA$5:$AA$323&$AF$5:$AF$323,0)),"TORRE OLMA"),""),IF(SUMIFS($AP$5:$AP$323,$AA$5:$AA$323,$Z25,$AF$5:$AF$323,"OTROS")>0,IFERROR("OTROS-"&INDEX($AE$5:$AE$323,MATCH($Z25&"OTROS",$AA$5:$AA$323&$AF$5:$AF$323,0)),"OTROS"),""))) | F25: =IF($A25="","",IFERROR(INDEX($BK$5:$BK$323,MATCH($Z25,$AA$5:$AA$323,0)),"-")) | G25: =IF($A25="","",IFERROR(INDEX($BL$5:$BL$323,MATCH($Z25,$AA$5:$AA$323,0)),"-")) | H25: =IF($A25="","",IFERROR(INDEX($BM$5:$BM$323,MATCH($Z25,$AA$5:$AA$323,0)),"-")) | I25: =IF($A25="","",IFERROR(INDEX($BN$5:$BN$323,MATCH($Z25,$AA$5:$AA$323,0)),"-")) | J25: =IF($A25="","",IFERROR(INDEX($BO$5:$BO$323,MATCH($Z25,$AA$5:$AA$323,0)),"-")) | K25: =IF($A25="","",IFERROR(INDEX($BP$5:$BP$323,MATCH($Z25,$AA$5:$AA$323,0)),"-")) | L25: =IF($A25="","",IFERROR(INDEX($BQ$5:$BQ$323,MATCH($Z25,$AA$5:$AA$323,0)),"-")) | M25: =IF($A25="","",(--(SUMIF($AA$5:$AA$323,$Z25,$AI$5:$AI$323)>0))+(--(SUMIF($AA$5:$AA$323,$Z25,$AJ$5:$AJ$323)>0))+(--(SUMIF($AA$5:$AA$323,$Z25,$AK$5:$AK$323)>0))+(--(SUMIF($AA$5:$AA$323,$Z25,$AL$5:$AL$323)>0))+(--(SUMIF($AA$5:$AA$323,$Z25,$AM$5:$AM$323)>0))+(--(SUMIF($AA$5:$AA$323,$Z25,$AN$5:$AN$323)>0))+(--(SUMIF($AA$5:$AA$323,$Z25,$AO$5:$AO$323)>0))) | N25: =IF($A25="","",MAX(0,M25-6)) | O25: =IF($A25="","",SUMIF($AA$5:$AA$323,$Z25,$AP$5:$AP$323)-M25) | P25: =IF($A25="","",SUMIF($AA$5:$AA$323,$Z25,$BG$5:$BG$323)) | Q25: =IF($A25="","",SUMIF($AA$5:$AA$323,$Z25,$BH$5:$BH$323)) | R25: =IF($A25="","",SUMIF($AA$5:$AA$323,$Z25,$BI$5:$BI$323)) | U25: =IF($A25="","",SUMIF($AA$5:$AA$323,$Z25,$BJ$5:$BJ$323)) | W25: =IF($A25="","",_xlfn.TEXTJOIN(" | ",TRUE(),IF(N25>0,"+ de 6 días: revisar adicionales",""),IF(O25>0,"Doble evento mismo día: revisar turno/pago",""),IF(SUMIF($AA$5:$AA$323,$Z25,$AX$5:$AX$323)>((--(SUMIF($AA$5:$AA$323,$Z25,$AQ$5:$AQ$323)>0))+(--(SUMIF($AA$5:$AA$323,$Z25,$AR$5:$AR$323)>0))+(--(SUMIF($AA$5:$AA$323,$Z25,$AS$5:$AS$323)>0))+(--(SUMIF($AA$5:$AA$323,$Z25,$AT$5:$AT$323)>0))+(--(SUMIF($AA$5:$AA$323,$Z25,$AU$5:$AU$323)>0))+(--(SUMIF($AA$5:$AA$323,$Z25,$AV$5:$AV$323)>0))+(--(SUMIF($AA$5:$AA$323,$Z25,$AW$5:$AW$323)>0))),"FL múltiple mismo día: revisar pago festivo",""),IF(SUMIF($AA$5:$AA$323,$Z25,$BF$5:$BF$323)>((--(SUMIF($AA$5:$AA$323,$Z25,$AY$5:$AY$323)>0))+(--(SUMIF($AA$5:$AA$323,$Z25,$AZ$5:$AZ$323)>0))+(--(SUMIF($AA$5:$AA$323,$Z25,$BA$5:$BA$323)>0))+(--(SUMIF($AA$5:$AA$323,$Z25,$BB$5:$BB$323)>0))+(--(SUMIF($AA$5:$AA$323,$Z25,$BC$5:$BC$323)>0))+(--(SUMIF($AA$5:$AA$323,$Z25,$BD$5:$BD$323)>0))+(--(SUMIF($AA$5:$AA$323,$Z25,$BE$5:$BE$323)>0))),"DL múltiple mismo día: revisar pago descanso",""))) | Y25: =IFERROR(MATCH(21,$AH$5:$AH$323,0),"") | Z25: =IF(Y25="","",INDEX($AA$5:$AA$323,Y25)) | AA25: =IF(AC25="","","M:"&AC25) | AB25: =IF(Asistencia!A26="","",Asistencia!A26) | AC25: =IF(Asistencia!A26="","",SUBSTITUTE(SUBSTITUTE(SUBSTITUTE(SUBSTITUTE(SUBSTITUTE(SUBSTITUTE(SUBSTITUTE(UPPER(TRIM(Asistencia!A26)),"Á","A"),"É","E"),"Í","I"),"Ó","O"),"Ú","U"),"Ñ","N")," "," ")) | AD25: =IF(Asistencia!E26="","",Asistencia!E26) | AE25: =IF(Asistencia!D26="","",UPPER(TRIM(Asistencia!D26))) | AF25: ARMIDA | AG25: =IF(AND(AA25<>"",COUNTIF($AA$5:AA25,AA25)=1),1,0) -> 0 | AH25: =IF(AG25=1,SUM($AG$5:AG25),"") | AI25: =IF(OR(EXACT(Asistencia!F26,"A"),EXACT(Asistencia!F26,"R"),EXACT(Asistencia!F26,"DL"),EXACT(Asistencia!F26,"FL"),EXACT(Asistencia!F26,"FE"),EXACT(Asistencia!F26,"PCS"),EXACT(Asistencia!F26,"V")),1,0) -> 0 | AJ25: =IF(OR(EXACT(Asistencia!G26,"A"),EXACT(Asistencia!G26,"R"),EXACT(Asistencia!G26,"DL"),EXACT(Asistencia!G26,"FL"),EXACT(Asistencia!G26,"FE"),EXACT(Asistencia!G26,"PCS"),EXACT(Asistencia!G26,"V")),1,0) -> 0 | AK25: =IF(OR(EXACT(Asistencia!H26,"A"),EXACT(Asistencia!H26,"R"),EXACT(Asistencia!H26,"DL"),EXACT(Asistencia!H26,"FL"),EXACT(Asistencia!H26,"FE"),EXACT(Asistencia!H26,"PCS"),EXACT(Asistencia!H26,"V")),1,0) -> 0 | AL25: =IF(OR(EXACT(Asistencia!I26,"A"),EXACT(Asistencia!I26,"R"),EXACT(Asistencia!I26,"DL"),EXACT(Asistencia!I26,"FL"),EXACT(Asistencia!I26,"FE"),EXACT(Asistencia!I26,"PCS"),EXACT(Asistencia!I26,"V")),1,0) -> 0 | AM25: =IF(OR(EXACT(Asistencia!J26,"A"),EXACT(Asistencia!J26,"R"),EXACT(Asistencia!J26,"DL"),EXACT(Asistencia!J26,"FL"),EXACT(Asistencia!J26,"FE"),EXACT(Asistencia!J26,"PCS"),EXACT(Asistencia!J26,"V")),1,0) -> 0 | AN25: =IF(OR(EXACT(Asistencia!K26,"A"),EXACT(Asistencia!K26,"R"),EXACT(Asistencia!K26,"DL"),EXACT(Asistencia!K26,"FL"),EXACT(Asistencia!K26,"FE"),EXACT(Asistencia!K26,"PCS"),EXACT(Asistencia!K26,"V")),1,0) -> 0 | AO25: =IF(OR(EXACT(Asistencia!L26,"A"),EXACT(Asistencia!L26,"R"),EXACT(Asistencia!L26,"DL"),EXACT(Asistencia!L26,"FL"),EXACT(Asistencia!L26,"FE"),EXACT(Asistencia!L26,"PCS"),EXACT(Asistencia!L26,"V")),1,0) -> 0 | AP25: =SUM(AI25:AO25) -> 0 | AQ25: =IF(EXACT(Asistencia!F26,"FL"),1,0) -> 0 | AR25: =IF(EXACT(Asistencia!G26,"FL"),1,0) -> 0 | AS25: =IF(EXACT(Asistencia!H26,"FL"),1,0) -> 0 | AT25: =IF(EXACT(Asistencia!I26,"FL"),1,0) -> 0 | AU25: =IF(EXACT(Asistencia!J26,"FL"),1,0) -> 0 | AV25: =IF(EXACT(Asistencia!K26,"FL"),1,0) -> 0 | AW25: =IF(EXACT(Asistencia!L26,"FL"),1,0) -> 0 | AX25: =SUM(AQ25:AW25) -> 0 | AY25: =IF(EXACT(Asistencia!F26,"DL"),1,0) -> 0 | AZ25: =IF(EXACT(Asistencia!G26,"DL"),1,0) -> 0 | BA25: =IF(EXACT(Asistencia!H26,"DL"),1,0) -> 0 | BB25: =IF(EXACT(Asistencia!I26,"DL"),1,0) -> 0 | BC25: =IF(EXACT(Asistencia!J26,"DL"),1,0) -> 0 | BD25: =IF(EXACT(Asistencia!K26,"DL"),1,0) -> 0 | BE25: =IF(EXACT(Asistencia!L26,"DL"),1,0) -> 0 | BF25: =SUM(AY25:BE25) -> 0 | BG25: =IF(ISNUMBER(Asistencia!M26),Asistencia!M26,0) -> 0 | BH25: =IF(ISNUMBER(Asistencia!N26),Asistencia!N26,0) -> 0 | BI25: =IF(ISNUMBER(Asistencia!O26),Asistencia!O26,0) -> 0 | BJ25: =IF(ISNUMBER(Asistencia!P26),Asistencia!P26,0) -> 0 | BK25: =IF(Asistencia!F26="","",Asistencia!F26) | BL25: =IF(Asistencia!G26="","",Asistencia!G26) | BM25: =IF(Asistencia!H26="","",Asistencia!H26) | BN25: =IF(Asistencia!I26="","",Asistencia!I26) | BO25: =IF(Asistencia!J26="","",Asistencia!J26) | BP25: =IF(Asistencia!K26="","",Asistencia!K26) | BQ25: =IF(Asistencia!L26="","",Asistencia!L26)
A26: =IF(Y26="","",INDEX($AB$5:$AB$323,Y26)) | B26: =IF(Y26="","",INDEX($AD$5:$AD$323,Y26)) | E26: =IF($A26="","",_xlfn.TEXTJOIN(" / ",TRUE(),IF(SUMIFS($AP$5:$AP$323,$AA$5:$AA$323,$Z26,$AF$5:$AF$323,"ARMIDA")>0,IFERROR("ARMIDA-"&INDEX($AE$5:$AE$323,MATCH($Z26&"ARMIDA",$AA$5:$AA$323&$AF$5:$AF$323,0)),"ARMIDA"),""),IF(SUMIFS($AP$5:$AP$323,$AA$5:$AA$323,$Z26,$AF$5:$AF$323,"AURIGA")>0,IFERROR("AURIGA-"&INDEX($AE$5:$AE$323,MATCH($Z26&"AURIGA",$AA$5:$AA$323&$AF$5:$AF$323,0)),"AURIGA"),""),IF(SUMIFS($AP$5:$AP$323,$AA$5:$AA$323,$Z26,$AF$5:$AF$323,"AURORA")>0,IFERROR("AURORA-"&INDEX($AE$5:$AE$323,MATCH($Z26&"AURORA",$AA$5:$AA$323&$AF$5:$AF$323,0)),"AURORA"),""),IF(SUMIFS($AP$5:$AP$323,$AA$5:$AA$323,$Z26,$AF$5:$AF$323,"CITICA")>0,IFERROR("CITICA-"&INDEX($AE$5:$AE$323,MATCH($Z26&"CITICA",$AA$5:$AA$323&$AF$5:$AF$323,0)),"CITICA"),""),IF(SUMIFS($AP$5:$AP$323,$AA$5:$AA$323,$Z26,$AF$5:$AF$323,"GM")>0,IFERROR("GM-"&INDEX($AE$5:$AE$323,MATCH($Z26&"GM",$AA$5:$AA$323&$AF$5:$AF$323,0)),"GM"),""),IF(SUMIFS($AP$5:$AP$323,$AA$5:$AA$323,$Z26,$AF$5:$AF$323,"TORRE BALZAK")>0,IFERROR("TORRE BALZAK-"&INDEX($AE$5:$AE$323,MATCH($Z26&"TORRE BALZAK",$AA$5:$AA$323&$AF$5:$AF$323,0)),"TORRE BALZAK"),""),IF(SUMIFS($AP$5:$AP$323,$AA$5:$AA$323,$Z26,$AF$5:$AF$323,"TORRE OLMA")>0,IFERROR("TORRE OLMA-"&INDEX($AE$5:$AE$323,MATCH($Z26&"TORRE OLMA",$AA$5:$AA$323&$AF$5:$AF$323,0)),"TORRE OLMA"),""),IF(SUMIFS($AP$5:$AP$323,$AA$5:$AA$323,$Z26,$AF$5:$AF$323,"OTROS")>0,IFERROR("OTROS-"&INDEX($AE$5:$AE$323,MATCH($Z26&"OTROS",$AA$5:$AA$323&$AF$5:$AF$323,0)),"OTROS"),""))) | F26: =IF($A26="","",IFERROR(INDEX($BK$5:$BK$323,MATCH($Z26,$AA$5:$AA$323,0)),"-")) | G26: =IF($A26="","",IFERROR(INDEX($BL$5:$BL$323,MATCH($Z26,$AA$5:$AA$323,0)),"-")) | H26: =IF($A26="","",IFERROR(INDEX($BM$5:$BM$323,MATCH($Z26,$AA$5:$AA$323,0)),"-")) | I26: =IF($A26="","",IFERROR(INDEX($BN$5:$BN$323,MATCH($Z26,$AA$5:$AA$323,0)),"-")) | J26: =IF($A26="","",IFERROR(INDEX($BO$5:$BO$323,MATCH($Z26,$AA$5:$AA$323,0)),"-")) | K26: =IF($A26="","",IFERROR(INDEX($BP$5:$BP$323,MATCH($Z26,$AA$5:$AA$323,0)),"-")) | L26: =IF($A26="","",IFERROR(INDEX($BQ$5:$BQ$323,MATCH($Z26,$AA$5:$AA$323,0)),"-")) | M26: =IF($A26="","",(--(SUMIF($AA$5:$AA$323,$Z26,$AI$5:$AI$323)>0))+(--(SUMIF($AA$5:$AA$323,$Z26,$AJ$5:$AJ$323)>0))+(--(SUMIF($AA$5:$AA$323,$Z26,$AK$5:$AK$323)>0))+(--(SUMIF($AA$5:$AA$323,$Z26,$AL$5:$AL$323)>0))+(--(SUMIF($AA$5:$AA$323,$Z26,$AM$5:$AM$323)>0))+(--(SUMIF($AA$5:$AA$323,$Z26,$AN$5:$AN$323)>0))+(--(SUMIF($AA$5:$AA$323,$Z26,$AO$5:$AO$323)>0))) | N26: =IF($A26="","",MAX(0,M26-6)) | O26: =IF($A26="","",SUMIF($AA$5:$AA$323,$Z26,$AP$5:$AP$323)-M26) | P26: =IF($A26="","",SUMIF($AA$5:$AA$323,$Z26,$BG$5:$BG$323)) | Q26: =IF($A26="","",SUMIF($AA$5:$AA$323,$Z26,$BH$5:$BH$323)) | R26: =IF($A26="","",SUMIF($AA$5:$AA$323,$Z26,$BI$5:$BI$323)) | U26: =IF($A26="","",SUMIF($AA$5:$AA$323,$Z26,$BJ$5:$BJ$323)) | W26: =IF($A26="","",_xlfn.TEXTJOIN(" | ",TRUE(),IF(N26>0,"+ de 6 días: revisar adicionales",""),IF(O26>0,"Doble evento mismo día: revisar turno/pago",""),IF(SUMIF($AA$5:$AA$323,$Z26,$AX$5:$AX$323)>((--(SUMIF($AA$5:$AA$323,$Z26,$AQ$5:$AQ$323)>0))+(--(SUMIF($AA$5:$AA$323,$Z26,$AR$5:$AR$323)>0))+(--(SUMIF($AA$5:$AA$323,$Z26,$AS$5:$AS$323)>0))+(--(SUMIF($AA$5:$AA$323,$Z26,$AT$5:$AT$323)>0))+(--(SUMIF($AA$5:$AA$323,$Z26,$AU$5:$AU$323)>0))+(--(SUMIF($AA$5:$AA$323,$Z26,$AV$5:$AV$323)>0))+(--(SUMIF($AA$5:$AA$323,$Z26,$AW$5:$AW$323)>0))),"FL múltiple mismo día: revisar pago festivo",""),IF(SUMIF($AA$5:$AA$323,$Z26,$BF$5:$BF$323)>((--(SUMIF($AA$5:$AA$323,$Z26,$AY$5:$AY$323)>0))+(--(SUMIF($AA$5:$AA$323,$Z26,$AZ$5:$AZ$323)>0))+(--(SUMIF($AA$5:$AA$323,$Z26,$BA$5:$BA$323)>0))+(--(SUMIF($AA$5:$AA$323,$Z26,$BB$5:$BB$323)>0))+(--(SUMIF($AA$5:$AA$323,$Z26,$BC$5:$BC$323)>0))+(--(SUMIF($AA$5:$AA$323,$Z26,$BD$5:$BD$323)>0))+(--(SUMIF($AA$5:$AA$323,$Z26,$BE$5:$BE$323)>0))),"DL múltiple mismo día: revisar pago descanso",""))) | Y26: =IFERROR(MATCH(22,$AH$5:$AH$323,0),"") | Z26: =IF(Y26="","",INDEX($AA$5:$AA$323,Y26)) | AA26: =IF(AC26="","","M:"&AC26) | AB26: =IF(Asistencia!A27="","",Asistencia!A27) | AC26: =IF(Asistencia!A27="","",SUBSTITUTE(SUBSTITUTE(SUBSTITUTE(SUBSTITUTE(SUBSTITUTE(SUBSTITUTE(SUBSTITUTE(UPPER(TRIM(Asistencia!A27)),"Á","A"),"É","E"),"Í","I"),"Ó","O"),"Ú","U"),"Ñ","N")," "," ")) | AD26: =IF(Asistencia!E27="","",Asistencia!E27) | AE26: =IF(Asistencia!D27="","",UPPER(TRIM(Asistencia!D27))) | AF26: ARMIDA | AG26: =IF(AND(AA26<>"",COUNTIF($AA$5:AA26,AA26)=1),1,0) -> 0 | AH26: =IF(AG26=1,SUM($AG$5:AG26),"") | AI26: =IF(OR(EXACT(Asistencia!F27,"A"),EXACT(Asistencia!F27,"R"),EXACT(Asistencia!F27,"DL"),EXACT(Asistencia!F27,"FL"),EXACT(Asistencia!F27,"FE"),EXACT(Asistencia!F27,"PCS"),EXACT(Asistencia!F27,"V")),1,0) -> 0 | AJ26: =IF(OR(EXACT(Asistencia!G27,"A"),EXACT(Asistencia!G27,"R"),EXACT(Asistencia!G27,"DL"),EXACT(Asistencia!G27,"FL"),EXACT(Asistencia!G27,"FE"),EXACT(Asistencia!G27,"PCS"),EXACT(Asistencia!G27,"V")),1,0) -> 0 | AK26: =IF(OR(EXACT(Asistencia!H27,"A"),EXACT(Asistencia!H27,"R"),EXACT(Asistencia!H27,"DL"),EXACT(Asistencia!H27,"FL"),EXACT(Asistencia!H27,"FE"),EXACT(Asistencia!H27,"PCS"),EXACT(Asistencia!H27,"V")),1,0) -> 0 | AL26: =IF(OR(EXACT(Asistencia!I27,"A"),EXACT(Asistencia!I27,"R"),EXACT(Asistencia!I27,"DL"),EXACT(Asistencia!I27,"FL"),EXACT(Asistencia!I27,"FE"),EXACT(Asistencia!I27,"PCS"),EXACT(Asistencia!I27,"V")),1,0) -> 0 | AM26: =IF(OR(EXACT(Asistencia!J27,"A"),EXACT(Asistencia!J27,"R"),EXACT(Asistencia!J27,"DL"),EXACT(Asistencia!J27,"FL"),EXACT(Asistencia!J27,"FE"),EXACT(Asistencia!J27,"PCS"),EXACT(Asistencia!J27,"V")),1,0) -> 0 | AN26: =IF(OR(EXACT(Asistencia!K27,"A"),EXACT(Asistencia!K27,"R"),EXACT(Asistencia!K27,"DL"),EXACT(Asistencia!K27,"FL"),EXACT(Asistencia!K27,"FE"),EXACT(Asistencia!K27,"PCS"),EXACT(Asistencia!K27,"V")),1,0) -> 0 | AO26: =IF(OR(EXACT(Asistencia!L27,"A"),EXACT(Asistencia!L27,"R"),EXACT(Asistencia!L27,"DL"),EXACT(Asistencia!L27,"FL"),EXACT(Asistencia!L27,"FE"),EXACT(Asistencia!L27,"PCS"),EXACT(Asistencia!L27,"V")),1,0) -> 0 | AP26: =SUM(AI26:AO26) -> 0 | AQ26: =IF(EXACT(Asistencia!F27,"FL"),1,0) -> 0 | AR26: =IF(EXACT(Asistencia!G27,"FL"),1,0) -> 0 | AS26: =IF(EXACT(Asistencia!H27,"FL"),1,0) -> 0 | AT26: =IF(EXACT(Asistencia!I27,"FL"),1,0) -> 0 | AU26: =IF(EXACT(Asistencia!J27,"FL"),1,0) -> 0 | AV26: =IF(EXACT(Asistencia!K27,"FL"),1,0) -> 0 | AW26: =IF(EXACT(Asistencia!L27,"FL"),1,0) -> 0 | AX26: =SUM(AQ26:AW26) -> 0 | AY26: =IF(EXACT(Asistencia!F27,"DL"),1,0) -> 0 | AZ26: =IF(EXACT(Asistencia!G27,"DL"),1,0) -> 0 | BA26: =IF(EXACT(Asistencia!H27,"DL"),1,0) -> 0 | BB26: =IF(EXACT(Asistencia!I27,"DL"),1,0) -> 0 | BC26: =IF(EXACT(Asistencia!J27,"DL"),1,0) -> 0 | BD26: =IF(EXACT(Asistencia!K27,"DL"),1,0) -> 0 | BE26: =IF(EXACT(Asistencia!L27,"DL"),1,0) -> 0 | BF26: =SUM(AY26:BE26) -> 0 | BG26: =IF(ISNUMBER(Asistencia!M27),Asistencia!M27,0) -> 0 | BH26: =IF(ISNUMBER(Asistencia!N27),Asistencia!N27,0) -> 0 | BI26: =IF(ISNUMBER(Asistencia!O27),Asistencia!O27,0) -> 0 | BJ26: =IF(ISNUMBER(Asistencia!P27),Asistencia!P27,0) -> 0 | BK26: =IF(Asistencia!F27="","",Asistencia!F27) | BL26: =IF(Asistencia!G27="","",Asistencia!G27) | BM26: =IF(Asistencia!H27="","",Asistencia!H27) | BN26: =IF(Asistencia!I27="","",Asistencia!I27) | BO26: =IF(Asistencia!J27="","",Asistencia!J27) | BP26: =IF(Asistencia!K27="","",Asistencia!K27) | BQ26: =IF(Asistencia!L27="","",Asistencia!L27)
A27: =IF(Y27="","",INDEX($AB$5:$AB$323,Y27)) | B27: =IF(Y27="","",INDEX($AD$5:$AD$323,Y27)) | E27: =IF($A27="","",_xlfn.TEXTJOIN(" / ",TRUE(),IF(SUMIFS($AP$5:$AP$323,$AA$5:$AA$323,$Z27,$AF$5:$AF$323,"ARMIDA")>0,IFERROR("ARMIDA-"&INDEX($AE$5:$AE$323,MATCH($Z27&"ARMIDA",$AA$5:$AA$323&$AF$5:$AF$323,0)),"ARMIDA"),""),IF(SUMIFS($AP$5:$AP$323,$AA$5:$AA$323,$Z27,$AF$5:$AF$323,"AURIGA")>0,IFERROR("AURIGA-"&INDEX($AE$5:$AE$323,MATCH($Z27&"AURIGA",$AA$5:$AA$323&$AF$5:$AF$323,0)),"AURIGA"),""),IF(SUMIFS($AP$5:$AP$323,$AA$5:$AA$323,$Z27,$AF$5:$AF$323,"AURORA")>0,IFERROR("AURORA-"&INDEX($AE$5:$AE$323,MATCH($Z27&"AURORA",$AA$5:$AA$323&$AF$5:$AF$323,0)),"AURORA"),""),IF(SUMIFS($AP$5:$AP$323,$AA$5:$AA$323,$Z27,$AF$5:$AF$323,"CITICA")>0,IFERROR("CITICA-"&INDEX($AE$5:$AE$323,MATCH($Z27&"CITICA",$AA$5:$AA$323&$AF$5:$AF$323,0)),"CITICA"),""),IF(SUMIFS($AP$5:$AP$323,$AA$5:$AA$323,$Z27,$AF$5:$AF$323,"GM")>0,IFERROR("GM-"&INDEX($AE$5:$AE$323,MATCH($Z27&"GM",$AA$5:$AA$323&$AF$5:$AF$323,0)),"GM"),""),IF(SUMIFS($AP$5:$AP$323,$AA$5:$AA$323,$Z27,$AF$5:$AF$323,"TORRE BALZAK")>0,IFERROR("TORRE BALZAK-"&INDEX($AE$5:$AE$323,MATCH($Z27&"TORRE BALZAK",$AA$5:$AA$323&$AF$5:$AF$323,0)),"TORRE BALZAK"),""),IF(SUMIFS($AP$5:$AP$323,$AA$5:$AA$323,$Z27,$AF$5:$AF$323,"TORRE OLMA")>0,IFERROR("TORRE OLMA-"&INDEX($AE$5:$AE$323,MATCH($Z27&"TORRE OLMA",$AA$5:$AA$323&$AF$5:$AF$323,0)),"TORRE OLMA"),""),IF(SUMIFS($AP$5:$AP$323,$AA$5:$AA$323,$Z27,$AF$5:$AF$323,"OTROS")>0,IFERROR("OTROS-"&INDEX($AE$5:$AE$323,MATCH($Z27&"OTROS",$AA$5:$AA$323&$AF$5:$AF$323,0)),"OTROS"),""))) | F27: =IF($A27="","",IFERROR(INDEX($BK$5:$BK$323,MATCH($Z27,$AA$5:$AA$323,0)),"-")) | G27: =IF($A27="","",IFERROR(INDEX($BL$5:$BL$323,MATCH($Z27,$AA$5:$AA$323,0)),"-")) | H27: =IF($A27="","",IFERROR(INDEX($BM$5:$BM$323,MATCH($Z27,$AA$5:$AA$323,0)),"-")) | I27: =IF($A27="","",IFERROR(INDEX($BN$5:$BN$323,MATCH($Z27,$AA$5:$AA$323,0)),"-")) | J27: =IF($A27="","",IFERROR(INDEX($BO$5:$BO$323,MATCH($Z27,$AA$5:$AA$323,0)),"-")) | K27: =IF($A27="","",IFERROR(INDEX($BP$5:$BP$323,MATCH($Z27,$AA$5:$AA$323,0)),"-")) | L27: =IF($A27="","",IFERROR(INDEX($BQ$5:$BQ$323,MATCH($Z27,$AA$5:$AA$323,0)),"-")) | M27: =IF($A27="","",(--(SUMIF($AA$5:$AA$323,$Z27,$AI$5:$AI$323)>0))+(--(SUMIF($AA$5:$AA$323,$Z27,$AJ$5:$AJ$323)>0))+(--(SUMIF($AA$5:$AA$323,$Z27,$AK$5:$AK$323)>0))+(--(SUMIF($AA$5:$AA$323,$Z27,$AL$5:$AL$323)>0))+(--(SUMIF($AA$5:$AA$323,$Z27,$AM$5:$AM$323)>0))+(--(SUMIF($AA$5:$AA$323,$Z27,$AN$5:$AN$323)>0))+(--(SUMIF($AA$5:$AA$323,$Z27,$AO$5:$AO$323)>0))) | N27: =IF($A27="","",MAX(0,M27-6)) | O27: =IF($A27="","",SUMIF($AA$5:$AA$323,$Z27,$AP$5:$AP$323)-M27) | P27: =IF($A27="","",SUMIF($AA$5:$AA$323,$Z27,$BG$5:$BG$323)) | Q27: =IF($A27="","",SUMIF($AA$5:$AA$323,$Z27,$BH$5:$BH$323)) | R27: =IF($A27="","",SUMIF($AA$5:$AA$323,$Z27,$BI$5:$BI$323)) | U27: =IF($A27="","",SUMIF($AA$5:$AA$323,$Z27,$BJ$5:$BJ$323)) | W27: =IF($A27="","",_xlfn.TEXTJOIN(" | ",TRUE(),IF(N27>0,"+ de 6 días: revisar adicionales",""),IF(O27>0,"Doble evento mismo día: revisar turno/pago",""),IF(SUMIF($AA$5:$AA$323,$Z27,$AX$5:$AX$323)>((--(SUMIF($AA$5:$AA$323,$Z27,$AQ$5:$AQ$323)>0))+(--(SUMIF($AA$5:$AA$323,$Z27,$AR$5:$AR$323)>0))+(--(SUMIF($AA$5:$AA$323,$Z27,$AS$5:$AS$323)>0))+(--(SUMIF($AA$5:$AA$323,$Z27,$AT$5:$AT$323)>0))+(--(SUMIF($AA$5:$AA$323,$Z27,$AU$5:$AU$323)>0))+(--(SUMIF($AA$5:$AA$323,$Z27,$AV$5:$AV$323)>0))+(--(SUMIF($AA$5:$AA$323,$Z27,$AW$5:$AW$323)>0))),"FL múltiple mismo día: revisar pago festivo",""),IF(SUMIF($AA$5:$AA$323,$Z27,$BF$5:$BF$323)>((--(SUMIF($AA$5:$AA$323,$Z27,$AY$5:$AY$323)>0))+(--(SUMIF($AA$5:$AA$323,$Z27,$AZ$5:$AZ$323)>0))+(--(SUMIF($AA$5:$AA$323,$Z27,$BA$5:$BA$323)>0))+(--(SUMIF($AA$5:$AA$323,$Z27,$BB$5:$BB$323)>0))+(--(SUMIF($AA$5:$AA$323,$Z27,$BC$5:$BC$323)>0))+(--(SUMIF($AA$5:$AA$323,$Z27,$BD$5:$BD$323)>0))+(--(SUMIF($AA$5:$AA$323,$Z27,$BE$5:$BE$323)>0))),"DL múltiple mismo día: revisar pago descanso",""))) | Y27: =IFERROR(MATCH(23,$AH$5:$AH$323,0),"") | Z27: =IF(Y27="","",INDEX($AA$5:$AA$323,Y27)) | AA27: =IF(AC27="","","M:"&AC27) | AB27: =IF(Asistencia!A28="","",Asistencia!A28) | AC27: =IF(Asistencia!A28="","",SUBSTITUTE(SUBSTITUTE(SUBSTITUTE(SUBSTITUTE(SUBSTITUTE(SUBSTITUTE(SUBSTITUTE(UPPER(TRIM(Asistencia!A28)),"Á","A"),"É","E"),"Í","I"),"Ó","O"),"Ú","U"),"Ñ","N")," "," ")) | AD27: =IF(Asistencia!E28="","",Asistencia!E28) | AE27: =IF(Asistencia!D28="","",UPPER(TRIM(Asistencia!D28))) | AF27: ARMIDA | AG27: =IF(AND(AA27<>"",COUNTIF($AA$5:AA27,AA27)=1),1,0) -> 0 | AH27: =IF(AG27=1,SUM($AG$5:AG27),"") | AI27: =IF(OR(EXACT(Asistencia!F28,"A"),EXACT(Asistencia!F28,"R"),EXACT(Asistencia!F28,"DL"),EXACT(Asistencia!F28,"FL"),EXACT(Asistencia!F28,"FE"),EXACT(Asistencia!F28,"PCS"),EXACT(Asistencia!F28,"V")),1,0) -> 0 | AJ27: =IF(OR(EXACT(Asistencia!G28,"A"),EXACT(Asistencia!G28,"R"),EXACT(Asistencia!G28,"DL"),EXACT(Asistencia!G28,"FL"),EXACT(Asistencia!G28,"FE"),EXACT(Asistencia!G28,"PCS"),EXACT(Asistencia!G28,"V")),1,0) -> 0 | AK27: =IF(OR(EXACT(Asistencia!H28,"A"),EXACT(Asistencia!H28,"R"),EXACT(Asistencia!H28,"DL"),EXACT(Asistencia!H28,"FL"),EXACT(Asistencia!H28,"FE"),EXACT(Asistencia!H28,"PCS"),EXACT(Asistencia!H28,"V")),1,0) -> 0 | AL27: =IF(OR(EXACT(Asistencia!I28,"A"),EXACT(Asistencia!I28,"R"),EXACT(Asistencia!I28,"DL"),EXACT(Asistencia!I28,"FL"),EXACT(Asistencia!I28,"FE"),EXACT(Asistencia!I28,"PCS"),EXACT(Asistencia!I28,"V")),1,0) -> 0 | AM27: =IF(OR(EXACT(Asistencia!J28,"A"),EXACT(Asistencia!J28,"R"),EXACT(Asistencia!J28,"DL"),EXACT(Asistencia!J28,"FL"),EXACT(Asistencia!J28,"FE"),EXACT(Asistencia!J28,"PCS"),EXACT(Asistencia!J28,"V")),1,0) -> 0 | AN27: =IF(OR(EXACT(Asistencia!K28,"A"),EXACT(Asistencia!K28,"R"),EXACT(Asistencia!K28,"DL"),EXACT(Asistencia!K28,"FL"),EXACT(Asistencia!K28,"FE"),EXACT(Asistencia!K28,"PCS"),EXACT(Asistencia!K28,"V")),1,0) -> 0 | AO27: =IF(OR(EXACT(Asistencia!L28,"A"),EXACT(Asistencia!L28,"R"),EXACT(Asistencia!L28,"DL"),EXACT(Asistencia!L28,"FL"),EXACT(Asistencia!L28,"FE"),EXACT(Asistencia!L28,"PCS"),EXACT(Asistencia!L28,"V")),1,0) -> 0 | AP27: =SUM(AI27:AO27) -> 0 | AQ27: =IF(EXACT(Asistencia!F28,"FL"),1,0) -> 0 | AR27: =IF(EXACT(Asistencia!G28,"FL"),1,0) -> 0 | AS27: =IF(EXACT(Asistencia!H28,"FL"),1,0) -> 0 | AT27: =IF(EXACT(Asistencia!I28,"FL"),1,0) -> 0 | AU27: =IF(EXACT(Asistencia!J28,"FL"),1,0) -> 0 | AV27: =IF(EXACT(Asistencia!K28,"FL"),1,0) -> 0 | AW27: =IF(EXACT(Asistencia!L28,"FL"),1,0) -> 0 | AX27: =SUM(AQ27:AW27) -> 0 | AY27: =IF(EXACT(Asistencia!F28,"DL"),1,0) -> 0 | AZ27: =IF(EXACT(Asistencia!G28,"DL"),1,0) -> 0 | BA27: =IF(EXACT(Asistencia!H28,"DL"),1,0) -> 0 | BB27: =IF(EXACT(Asistencia!I28,"DL"),1,0) -> 0 | BC27: =IF(EXACT(Asistencia!J28,"DL"),1,0) -> 0 | BD27: =IF(EXACT(Asistencia!K28,"DL"),1,0) -> 0 | BE27: =IF(EXACT(Asistencia!L28,"DL"),1,0) -> 0 | BF27: =SUM(AY27:BE27) -> 0 | BG27: =IF(ISNUMBER(Asistencia!M28),Asistencia!M28,0) -> 0 | BH27: =IF(ISNUMBER(Asistencia!N28),Asistencia!N28,0) -> 0 | BI27: =IF(ISNUMBER(Asistencia!O28),Asistencia!O28,0) -> 0 | BJ27: =IF(ISNUMBER(Asistencia!P28),Asistencia!P28,0) -> 0 | BK27: =IF(Asistencia!F28="","",Asistencia!F28) | BL27: =IF(Asistencia!G28="","",Asistencia!G28) | BM27: =IF(Asistencia!H28="","",Asistencia!H28) | BN27: =IF(Asistencia!I28="","",Asistencia!I28) | BO27: =IF(Asistencia!J28="","",Asistencia!J28) | BP27: =IF(Asistencia!K28="","",Asistencia!K28) | BQ27: =IF(Asistencia!L28="","",Asistencia!L28)
A28: =IF(Y28="","",INDEX($AB$5:$AB$323,Y28)) | B28: =IF(Y28="","",INDEX($AD$5:$AD$323,Y28)) | E28: =IF($A28="","",_xlfn.TEXTJOIN(" / ",TRUE(),IF(SUMIFS($AP$5:$AP$323,$AA$5:$AA$323,$Z28,$AF$5:$AF$323,"ARMIDA")>0,IFERROR("ARMIDA-"&INDEX($AE$5:$AE$323,MATCH($Z28&"ARMIDA",$AA$5:$AA$323&$AF$5:$AF$323,0)),"ARMIDA"),""),IF(SUMIFS($AP$5:$AP$323,$AA$5:$AA$323,$Z28,$AF$5:$AF$323,"AURIGA")>0,IFERROR("AURIGA-"&INDEX($AE$5:$AE$323,MATCH($Z28&"AURIGA",$AA$5:$AA$323&$AF$5:$AF$323,0)),"AURIGA"),""),IF(SUMIFS($AP$5:$AP$323,$AA$5:$AA$323,$Z28,$AF$5:$AF$323,"AURORA")>0,IFERROR("AURORA-"&INDEX($AE$5:$AE$323,MATCH($Z28&"AURORA",$AA$5:$AA$323&$AF$5:$AF$323,0)),"AURORA"),""),IF(SUMIFS($AP$5:$AP$323,$AA$5:$AA$323,$Z28,$AF$5:$AF$323,"CITICA")>0,IFERROR("CITICA-"&INDEX($AE$5:$AE$323,MATCH($Z28&"CITICA",$AA$5:$AA$323&$AF$5:$AF$323,0)),"CITICA"),""),IF(SUMIFS($AP$5:$AP$323,$AA$5:$AA$323,$Z28,$AF$5:$AF$323,"GM")>0,IFERROR("GM-"&INDEX($AE$5:$AE$323,MATCH($Z28&"GM",$AA$5:$AA$323&$AF$5:$AF$323,0)),"GM"),""),IF(SUMIFS($AP$5:$AP$323,$AA$5:$AA$323,$Z28,$AF$5:$AF$323,"TORRE BALZAK")>0,IFERROR("TORRE BALZAK-"&INDEX($AE$5:$AE$323,MATCH($Z28&"TORRE BALZAK",$AA$5:$AA$323&$AF$5:$AF$323,0)),"TORRE BALZAK"),""),IF(SUMIFS($AP$5:$AP$323,$AA$5:$AA$323,$Z28,$AF$5:$AF$323,"TORRE OLMA")>0,IFERROR("TORRE OLMA-"&INDEX($AE$5:$AE$323,MATCH($Z28&"TORRE OLMA",$AA$5:$AA$323&$AF$5:$AF$323,0)),"TORRE OLMA"),""),IF(SUMIFS($AP$5:$AP$323,$AA$5:$AA$323,$Z28,$AF$5:$AF$323,"OTROS")>0,IFERROR("OTROS-"&INDEX($AE$5:$AE$323,MATCH($Z28&"OTROS",$AA$5:$AA$323&$AF$5:$AF$323,0)),"OTROS"),""))) | F28: =IF($A28="","",IFERROR(INDEX($BK$5:$BK$323,MATCH($Z28,$AA$5:$AA$323,0)),"-")) | G28: =IF($A28="","",IFERROR(INDEX($BL$5:$BL$323,MATCH($Z28,$AA$5:$AA$323,0)),"-")) | H28: =IF($A28="","",IFERROR(INDEX($BM$5:$BM$323,MATCH($Z28,$AA$5:$AA$323,0)),"-")) | I28: =IF($A28="","",IFERROR(INDEX($BN$5:$BN$323,MATCH($Z28,$AA$5:$AA$323,0)),"-")) | J28: =IF($A28="","",IFERROR(INDEX($BO$5:$BO$323,MATCH($Z28,$AA$5:$AA$323,0)),"-")) | K28: =IF($A28="","",IFERROR(INDEX($BP$5:$BP$323,MATCH($Z28,$AA$5:$AA$323,0)),"-")) | L28: =IF($A28="","",IFERROR(INDEX($BQ$5:$BQ$323,MATCH($Z28,$AA$5:$AA$323,0)),"-")) | M28: =IF($A28="","",(--(SUMIF($AA$5:$AA$323,$Z28,$AI$5:$AI$323)>0))+(--(SUMIF($AA$5:$AA$323,$Z28,$AJ$5:$AJ$323)>0))+(--(SUMIF($AA$5:$AA$323,$Z28,$AK$5:$AK$323)>0))+(--(SUMIF($AA$5:$AA$323,$Z28,$AL$5:$AL$323)>0))+(--(SUMIF($AA$5:$AA$323,$Z28,$AM$5:$AM$323)>0))+(--(SUMIF($AA$5:$AA$323,$Z28,$AN$5:$AN$323)>0))+(--(SUMIF($AA$5:$AA$323,$Z28,$AO$5:$AO$323)>0))) | N28: =IF($A28="","",MAX(0,M28-6)) | O28: =IF($A28="","",SUMIF($AA$5:$AA$323,$Z28,$AP$5:$AP$323)-M28) | P28: =IF($A28="","",SUMIF($AA$5:$AA$323,$Z28,$BG$5:$BG$323)) | Q28: =IF($A28="","",SUMIF($AA$5:$AA$323,$Z28,$BH$5:$BH$323)) | R28: =IF($A28="","",SUMIF($AA$5:$AA$323,$Z28,$BI$5:$BI$323)) | U28: =IF($A28="","",SUMIF($AA$5:$AA$323,$Z28,$BJ$5:$BJ$323)) | W28: =IF($A28="","",_xlfn.TEXTJOIN(" | ",TRUE(),IF(N28>0,"+ de 6 días: revisar adicionales",""),IF(O28>0,"Doble evento mismo día: revisar turno/pago",""),IF(SUMIF($AA$5:$AA$323,$Z28,$AX$5:$AX$323)>((--(SUMIF($AA$5:$AA$323,$Z28,$AQ$5:$AQ$323)>0))+(--(SUMIF($AA$5:$AA$323,$Z28,$AR$5:$AR$323)>0))+(--(SUMIF($AA$5:$AA$323,$Z28,$AS$5:$AS$323)>0))+(--(SUMIF($AA$5:$AA$323,$Z28,$AT$5:$AT$323)>0))+(--(SUMIF($AA$5:$AA$323,$Z28,$AU$5:$AU$323)>0))+(--(SUMIF($AA$5:$AA$323,$Z28,$AV$5:$AV$323)>0))+(--(SUMIF($AA$5:$AA$323,$Z28,$AW$5:$AW$323)>0))),"FL múltiple mismo día: revisar pago festivo",""),IF(SUMIF($AA$5:$AA$323,$Z28,$BF$5:$BF$323)>((--(SUMIF($AA$5:$AA$323,$Z28,$AY$5:$AY$323)>0))+(--(SUMIF($AA$5:$AA$323,$Z28,$AZ$5:$AZ$323)>0))+(--(SUMIF($AA$5:$AA$323,$Z28,$BA$5:$BA$323)>0))+(--(SUMIF($AA$5:$AA$323,$Z28,$BB$5:$BB$323)>0))+(--(SUMIF($AA$5:$AA$323,$Z28,$BC$5:$BC$323)>0))+(--(SUMIF($AA$5:$AA$323,$Z28,$BD$5:$BD$323)>0))+(--(SUMIF($AA$5:$AA$323,$Z28,$BE$5:$BE$323)>0))),"DL múltiple mismo día: revisar pago descanso",""))) | Y28: =IFERROR(MATCH(24,$AH$5:$AH$323,0),"") | Z28: =IF(Y28="","",INDEX($AA$5:$AA$323,Y28)) | AA28: =IF(AC28="","","M:"&AC28) | AB28: =IF(Asistencia!A29="","",Asistencia!A29) | AC28: =IF(Asistencia!A29="","",SUBSTITUTE(SUBSTITUTE(SUBSTITUTE(SUBSTITUTE(SUBSTITUTE(SUBSTITUTE(SUBSTITUTE(UPPER(TRIM(Asistencia!A29)),"Á","A"),"É","E"),"Í","I"),"Ó","O"),"Ú","U"),"Ñ","N")," "," ")) | AD28: =IF(Asistencia!E29="","",Asistencia!E29) | AE28: =IF(Asistencia!D29="","",UPPER(TRIM(Asistencia!D29))) | AF28: ARMIDA | AG28: =IF(AND(AA28<>"",COUNTIF($AA$5:AA28,AA28)=1),1,0) -> 0 | AH28: =IF(AG28=1,SUM($AG$5:AG28),"") | AI28: =IF(OR(EXACT(Asistencia!F29,"A"),EXACT(Asistencia!F29,"R"),EXACT(Asistencia!F29,"DL"),EXACT(Asistencia!F29,"FL"),EXACT(Asistencia!F29,"FE"),EXACT(Asistencia!F29,"PCS"),EXACT(Asistencia!F29,"V")),1,0) -> 0 | AJ28: =IF(OR(EXACT(Asistencia!G29,"A"),EXACT(Asistencia!G29,"R"),EXACT(Asistencia!G29,"DL"),EXACT(Asistencia!G29,"FL"),EXACT(Asistencia!G29,"FE"),EXACT(Asistencia!G29,"PCS"),EXACT(Asistencia!G29,"V")),1,0) -> 0 | AK28: =IF(OR(EXACT(Asistencia!H29,"A"),EXACT(Asistencia!H29,"R"),EXACT(Asistencia!H29,"DL"),EXACT(Asistencia!H29,"FL"),EXACT(Asistencia!H29,"FE"),EXACT(Asistencia!H29,"PCS"),EXACT(Asistencia!H29,"V")),1,0) -> 0 | AL28: =IF(OR(EXACT(Asistencia!I29,"A"),EXACT(Asistencia!I29,"R"),EXACT(Asistencia!I29,"DL"),EXACT(Asistencia!I29,"FL"),EXACT(Asistencia!I29,"FE"),EXACT(Asistencia!I29,"PCS"),EXACT(Asistencia!I29,"V")),1,0) -> 0 | AM28: =IF(OR(EXACT(Asistencia!J29,"A"),EXACT(Asistencia!J29,"R"),EXACT(Asistencia!J29,"DL"),EXACT(Asistencia!J29,"FL"),EXACT(Asistencia!J29,"FE"),EXACT(Asistencia!J29,"PCS"),EXACT(Asistencia!J29,"V")),1,0) -> 0 | AN28: =IF(OR(EXACT(Asistencia!K29,"A"),EXACT(Asistencia!K29,"R"),EXACT(Asistencia!K29,"DL"),EXACT(Asistencia!K29,"FL"),EXACT(Asistencia!K29,"FE"),EXACT(Asistencia!K29,"PCS"),EXACT(Asistencia!K29,"V")),1,0) -> 0 | AO28: =IF(OR(EXACT(Asistencia!L29,"A"),EXACT(Asistencia!L29,"R"),EXACT(Asistencia!L29,"DL"),EXACT(Asistencia!L29,"FL"),EXACT(Asistencia!L29,"FE"),EXACT(Asistencia!L29,"PCS"),EXACT(Asistencia!L29,"V")),1,0) -> 0 | AP28: =SUM(AI28:AO28) -> 0 | AQ28: =IF(EXACT(Asistencia!F29,"FL"),1,0) -> 0 | AR28: =IF(EXACT(Asistencia!G29,"FL"),1,0) -> 0 | AS28: =IF(EXACT(Asistencia!H29,"FL"),1,0) -> 0 | AT28: =IF(EXACT(Asistencia!I29,"FL"),1,0) -> 0 | AU28: =IF(EXACT(Asistencia!J29,"FL"),1,0) -> 0 | AV28: =IF(EXACT(Asistencia!K29,"FL"),1,0) -> 0 | AW28: =IF(EXACT(Asistencia!L29,"FL"),1,0) -> 0 | AX28: =SUM(AQ28:AW28) -> 0 | AY28: =IF(EXACT(Asistencia!F29,"DL"),1,0) -> 0 | AZ28: =IF(EXACT(Asistencia!G29,"DL"),1,0) -> 0 | BA28: =IF(EXACT(Asistencia!H29,"DL"),1,0) -> 0 | BB28: =IF(EXACT(Asistencia!I29,"DL"),1,0) -> 0 | BC28: =IF(EXACT(Asistencia!J29,"DL"),1,0) -> 0 | BD28: =IF(EXACT(Asistencia!K29,"DL"),1,0) -> 0 | BE28: =IF(EXACT(Asistencia!L29,"DL"),1,0) -> 0 | BF28: =SUM(AY28:BE28) -> 0 | BG28: =IF(ISNUMBER(Asistencia!M29),Asistencia!M29,0) -> 0 | BH28: =IF(ISNUMBER(Asistencia!N29),Asistencia!N29,0) -> 0 | BI28: =IF(ISNUMBER(Asistencia!O29),Asistencia!O29,0) -> 0 | BJ28: =IF(ISNUMBER(Asistencia!P29),Asistencia!P29,0) -> 0 | BK28: =IF(Asistencia!F29="","",Asistencia!F29) | BL28: =IF(Asistencia!G29="","",Asistencia!G29) | BM28: =IF(Asistencia!H29="","",Asistencia!H29) | BN28: =IF(Asistencia!I29="","",Asistencia!I29) | BO28: =IF(Asistencia!J29="","",Asistencia!J29) | BP28: =IF(Asistencia!K29="","",Asistencia!K29) | BQ28: =IF(Asistencia!L29="","",Asistencia!L29)
A29: =IF(Y29="","",INDEX($AB$5:$AB$323,Y29)) | B29: =IF(Y29="","",INDEX($AD$5:$AD$323,Y29)) | E29: =IF($A29="","",_xlfn.TEXTJOIN(" / ",TRUE(),IF(SUMIFS($AP$5:$AP$323,$AA$5:$AA$323,$Z29,$AF$5:$AF$323,"ARMIDA")>0,IFERROR("ARMIDA-"&INDEX($AE$5:$AE$323,MATCH($Z29&"ARMIDA",$AA$5:$AA$323&$AF$5:$AF$323,0)),"ARMIDA"),""),IF(SUMIFS($AP$5:$AP$323,$AA$5:$AA$323,$Z29,$AF$5:$AF$323,"AURIGA")>0,IFERROR("AURIGA-"&INDEX($AE$5:$AE$323,MATCH($Z29&"AURIGA",$AA$5:$AA$323&$AF$5:$AF$323,0)),"AURIGA"),""),IF(SUMIFS($AP$5:$AP$323,$AA$5:$AA$323,$Z29,$AF$5:$AF$323,"AURORA")>0,IFERROR("AURORA-"&INDEX($AE$5:$AE$323,MATCH($Z29&"AURORA",$AA$5:$AA$323&$AF$5:$AF$323,0)),"AURORA"),""),IF(SUMIFS($AP$5:$AP$323,$AA$5:$AA$323,$Z29,$AF$5:$AF$323,"CITICA")>0,IFERROR("CITICA-"&INDEX($AE$5:$AE$323,MATCH($Z29&"CITICA",$AA$5:$AA$323&$AF$5:$AF$323,0)),"CITICA"),""),IF(SUMIFS($AP$5:$AP$323,$AA$5:$AA$323,$Z29,$AF$5:$AF$323,"GM")>0,IFERROR("GM-"&INDEX($AE$5:$AE$323,MATCH($Z29&"GM",$AA$5:$AA$323&$AF$5:$AF$323,0)),"GM"),""),IF(SUMIFS($AP$5:$AP$323,$AA$5:$AA$323,$Z29,$AF$5:$AF$323,"TORRE BALZAK")>0,IFERROR("TORRE BALZAK-"&INDEX($AE$5:$AE$323,MATCH($Z29&"TORRE BALZAK",$AA$5:$AA$323&$AF$5:$AF$323,0)),"TORRE BALZAK"),""),IF(SUMIFS($AP$5:$AP$323,$AA$5:$AA$323,$Z29,$AF$5:$AF$323,"TORRE OLMA")>0,IFERROR("TORRE OLMA-"&INDEX($AE$5:$AE$323,MATCH($Z29&"TORRE OLMA",$AA$5:$AA$323&$AF$5:$AF$323,0)),"TORRE OLMA"),""),IF(SUMIFS($AP$5:$AP$323,$AA$5:$AA$323,$Z29,$AF$5:$AF$323,"OTROS")>0,IFERROR("OTROS-"&INDEX($AE$5:$AE$323,MATCH($Z29&"OTROS",$AA$5:$AA$323&$AF$5:$AF$323,0)),"OTROS"),""))) | F29: =IF($A29="","",IFERROR(INDEX($BK$5:$BK$323,MATCH($Z29,$AA$5:$AA$323,0)),"-")) | G29: =IF($A29="","",IFERROR(INDEX($BL$5:$BL$323,MATCH($Z29,$AA$5:$AA$323,0)),"-")) | H29: =IF($A29="","",IFERROR(INDEX($BM$5:$BM$323,MATCH($Z29,$AA$5:$AA$323,0)),"-")) | I29: =IF($A29="","",IFERROR(INDEX($BN$5:$BN$323,MATCH($Z29,$AA$5:$AA$323,0)),"-")) | J29: =IF($A29="","",IFERROR(INDEX($BO$5:$BO$323,MATCH($Z29,$AA$5:$AA$323,0)),"-")) | K29: =IF($A29="","",IFERROR(INDEX($BP$5:$BP$323,MATCH($Z29,$AA$5:$AA$323,0)),"-")) | L29: =IF($A29="","",IFERROR(INDEX($BQ$5:$BQ$323,MATCH($Z29,$AA$5:$AA$323,0)),"-")) | M29: =IF($A29="","",(--(SUMIF($AA$5:$AA$323,$Z29,$AI$5:$AI$323)>0))+(--(SUMIF($AA$5:$AA$323,$Z29,$AJ$5:$AJ$323)>0))+(--(SUMIF($AA$5:$AA$323,$Z29,$AK$5:$AK$323)>0))+(--(SUMIF($AA$5:$AA$323,$Z29,$AL$5:$AL$323)>0))+(--(SUMIF($AA$5:$AA$323,$Z29,$AM$5:$AM$323)>0))+(--(SUMIF($AA$5:$AA$323,$Z29,$AN$5:$AN$323)>0))+(--(SUMIF($AA$5:$AA$323,$Z29,$AO$5:$AO$323)>0))) | N29: =IF($A29="","",MAX(0,M29-6)) | O29: =IF($A29="","",SUMIF($AA$5:$AA$323,$Z29,$AP$5:$AP$323)-M29) | P29: =IF($A29="","",SUMIF($AA$5:$AA$323,$Z29,$BG$5:$BG$323)) | Q29: =IF($A29="","",SUMIF($AA$5:$AA$323,$Z29,$BH$5:$BH$323)) | R29: =IF($A29="","",SUMIF($AA$5:$AA$323,$Z29,$BI$5:$BI$323)) | U29: =IF($A29="","",SUMIF($AA$5:$AA$323,$Z29,$BJ$5:$BJ$323)) | W29: =IF($A29="","",_xlfn.TEXTJOIN(" | ",TRUE(),IF(N29>0,"+ de 6 días: revisar adicionales",""),IF(O29>0,"Doble evento mismo día: revisar turno/pago",""),IF(SUMIF($AA$5:$AA$323,$Z29,$AX$5:$AX$323)>((--(SUMIF($AA$5:$AA$323,$Z29,$AQ$5:$AQ$323)>0))+(--(SUMIF($AA$5:$AA$323,$Z29,$AR$5:$AR$323)>0))+(--(SUMIF($AA$5:$AA$323,$Z29,$AS$5:$AS$323)>0))+(--(SUMIF($AA$5:$AA$323,$Z29,$AT$5:$AT$323)>0))+(--(SUMIF($AA$5:$AA$323,$Z29,$AU$5:$AU$323)>0))+(--(SUMIF($AA$5:$AA$323,$Z29,$AV$5:$AV$323)>0))+(--(SUMIF($AA$5:$AA$323,$Z29,$AW$5:$AW$323)>0))),"FL múltiple mismo día: revisar pago festivo",""),IF(SUMIF($AA$5:$AA$323,$Z29,$BF$5:$BF$323)>((--(SUMIF($AA$5:$AA$323,$Z29,$AY$5:$AY$323)>0))+(--(SUMIF($AA$5:$AA$323,$Z29,$AZ$5:$AZ$323)>0))+(--(SUMIF($AA$5:$AA$323,$Z29,$BA$5:$BA$323)>0))+(--(SUMIF($AA$5:$AA$323,$Z29,$BB$5:$BB$323)>0))+(--(SUMIF($AA$5:$AA$323,$Z29,$BC$5:$BC$323)>0))+(--(SUMIF($AA$5:$AA$323,$Z29,$BD$5:$BD$323)>0))+(--(SUMIF($AA$5:$AA$323,$Z29,$BE$5:$BE$323)>0))),"DL múltiple mismo día: revisar pago descanso",""))) | Y29: =IFERROR(MATCH(25,$AH$5:$AH$323,0),"") | Z29: =IF(Y29="","",INDEX($AA$5:$AA$323,Y29)) | AA29: =IF(AC29="","","M:"&AC29) | AB29: =IF(Asistencia!A30="","",Asistencia!A30) | AC29: =IF(Asistencia!A30="","",SUBSTITUTE(SUBSTITUTE(SUBSTITUTE(SUBSTITUTE(SUBSTITUTE(SUBSTITUTE(SUBSTITUTE(UPPER(TRIM(Asistencia!A30)),"Á","A"),"É","E"),"Í","I"),"Ó","O"),"Ú","U"),"Ñ","N")," "," ")) | AD29: =IF(Asistencia!E30="","",Asistencia!E30) | AE29: =IF(Asistencia!D30="","",UPPER(TRIM(Asistencia!D30))) | AF29: ARMIDA | AG29: =IF(AND(AA29<>"",COUNTIF($AA$5:AA29,AA29)=1),1,0) -> 0 | AH29: =IF(AG29=1,SUM($AG$5:AG29),"") | AI29: =IF(OR(EXACT(Asistencia!F30,"A"),EXACT(Asistencia!F30,"R"),EXACT(Asistencia!F30,"DL"),EXACT(Asistencia!F30,"FL"),EXACT(Asistencia!F30,"FE"),EXACT(Asistencia!F30,"PCS"),EXACT(Asistencia!F30,"V")),1,0) -> 0 | AJ29: =IF(OR(EXACT(Asistencia!G30,"A"),EXACT(Asistencia!G30,"R"),EXACT(Asistencia!G30,"DL"),EXACT(Asistencia!G30,"FL"),EXACT(Asistencia!G30,"FE"),EXACT(Asistencia!G30,"PCS"),EXACT(Asistencia!G30,"V")),1,0) -> 0 | AK29: =IF(OR(EXACT(Asistencia!H30,"A"),EXACT(Asistencia!H30,"R"),EXACT(Asistencia!H30,"DL"),EXACT(Asistencia!H30,"FL"),EXACT(Asistencia!H30,"FE"),EXACT(Asistencia!H30,"PCS"),EXACT(Asistencia!H30,"V")),1,0) -> 0 | AL29: =IF(OR(EXACT(Asistencia!I30,"A"),EXACT(Asistencia!I30,"R"),EXACT(Asistencia!I30,"DL"),EXACT(Asistencia!I30,"FL"),EXACT(Asistencia!I30,"FE"),EXACT(Asistencia!I30,"PCS"),EXACT(Asistencia!I30,"V")),1,0) -> 0 | AM29: =IF(OR(EXACT(Asistencia!J30,"A"),EXACT(Asistencia!J30,"R"),EXACT(Asistencia!J30,"DL"),EXACT(Asistencia!J30,"FL"),EXACT(Asistencia!J30,"FE"),EXACT(Asistencia!J30,"PCS"),EXACT(Asistencia!J30,"V")),1,0) -> 0 | AN29: =IF(OR(EXACT(Asistencia!K30,"A"),EXACT(Asistencia!K30,"R"),EXACT(Asistencia!K30,"DL"),EXACT(Asistencia!K30,"FL"),EXACT(Asistencia!K30,"FE"),EXACT(Asistencia!K30,"PCS"),EXACT(Asistencia!K30,"V")),1,0) -> 0 | AO29: =IF(OR(EXACT(Asistencia!L30,"A"),EXACT(Asistencia!L30,"R"),EXACT(Asistencia!L30,"DL"),EXACT(Asistencia!L30,"FL"),EXACT(Asistencia!L30,"FE"),EXACT(Asistencia!L30,"PCS"),EXACT(Asistencia!L30,"V")),1,0) -> 0 | AP29: =SUM(AI29:AO29) -> 0 | AQ29: =IF(EXACT(Asistencia!F30,"FL"),1,0) -> 0 | AR29: =IF(EXACT(Asistencia!G30,"FL"),1,0) -> 0 | AS29: =IF(EXACT(Asistencia!H30,"FL"),1,0) -> 0 | AT29: =IF(EXACT(Asistencia!I30,"FL"),1,0) -> 0 | AU29: =IF(EXACT(Asistencia!J30,"FL"),1,0) -> 0 | AV29: =IF(EXACT(Asistencia!K30,"FL"),1,0) -> 0 | AW29: =IF(EXACT(Asistencia!L30,"FL"),1,0) -> 0 | AX29: =SUM(AQ29:AW29) -> 0 | AY29: =IF(EXACT(Asistencia!F30,"DL"),1,0) -> 0 | AZ29: =IF(EXACT(Asistencia!G30,"DL"),1,0) -> 0 | BA29: =IF(EXACT(Asistencia!H30,"DL"),1,0) -> 0 | BB29: =IF(EXACT(Asistencia!I30,"DL"),1,0) -> 0 | BC29: =IF(EXACT(Asistencia!J30,"DL"),1,0) -> 0 | BD29: =IF(EXACT(Asistencia!K30,"DL"),1,0) -> 0 | BE29: =IF(EXACT(Asistencia!L30,"DL"),1,0) -> 0 | BF29: =SUM(AY29:BE29) -> 0 | BG29: =IF(ISNUMBER(Asistencia!M30),Asistencia!M30,0) -> 0 | BH29: =IF(ISNUMBER(Asistencia!N30),Asistencia!N30,0) -> 0 | BI29: =IF(ISNUMBER(Asistencia!O30),Asistencia!O30,0) -> 0 | BJ29: =IF(ISNUMBER(Asistencia!P30),Asistencia!P30,0) -> 0 | BK29: =IF(Asistencia!F30="","",Asistencia!F30) | BL29: =IF(Asistencia!G30="","",Asistencia!G30) | BM29: =IF(Asistencia!H30="","",Asistencia!H30) | BN29: =IF(Asistencia!I30="","",Asistencia!I30) | BO29: =IF(Asistencia!J30="","",Asistencia!J30) | BP29: =IF(Asistencia!K30="","",Asistencia!K30) | BQ29: =IF(Asistencia!L30="","",Asistencia!L30)
A30: =IF(Y30="","",INDEX($AB$5:$AB$323,Y30)) | B30: =IF(Y30="","",INDEX($AD$5:$AD$323,Y30)) | E30: =IF($A30="","",_xlfn.TEXTJOIN(" / ",TRUE(),IF(SUMIFS($AP$5:$AP$323,$AA$5:$AA$323,$Z30,$AF$5:$AF$323,"ARMIDA")>0,IFERROR("ARMIDA-"&INDEX($AE$5:$AE$323,MATCH($Z30&"ARMIDA",$AA$5:$AA$323&$AF$5:$AF$323,0)),"ARMIDA"),""),IF(SUMIFS($AP$5:$AP$323,$AA$5:$AA$323,$Z30,$AF$5:$AF$323,"AURIGA")>0,IFERROR("AURIGA-"&INDEX($AE$5:$AE$323,MATCH($Z30&"AURIGA",$AA$5:$AA$323&$AF$5:$AF$323,0)),"AURIGA"),""),IF(SUMIFS($AP$5:$AP$323,$AA$5:$AA$323,$Z30,$AF$5:$AF$323,"AURORA")>0,IFERROR("AURORA-"&INDEX($AE$5:$AE$323,MATCH($Z30&"AURORA",$AA$5:$AA$323&$AF$5:$AF$323,0)),"AURORA"),""),IF(SUMIFS($AP$5:$AP$323,$AA$5:$AA$323,$Z30,$AF$5:$AF$323,"CITICA")>0,IFERROR("CITICA-"&INDEX($AE$5:$AE$323,MATCH($Z30&"CITICA",$AA$5:$AA$323&$AF$5:$AF$323,0)),"CITICA"),""),IF(SUMIFS($AP$5:$AP$323,$AA$5:$AA$323,$Z30,$AF$5:$AF$323,"GM")>0,IFERROR("GM-"&INDEX($AE$5:$AE$323,MATCH($Z30&"GM",$AA$5:$AA$323&$AF$5:$AF$323,0)),"GM"),""),IF(SUMIFS($AP$5:$AP$323,$AA$5:$AA$323,$Z30,$AF$5:$AF$323,"TORRE BALZAK")>0,IFERROR("TORRE BALZAK-"&INDEX($AE$5:$AE$323,MATCH($Z30&"TORRE BALZAK",$AA$5:$AA$323&$AF$5:$AF$323,0)),"TORRE BALZAK"),""),IF(SUMIFS($AP$5:$AP$323,$AA$5:$AA$323,$Z30,$AF$5:$AF$323,"TORRE OLMA")>0,IFERROR("TORRE OLMA-"&INDEX($AE$5:$AE$323,MATCH($Z30&"TORRE OLMA",$AA$5:$AA$323&$AF$5:$AF$323,0)),"TORRE OLMA"),""),IF(SUMIFS($AP$5:$AP$323,$AA$5:$AA$323,$Z30,$AF$5:$AF$323,"OTROS")>0,IFERROR("OTROS-"&INDEX($AE$5:$AE$323,MATCH($Z30&"OTROS",$AA$5:$AA$323&$AF$5:$AF$323,0)),"OTROS"),""))) | F30: =IF($A30="","",IFERROR(INDEX($BK$5:$BK$323,MATCH($Z30,$AA$5:$AA$323,0)),"-")) | G30: =IF($A30="","",IFERROR(INDEX($BL$5:$BL$323,MATCH($Z30,$AA$5:$AA$323,0)),"-")) | H30: =IF($A30="","",IFERROR(INDEX($BM$5:$BM$323,MATCH($Z30,$AA$5:$AA$323,0)),"-")) | I30: =IF($A30="","",IFERROR(INDEX($BN$5:$BN$323,MATCH($Z30,$AA$5:$AA$323,0)),"-")) | J30: =IF($A30="","",IFERROR(INDEX($BO$5:$BO$323,MATCH($Z30,$AA$5:$AA$323,0)),"-")) | K30: =IF($A30="","",IFERROR(INDEX($BP$5:$BP$323,MATCH($Z30,$AA$5:$AA$323,0)),"-")) | L30: =IF($A30="","",IFERROR(INDEX($BQ$5:$BQ$323,MATCH($Z30,$AA$5:$AA$323,0)),"-")) | M30: =IF($A30="","",(--(SUMIF($AA$5:$AA$323,$Z30,$AI$5:$AI$323)>0))+(--(SUMIF($AA$5:$AA$323,$Z30,$AJ$5:$AJ$323)>0))+(--(SUMIF($AA$5:$AA$323,$Z30,$AK$5:$AK$323)>0))+(--(SUMIF($AA$5:$AA$323,$Z30,$AL$5:$AL$323)>0))+(--(SUMIF($AA$5:$AA$323,$Z30,$AM$5:$AM$323)>0))+(--(SUMIF($AA$5:$AA$323,$Z30,$AN$5:$AN$323)>0))+(--(SUMIF($AA$5:$AA$323,$Z30,$AO$5:$AO$323)>0))) | N30: =IF($A30="","",MAX(0,M30-6)) | O30: =IF($A30="","",SUMIF($AA$5:$AA$323,$Z30,$AP$5:$AP$323)-M30) | P30: =IF($A30="","",SUMIF($AA$5:$AA$323,$Z30,$BG$5:$BG$323)) | Q30: =IF($A30="","",SUMIF($AA$5:$AA$323,$Z30,$BH$5:$BH$323)) | R30: =IF($A30="","",SUMIF($AA$5:$AA$323,$Z30,$BI$5:$BI$323)) | U30: =IF($A30="","",SUMIF($AA$5:$AA$323,$Z30,$BJ$5:$BJ$323)) | W30: =IF($A30="","",_xlfn.TEXTJOIN(" | ",TRUE(),IF(N30>0,"+ de 6 días: revisar adicionales",""),IF(O30>0,"Doble evento mismo día: revisar turno/pago",""),IF(SUMIF($AA$5:$AA$323,$Z30,$AX$5:$AX$323)>((--(SUMIF($AA$5:$AA$323,$Z30,$AQ$5:$AQ$323)>0))+(--(SUMIF($AA$5:$AA$323,$Z30,$AR$5:$AR$323)>0))+(--(SUMIF($AA$5:$AA$323,$Z30,$AS$5:$AS$323)>0))+(--(SUMIF($AA$5:$AA$323,$Z30,$AT$5:$AT$323)>0))+(--(SUMIF($AA$5:$AA$323,$Z30,$AU$5:$AU$323)>0))+(--(SUMIF($AA$5:$AA$323,$Z30,$AV$5:$AV$323)>0))+(--(SUMIF($AA$5:$AA$323,$Z30,$AW$5:$AW$323)>0))),"FL múltiple mismo día: revisar pago festivo",""),IF(SUMIF($AA$5:$AA$323,$Z30,$BF$5:$BF$323)>((--(SUMIF($AA$5:$AA$323,$Z30,$AY$5:$AY$323)>0))+(--(SUMIF($AA$5:$AA$323,$Z30,$AZ$5:$AZ$323)>0))+(--(SUMIF($AA$5:$AA$323,$Z30,$BA$5:$BA$323)>0))+(--(SUMIF($AA$5:$AA$323,$Z30,$BB$5:$BB$323)>0))+(--(SUMIF($AA$5:$AA$323,$Z30,$BC$5:$BC$323)>0))+(--(SUMIF($AA$5:$AA$323,$Z30,$BD$5:$BD$323)>0))+(--(SUMIF($AA$5:$AA$323,$Z30,$BE$5:$BE$323)>0))),"DL múltiple mismo día: revisar pago descanso",""))) | Y30: =IFERROR(MATCH(26,$AH$5:$AH$323,0),"") | Z30: =IF(Y30="","",INDEX($AA$5:$AA$323,Y30)) | AA30: =IF(AC30="","","M:"&AC30) | AB30: =IF(Asistencia!A31="","",Asistencia!A31) | AC30: =IF(Asistencia!A31="","",SUBSTITUTE(SUBSTITUTE(SUBSTITUTE(SUBSTITUTE(SUBSTITUTE(SUBSTITUTE(SUBSTITUTE(UPPER(TRIM(Asistencia!A31)),"Á","A"),"É","E"),"Í","I"),"Ó","O"),"Ú","U"),"Ñ","N")," "," ")) | AD30: =IF(Asistencia!E31="","",Asistencia!E31) | AE30: =IF(Asistencia!D31="","",UPPER(TRIM(Asistencia!D31))) | AF30: ARMIDA | AG30: =IF(AND(AA30<>"",COUNTIF($AA$5:AA30,AA30)=1),1,0) -> 0 | AH30: =IF(AG30=1,SUM($AG$5:AG30),"") | AI30: =IF(OR(EXACT(Asistencia!F31,"A"),EXACT(Asistencia!F31,"R"),EXACT(Asistencia!F31,"DL"),EXACT(Asistencia!F31,"FL"),EXACT(Asistencia!F31,"FE"),EXACT(Asistencia!F31,"PCS"),EXACT(Asistencia!F31,"V")),1,0) -> 0 | AJ30: =IF(OR(EXACT(Asistencia!G31,"A"),EXACT(Asistencia!G31,"R"),EXACT(Asistencia!G31,"DL"),EXACT(Asistencia!G31,"FL"),EXACT(Asistencia!G31,"FE"),EXACT(Asistencia!G31,"PCS"),EXACT(Asistencia!G31,"V")),1,0) -> 0 | AK30: =IF(OR(EXACT(Asistencia!H31,"A"),EXACT(Asistencia!H31,"R"),EXACT(Asistencia!H31,"DL"),EXACT(Asistencia!H31,"FL"),EXACT(Asistencia!H31,"FE"),EXACT(Asistencia!H31,"PCS"),EXACT(Asistencia!H31,"V")),1,0) -> 0 | AL30: =IF(OR(EXACT(Asistencia!I31,"A"),EXACT(Asistencia!I31,"R"),EXACT(Asistencia!I31,"DL"),EXACT(Asistencia!I31,"FL"),EXACT(Asistencia!I31,"FE"),EXACT(Asistencia!I31,"PCS"),EXACT(Asistencia!I31,"V")),1,0) -> 0 | AM30: =IF(OR(EXACT(Asistencia!J31,"A"),EXACT(Asistencia!J31,"R"),EXACT(Asistencia!J31,"DL"),EXACT(Asistencia!J31,"FL"),EXACT(Asistencia!J31,"FE"),EXACT(Asistencia!J31,"PCS"),EXACT(Asistencia!J31,"V")),1,0) -> 0 | AN30: =IF(OR(EXACT(Asistencia!K31,"A"),EXACT(Asistencia!K31,"R"),EXACT(Asistencia!K31,"DL"),EXACT(Asistencia!K31,"FL"),EXACT(Asistencia!K31,"FE"),EXACT(Asistencia!K31,"PCS"),EXACT(Asistencia!K31,"V")),1,0) -> 0 | AO30: =IF(OR(EXACT(Asistencia!L31,"A"),EXACT(Asistencia!L31,"R"),EXACT(Asistencia!L31,"DL"),EXACT(Asistencia!L31,"FL"),EXACT(Asistencia!L31,"FE"),EXACT(Asistencia!L31,"PCS"),EXACT(Asistencia!L31,"V")),1,0) -> 0 | AP30: =SUM(AI30:AO30) -> 0 | AQ30: =IF(EXACT(Asistencia!F31,"FL"),1,0) -> 0 | AR30: =IF(EXACT(Asistencia!G31,"FL"),1,0) -> 0 | AS30: =IF(EXACT(Asistencia!H31,"FL"),1,0) -> 0 | AT30: =IF(EXACT(Asistencia!I31,"FL"),1,0) -> 0 | AU30: =IF(EXACT(Asistencia!J31,"FL"),1,0) -> 0 | AV30: =IF(EXACT(Asistencia!K31,"FL"),1,0) -> 0 | AW30: =IF(EXACT(Asistencia!L31,"FL"),1,0) -> 0 | AX30: =SUM(AQ30:AW30) -> 0 | AY30: =IF(EXACT(Asistencia!F31,"DL"),1,0) -> 0 | AZ30: =IF(EXACT(Asistencia!G31,"DL"),1,0) -> 0 | BA30: =IF(EXACT(Asistencia!H31,"DL"),1,0) -> 0 | BB30: =IF(EXACT(Asistencia!I31,"DL"),1,0) -> 0 | BC30: =IF(EXACT(Asistencia!J31,"DL"),1,0) -> 0 | BD30: =IF(EXACT(Asistencia!K31,"DL"),1,0) -> 0 | BE30: =IF(EXACT(Asistencia!L31,"DL"),1,0) -> 0 | BF30: =SUM(AY30:BE30) -> 0 | BG30: =IF(ISNUMBER(Asistencia!M31),Asistencia!M31,0) -> 0 | BH30: =IF(ISNUMBER(Asistencia!N31),Asistencia!N31,0) -> 0 | BI30: =IF(ISNUMBER(Asistencia!O31),Asistencia!O31,0) -> 0 | BJ30: =IF(ISNUMBER(Asistencia!P31),Asistencia!P31,0) -> 0 | BK30: =IF(Asistencia!F31="","",Asistencia!F31) | BL30: =IF(Asistencia!G31="","",Asistencia!G31) | BM30: =IF(Asistencia!H31="","",Asistencia!H31) | BN30: =IF(Asistencia!I31="","",Asistencia!I31) | BO30: =IF(Asistencia!J31="","",Asistencia!J31) | BP30: =IF(Asistencia!K31="","",Asistencia!K31) | BQ30: =IF(Asistencia!L31="","",Asistencia!L31)
